Workbook

Sheet Key ID1
A1: Questions | B1: Latent Variable
A3: Qu1 | B3: Name
A4: Qu2 | B4: Occuption/Role
A5: Qu3 | B5: Email Address
A6: Qu4 | B6: How many people report to you?
A7: Qu5 | B7: Telephone Number
A8: Qu6 | B8: Name of Organisation
A9: Qu7 | B9: How long have you been this organisation for?
A10: Qu8 | B10: Who do you report to?
A11: Qu9 | B11: What is your age?
A12: Qu10 | B12: What is your educational qualification?
A13: Qu11 | B13: How many years of experience do you have in the financial industry
A14: Qu12 | B14: Categorize your Bank in terms of size
A15: Questions | B15: Latent Variable | D15: Strongly Agree | E15: Agree | F15: Somewhat Agree | G15: Neutral | H15: Somewhat Disagree | I15: Disagree | J15: StronglyDisagree
D16: 1 | E16: 2 | F16: 3 | G16: 4 | H16: 5 | I16: 6 | J16: 7
A17: Qu13 | B17: Section A | C17: This bank can be characterised as possessing an adequate risk management framework
A18: Qu14 | C18: Current bank governance policies priorities the need of stakeholders (i.e. government, creditors, depositors, taxpayers)
A19: Qu15 | C19: Outsiders' (e.g investor) and other stakeholders' (e.g. government, creditors, depositors, taxpayers) have influence over senior management
A20: Qu16 | C20: Managers in this bank tend to stair towards risk adverse investment
A21: Qu17 | C21: The board is capable of solving complex issues which is represented in management activities of this bank
A22: Qu18 | C22: Members of the boards of the Directors in this bank are financial experts
A23: Qu19 | C23: This bank exhibits proper risk management departments and possesses a Chief Risk Officer that report to the board
A24: Qu20 | C24: The audit committee board rather than board is responsible for this banks risk management function
A25: Qu21 | C25: The audit committees in this banks may not posses the adequate expertise to interpret complex risk management issues in the banking industry
A26: Qu22 | C26: The audit committees in this banks is subject to undue influence by executive management
A27: Qu23 | C27: Do you have any general comments on any issues raised in this session? (Optional)
A28: Questions | B28: Latent Variable | D28: Strongly Agree | E28: Agree | F28: Somewhat Agree | G28: Neutral | H28: Somewhat Disagree | I28: Disagree | J28: StronglyDisagree
D29: 1 | E29: 2 | F29: 3 | G29: 4 | H29: 5 | I29: 6 | J29: 7
A30: Qu24 | B30: Section B | C30: This bank is characterised by lack of information transparency
A31: Qu25 | C31: There are falsification of financial statements to regulatory authorities in this this bank
A32: Qu26 | C32: It is challenging for this banks to implement effective corporate governance mechanisms to mitigate the risk.
A33: Qu27 | C33: The Board of Directors lack monitoring and oversight of this banks' managers
A34: Qu28 | C34: This banks' directors is characterised with lack of expertise
A35: Qu29 | C35: This banks' directors is characterised with lack of expertise due to influence by the concentrated ownership structures of this banks shareholders
A36: Qu30 | C36: Unjust enrichment is prevalent through the use of Special Purpose Vehicles (SPV) to misuse depositors' funds
A37: Qu31 | C37: Managers engage in self-interested behaviour that may be detrimental to the survival of this bank
A38: Qu32 | C38: Adverse selection of borrowers is a feature of this bank
A39: Qu33 | C39: This Bank attempts to lure consumers away from competitors by offering lower interest rates, leading to an overall decrease in the quality of the loan portfolio
A40: Qu34 | C40: Do you have any general comments on any issues raised in this session? (Optional)
A41: Questions | B41: Latent Variable | D41: Strongly Agree | E41: Agree | F41: Somewhat Agree | G41: Neutral | H41: Somewhat Disagree | I41: Disagree | J41: StronglyDisagree
D42: 1 | E42: 2 | F42: 3 | G42: 4 | H42: 5 | I42: 6 | J42: 7
A43: Qu35 | B43: Section C | C43: banking regulations are enforced effectively in this bank
A44: Qu36 | C44: Nigeria lacks an effective judicial system to enforce banking regulations
A45: Qu37 | C45: Corporate governance guidelines are clear within you bank and outline acceptable employee conduct in particular scenarios
A46: Qu38 | C46: corporate governance legislation reflects the country's specific needs
A47: Qu39 | C47: There is confusion resulting from the abundance of corporate governance codes in the country
A48: Qu40 | C48: Multiple self-reyulatory codes creates an environment of uncertainty and lack of cohesion in the banking industry
A49: Qu41 | C49: Abundance of governance codes leads to uncertainty, weak enforcement and difficulty in distinguishing between banks that comply with good governance practice and those that do not
A50: Questions | B50: Latent Variable
A52: Qu42 | B52: Section D | C52: How many directors does your company have in the board?
A53: Qu43 | C53: How many of these directors are inside directors in the board
A54: Qu44 | C54: How many of these directors are outside directors in the board
A55: Qu45 | C55: The audit process in this bank is transparent
A56: Qu46 | C56: The board of directors hold themselves accountable in regards to corporate governance practices
A57: Qu47 | C57: Does your company comply with more than one corporate governance code and why
A58: Qu48 | C58: If yes to question above, Do the codes conflict and how?
A59: Qu49 | C59: How many committees (ie nomination committee, audit committee) does your bank have?
A60: Qu50 | C60: What are the names of the Banks board committees?
A61: Qu51 | C61: Who is in charge of your board?
A62: Qu52 | C62: How do you describe the ownership structure and control of your company?

Sheet Data
F1: Name | G1: Role | H1: Email address | I1: report | J1: telephone | K1: Organization | L1: Organization for | M1: report to | N1: Age | O1: qualification | P1: industry | Q1: size | R1: framework | S1: need of stokeholders | T1: other stokeholder | U1: investment | V1: bank | W1: experts | X1: board | Y1: function | Z1: industry | AA1: executive | AB1: session | AC1: transparency | AD1: bank | AE1: risk | AF1: managers | AG1: expertise | AH1: shareholders | AI1: funds | AJ1: bank | AK1: bank | AL1: portfolio | AM1: session | AN1: bank | AO1: regulations | AP1: scenarios | AQ1: needs | AR1: country | AS1: industry | AT1: do not | AU1: board | AV1: board | AW1: board | AX1: transparent | AY1: practices | AZ1: why | BA1: how | BB1: have | BC1: committess | BD1: board | BE1: company | BF1: session
A2: id | B2: age | C2: sex | D2: race | E2: Drive link | F2: qu1 | G2: qu2 | H2: qu3 | I2: qu4 | J2: qu5 | K2: qu6 | L2: qu7 | M2: qu8 | N2: qu9 | O2: qu10 | P2: qu11 | Q2: qu12 | R2: qu13 | S2: qu14 | T2: qu15 | U2: qu16 | V2: qu17 | W2: qu18 | X2: qu19 | Y2: qu20 | Z2: qu21 | AA2: qu22 | AB2: qu23 | AC2: qu24 | AD2: qu25 | AE2: qu26 | AF2: qu27 | AG2: qu28 | AH2: qu29 | AI2: qu30 | AJ2: qu31 | AK2: qu32 | AL2: qu33 | AM2: qu34 | AN2: qu35 | AO2: qu36 | AP2: qu37 | AQ2: qu38 | AR2: qu39 | AS2: qu40 | AT2: qu41 | AU2: qu42 | AV2: qu43 | AW2: qu44 | AX2: qu45 | AY2: qu46 | AZ2: qu47 | BA2: qu48 | BB2: qu49 | BC2: qu50 | BD2: qu51 | BE2: qu52 | BF2: qu53 | BG2: TotalScore
A3: 1 | B3: 49 | C3: Male | D3: White | E3: https://drive.google.com/file/d/1SzQpU-GBDh9NQXRQCviozvk0aTvXbauj/view?usp=sharing | G3: Banker | K3: Keystone Bank | L3: 8 years | M3: Branch Manager | N3: 42 years | O3: Degree plus professional certificates | P3: 9 years | Q3: Large (Between $xx and $xx) | R3: Strongly Agree | S3: Somewhat Agree | T3: Somewhat Agree | U3: Agree | V3: Agree | W3: Agree | X3: Agree | Y3: Agree | Z3: Agree | AA3: Agree | AC3: StronglyDisagree | AD3: Disagree | AE3: Disagree | AF3: Disagree | AG3: Disagree | AH3: Disagree | AI3: StronglyDisagree | AJ3: Disagree | AK3: Disagree | AL3: Disagree | AN3: StronglyAgree | AO3: StronglyDisagree | AP3: Somewhat Agree | AQ3: Agree | AR3: Neutral | AS3: Neutral | AT3: Somewhat Agree | AZ3: No | BB3: 5 | BD3: CEO | BE3: The largest sharaholders hes substantial voting right [for example above 35%) effectively controlling the company | BF3: No | BG3: 54
A4: 2 | B4: 52 | C4: Female | D4: White | E4: https://drive.google.com/file/d/1jzXgC_tUgQJavEgaW-YID0nIicFFzntr/view?usp=drive_link | G4: Banker / Customer | I4: None | K4: Zenith Bank | L4: 3 years | M4: Supervisor | N4: 28 years | O4: HND holder | P4: 3 years | Q4: Large (Between $xx and $xx) | R4: Strongly Agree | S4: Somewhat Agree | T4: Somewhat Disagree | U4: Disagree | V4: Agree | W4: Strongly Agree | X4: Strongly Agree | Y4: Somewhat Agree | Z4: Disagree | AA4: Somewhat Disagree | AB4: No | AC4: Disagree | AD4: Strongly Disagree | AE4: Somewhat Disagree | AF4: Strongly Disagree | AG4: Strongly Disagree | AH4: Disagree | AI4: Disagree | AJ4: Disagree | AK4: Somewhat Disagree | AL4: Somewhat Disagree | AM4: No | AN4: StronglyAgree | AO4: Somewhat Disagree | AP4: Agree | AQ4: Agree | AR4: Somewhat Disagree | AS4: Neutral | AT4: Neutral | AU4: 12 | AV4: 4 | AW4: 8 | AX4: Extremely High | AY4: Extremely High | AZ4: No | BB4: 5 | BC4: Jnn Ovia, Dame Adata, henry Orah, Adobi Ncopa | BD4: CEO | BE4: The largest sharaholders hes substantial voting right [for example above 35%) effectively controlling the company | BF4: No | BG4: 55
A5: 3 | B5: 31 | C5: Male | D5: Hispanic | E5: https://drive.google.com/file/d/19FpyhHdq2GSg1lECRpfSpgD0wmFT1tZr/view?usp=drive_link | G5: Banker / sales rep | I5: 7 | K5: United Bank for Africa | L5: 5 years | M5: Manager | N5: 33 years | O5: Degree holder | P5: 5 years | Q5: Large (Between $xx and $xx) | R5: Strongly Agree | S5: Somewhat Agree | T5: Somewhat Disagree | U5: Somewhat Disagree | V5: Agree | W5: Strongly Agree | X5: Agree | Y5: Somewhat Agree | Z5: Somewhat Disagree | AA5: Somewhat Disagree | AB5: No | AC5: Strongly Disagree | AD5: Strongly Disagree | AE5: Somewhat Disagree | AF5: Disagree | AG5: Strongly Disagree | AH5: Somewhat Disagree | AI5: Disagree | AJ5: Disagree | AK5: Somewhat Disagree | AL5: Somewhat Disagree | AM5: No | AN5: StronglyAgree | AO5: Disagree | AP5: StronglyAgree | AQ5: Agree | AR5: Neutral | AS5: Neutral | AT5: Neutral | AU5: 6 | AV5: 4 | AW5: 4 | AX5: Extremely High | AY5: High | AZ5: No | BB5: 5 | BD5: CEO | BE5: The largest sharaholders hes substantial voting right [for example above 35%) effectively controlling the company | BF5: No | BG5: 58
A6: 4 | B6: 28 | C6: Male | D6: Black | E6: https://drive.google.com/file/d/1iiAn9IETN4EZ1mTdLuBNn6RmVhx7cTFu/view?usp=drive_link | G6: Banker | I6: None | K6: UBA | L6: 5 years | M6: Supervisor | N6: 28 years | O6: HND holder | P6: 5 years | Q6: Large (Between $xx and $xx) | R6: Strongly Agree | S6: Somewhat Agree | T6: Somewhat Disagree | U6: Disagree | V6: Strongly Agree | W6: Strongly Agree | X6: Strongly Agree | Y6: Somewhat Disagree | Z6: Strongly Disagree | AA6: Somewhat Disagree | AB6: No | AC6: Disagree | AD6: Disagree | AE6: Somewhat Disagree | AF6: Strongly Disagree | AG6: Strongly Disagree | AH6: Somewhat Disagree | AI6: Disagree | AJ6: Somewhat Disagree | AK6: Disagree | AL6: Disagree | AM6: No | AN6: StronglyAgree | AO6: Disagree | AP6: StronglyAgree | AQ6: Agree | AR6: Neutral | AS6: Somewhat Disagree | AT6: Neutral | AU6: 12 | AV6: 6 | AW6: 4 | AX6: Extremely High | AY6: High | AZ6: No | BB6: 4 | BD6: CEO | BE6: The largest sharaholders hes substantial voting right [for example above 35%) effectively controlling the company | BF6: No | BG6: 62
A7: 5 | B7: 29 | C7: Male | D7: White | E7: https://drive.google.com/file/d/14NfNkcnJxekTz1-U25ccnTT6bTvhl01-/view?usp=drive_link | G7: Banker | I7: None | K7: Zenith Bank | L7: 5 years | M7: Head of Sales | N7: 32 years | O7: HND holder | P7: 5 years | Q7: Large (Between $xx and $xx) | R7: Strongly Agree | S7: Somewhat Agree | T7: Somewhat Disagree | U7: Disagree | V7: Strongly Agree | W7: Strongly Agree | X7: Strongly Agree | Y7: Somewhat Disagree | Z7: Disagree | AA7: Somewhat Disagree | AC7: Strongly Disagree | AD7: Disagree | AE7: Somewhat Disagree | AF7: Strongly Disagree | AG7: Strongly Disagree | AH7: Disagree | AI7: Somewhat Disagree | AJ7: Somewhat Disagree | AK7: Disagree | AL7: Somewhat Disagree | AM7: No | AN7: StronglyAgree | AO7: Disagree | AP7: StronglyAgree | AQ7: Somewhat Agree | AR7: Somewhat Disagree | AS7: Neutral | AT7: Neutral | AU7: 4 | AV7: 4 | AW7: 4 | AX7: Extremely High | AY7: Extremely High | AZ7: No | BB7: 4 | BD7: CEO | BE7: The largest sharaholders hes substantial voting right [for example above 35%) effectively controlling the company | BF7: No | BG7: 62
A8: 6 | B8: 50 | C8: Female | D8: Black | E8: https://drive.google.com/file/d/1fhly88QZnvHzPzfYX8_gJv5wZCLwmOAi/view?usp=drive_link | G8: Banker / Cashier | I8: None | K8: UBA | L8: 3 years | M8: Supervisor | N8: 26 years | O8: HND holder | P8: 3 years | Q8: Large (Between $xx and $xx) | R8: Agree | S8: Neutral | T8: Somewhat Disagree | U8: Disagree | V8: Agree | W8: Strongly Agree | X8: Agree | Y8: Neutral | Z8: Disagree | AA8: Disagree | AB8: No | AC8: StronglyDisagree | AD8: Disagree | AE8: Disagree | AF8: Disagree | AG8: Strongly Disagree | AH8: Somewhat Disagree | AI8: Somewhat Disagree | AJ8: Disagree | AK8: Disagree | AL8: Somewhat Disagree | AM8: No | AN8: StronglyAgree | AO8: Disagree | AP8: Agree | AQ8: Agree | AR8: Neutral | AS8: Neutral | AT8: Neutral | AU8: 4 | AV8: 4 | AW8: 4 | AX8: Extremely High | AY8: High | AZ8: No | BB8: 4 | BC8: Anthony Elumelu, Oluseyi Alawode, Alex Akpese, Muyiwa Akinyemi, Mustapha Atola | BD8: CEO | BE8: The largest sharaholders hes substantial voting right [for example above 35%) effectively controlling the company | BF8: No | BG8: 54
A9: 7 | B9: 31 | C9: Female | D9: White | E9: https://drive.google.com/file/d/1fz6POEMk-BsyshJxMKdLIqGS-y5Sizx7/view?usp=drive_link | G9: Banker / Sales Rep | I9: None | K9: Zenith Bank | L9: 8 years | M9: Operation Manager | N9: 33 years | O9: Degree holder | P9: 8 years | Q9: Large (Between $xx and $xx) | R9: Strongly Agree | S9: Somewhat Agree | T9: Somewhat Disagree | U9: Disagree | V9: Strongly Agree | W9: Strongly Agree | X9: Strongly Agree | Y9: Somewhat Agree | Z9: Somewhat Disagree | AA9: Disagree | AB9: No | AC9: StronglyDisagree | AD9: Disagree | AE9: Somewhat Disagree | AG9: Strongly Disagree | AH9: Strongly Disagree | AI9: Disagree | AJ9: Somewhat Disagree | AK9: Disagree | AL9: Disagree | AM9: No | AU9: 12 | AV9: 8 | AW9: 4 | AX9: Extremely High | AY9: Extremely High | AZ9: No | BB9: 12 | BD9: CEO | BE9: The largest sharaholders hes substantial voting right [for example above 35%) effectively controlling the company | BF9: No | BG9: 49
A10: 8 | B10: 24 | C10: Female | D10: Black | E10: https://drive.google.com/file/d/1nVJYcrhk4-grQEpsZ5cpUr9N-Xrjjocz/view?usp=drive_link | G10: Banker | I10: 2 | K10: Fidelity Bank | L10: 4 years | M10: Supervisor / Manager | N10: 37 years | O10: Degree holder | P10: 6 years | Q10: Large (Between $xx and $xx) | R10: Strongly Agree | S10: Agree | T10: Somewhat Disagree | U10: Disagree | V10: Strongly Agree | W10: Strongly Agree | X10: Agree | Y10: Somewhat Agree | Z10: Disagree | AA10: Disagree | AB10: No | AC10: StronglyDisagree | AD10: Disagree | AE10: Disagree | AF10: Strongly Disagree | AG10: Strongly Disagree | AH10: Strongly Disagree | AI10: Disagree | AJ10: StronglyDisagree | AK10: Somewhat Disagree | AL10: Disagree | AM10: No | AN10: StronglyAgree | AO10: Somewhat Disagree | AP10: StronglyAgree | AQ10: Agree | AR10: Somewhat Disagree | AS10: Neutral | AT10: Neutral | AU10: 12 | AV10: 4 | AW10: 6 | AX10: Extremely High | AY10: High | AZ10: No | BD10: CEO | BE10: The largest sharaholders hes substantial voting right [for example above 35%) effectively controlling the company | BF10: No | BG10: 64
A11: 9 | B11: 32 | C11: Female | D11: Black | E11: https://drive.google.com/file/d/1JOGDKhh9ccjIu1LHkxYX6B51d-E_2Jgt/view?usp=drive_link | F11: Enice Surname (the surname is not clearly legible). | G11: Head Guard | I11: 10 | J11: 0835423361 | K11: UBA | L11: 17 years | M11: Head of Security | N11: 37 years | P11: 11 years | Q11: Medium (Between $xx and $xx) | R11: Agree | S11: Neutral | T11: Disagree | U11: Agree | V11: Agree | W11: Strongly Agree | X11: Agree | Y11: Agree | Z11: Agree | AA11: Agree | AC11: Disagree | AD11: Agree | AE11: Strongly Disagree | AF11: Disagree | AG11: Disagree | AH11: Neutral | AI11: Disagree | AJ11: Agree | AK11: Agree | AL11: Agree | AM11: No | AN11: Agree | AO11: Disagree | AP11: Agree | AQ11: Disagree | AR11: Agree | AS11: Agree | AT11: Neutral | AU11: 6 | AV11: 3 | AW11: 3 | AX11: High | AY11: High | AZ11: Capacity | BB11: 4 | BC11: Manager | BD11: CEO | BE11: The largest sharaholders hes substantial voting right [for example above 35%) effectively controlling the company | BF11: No | BG11: 66
A12: 10 | B12: 33 | C12: Female | D12: White | E12: https://drive.google.com/file/d/1U-fKXCdwbYKETkSD1yug7OVlrNz914qm/view?usp=drive_link | F12: Enric Dechirygle | G12: Head Lead | I12: 4 | J12: 08135423361 | K12: UBA | L12: 11 years | M12: Head of Operations | N12: 37 years | P12: 11 years | Q12: Medium (Between $xx and $xx) | R12: Agree | S12: Neutral | T12: Disagree | U12: Agree | V12: Agree | W12: Strongly Agree | X12: Agree | Y12: Agree | Z12: Agree | AA12: Agree | AC12: Disagree | AD12: Agree | AE12: Strongly Disagree | AF12: Disagree | AG12: Disagree | AH12: Neutral | AI12: Disagree | AJ12: Agree | AK12: Disagree | AL12: Agree | AM12: No | AN12: Agree | AO12: Disagree | AP12: Agree | AQ12: Disagree | AR12: Agree | AS12: Agree | AT12: Neutral | AU12: 6 | AV12: 3 | AW12: 3 | AX12: Extremely High | AY12: High | AZ12: Capacity | BB12: 4 | BC12: Manager | BE12: The largest sharaholders hes substantial voting right [for example above 35%) effectively controlling the company | BF12: No | BG12: 59
A13: 11 | B13: 46 | C13: Female | D13: White | E13: https://drive.google.com/file/d/1J5L6SqQ0gGmkaYLs5PAqOe1hfL6akPyj/view?usp=drive_link | F13: Alexander Jack Obum | G13: Banker / Sales | J13: 08177433803 | K13: Keystone Bank | L13: 2 years | M13: Branch Manager | N13: 29 years | O13: Degree holder | P13: 2 years | Q13: Medium (Between $xx and $xx) | R13: Strongly Agree | S13: Strongly Agree | T13: Agree | U13: Neutral | V13: Agree | W13: Strongly Agree | X13: Agree | Y13: Agree | Z13: Neutral | AA13: Neutral | AC13: Disagree | AD13: Disagree | AE13: Disagree | AF13: Disagree | AG13: Disagree | AH13: Disagree | AI13: Strongly Disagree | AJ13: Strongly Disagree | AK13: Disagree | AL13: Disagree | AO13: StronglyAgree | AP13: StronglyAgree | AQ13: Neutral | AR13: Neutral | AS13: Somewhat Disagree | AT13: Somewhat Disagree | AX13: High | AY13: High | AZ13: No | BD13: CEO | BE13: The largest sharaholders hes substantial voting right [for example above 35%) effectively controlling the company | BF13: No | BG13: 59
A14: 12 | B14: 39 | C14: Female | D14: White | E14: https://drive.google.com/file/d/1A8iBRkOjGU2LJLgKSev8NQKdtgwnCYE5/view?usp=drive_link | F14: Ubaka Chukwunonso | G14: Banking | H14: rolandubaka@gmail.com | J14: 08137790630 | K14: Keystone Bank Ltd | L14: 2 years | M14: The branch manager | O14: Degree holder | P14: 2 years | Q14: Large (Between $xx and $xx) | R14: Agree | S14: Agree | T14: Neutral | U14: Neutral | V14: Agree | W14: Agree | X14: Agree | Y14: Agree | Z14: Disagree | AA14: Somewhat Disagree | AB14: None | AC14: Disagree | AD14: Strongly Disagree | AE14: Somewhat Disagree | AF14: Strongly Disagree | AG14: Strongly Disagree | AH14: Disagree | AI14: Disagree | AJ14: Strongly Disagree | AK14: Neutral | AL14: Somewhat Disagree | AM14: None | AN14: StronglyAgree | AO14: Somewhat Agree | AP14: Agree | AQ14: Agree | AR14: Neutral | AS14: Neutral | AT14: Somewhat Disagree | AU14: 3 | AV14: 3 | AX14: High | AY14: High | AZ14: No | BB14: 1 | BD14: CEO | BE14: The largest sharaholders hes substantial voting right [for example above 35%) effectively controlling the company | BG14: 84
A15: 13 | B15: 46 | C15: Male | D15: Black | E15: https://drive.google.com/file/d/1UUgJmKC8uljsYGhTKh9Sj_Mbr9csOo9k/view?usp=drive_link | F15: Raphael Ogeth | G15: Banker / Teller | H15: Nil | I15: Nil | J15: 07084110097 | K15: UBA | L15: 6 years | M15: Branch Manager | N15: 37 years | O15: Degree holder | P15: 1 years | R15: Strongly Agree | S15: Agree | T15: Neutral | U15: Neutral | V15: Strongly Agree | W15: Strongly Agree | X15: Strongly Agree | Y15: Neutral | Z15: Somewhat Disagree | AA15: Disagree | AC15: Disagree | AD15: Strongly Disagree | AE15: Disagree | AF15: Disagree | AG15: Strongly Disagree | AH15: Disagree | AI15: Disagree | AJ15: Disagree | AK15: Disagree | AL15: Disagree | AN15: StronglyAgree | AO15: Somewhat Agree | AP15: Agree | AQ15: Somewhat Agree | AR15: Somewhat Agree | AS15: Neutral | AT15: Somewhat Agree | BG15: 58
A16: 14 | B16: 41 | C16: Male | D16: White | E16: https://drive.google.com/file/d/1nUldy0qGlfuNg8yzGiZqJvF4ckIcWHMG/view?usp=drive_link | G16: Banker / Customer care | I16: None | K16: UBA | L16: 4 years | M16: Supervisor | N16: 38 years | O16: Degree holder | Q16: Large (Between $xx and $xx) | R16: Agree | S16: Agree | T16: Agree | U16: Agree | V16: Agree | W16: Somewhat Agree | X16: Strongly Agree | Y16: Somewhat Agree | Z16: Somewhat Agree | AA16: Disagree | AC16: Disagree | AD16: Strongly Disagree | AE16: Disagree | AF16: Disagree | AG16: Strongly Disagree | AH16: Disagree | AI16: Strongly Disagree | AJ16: Disagree | AK16: Disagree | AL16: Strongly Agree | AN16: StronglyAgree | AO16: Disagree | AP16: Agree | AQ16: Somewhat Agree | AR16: Somewhat Agree | AS16: Somewhat Agree | AT16: Somewhat Agree | AU16: 10 | AX16: Extremely High | AY16: High | AZ16: No | BB16: 4 | BD16: CEO | BF16: No | BG16: 63
A17: 15 | B17: 28 | C17: Female | D17: Black | E17: https://drive.google.com/file/d/1X_sHh84OWRsEIP4jyT3BZdiNrLaTXUl1/view?usp=drive_link | F17: John Paul | G17: Bank / Cashier | H17: johnpaul@gmail.com | I17: None | J17: 08169973581 | K17: Eco Bank | L17: 6 years | M17: Operation Manager | N17: 30 years | O17: Degree holder | P17: 6 years | Q17: Large (Between $xx and $xx) | R17: Strongly Agree | S17: Somewhat Agree | T17: Somewhat Disagree | U17: Disagree | V17: Strongly Agree | W17: Strongly Agree | X17: Strongly Agree | Y17: Somewhat Disagree | Z17: Somewhat Disagree | AA17: Disagree | AB17: No | AC17: Strongly Disagree | AD17: Strongly Disagree | AE17: Disagree | AF17: Disagree | AG17: Strongly Disagree | AH17: Disagree | AI17: Disagree | AJ17: Somewhat Disagree | AK17: Disagree | AL17: Disagree | AM17: No | AN17: StronglyAgree | AO17: Somewhat Disagree | AP17: StronglyAgree | AQ17: Agree | AR17: Somewhat Disagree | AS17: Neutral | AT17: Neutral | AU17: 12 | AV17: 4 | AW17: 4 | AX17: Extremely High | AY17: Extremely High | AZ17: No | BB17: 4 | BD17: CEO | BE17: The largest sharaholders hes substantial voting right [for example above 35%) effectively controlling the company | BF17: No | BG17: 56
A18: 16 | B18: 37 | C18: Male | D18: White | E18: https://drive.google.com/file/d/1JLf_ucCMIj1Z46kaArZ2W3EuSFihWV7O/view?usp=drive_link | F18: Raphael Ogeth | G18: Banker / Teller | H18: Nil | I18: Nil | J18: 07084110097 | K18: UBA | L18: 6 years | M18: Branch Manager | N18: 37 years | O18: HND holder | P18: 11 years | Q18: Large (Between $xx and $xx) | R18: Agree | S18: Somewhat Agree | T18: Somewhat Agree | U18: Somewhat Disagree | V18: Agree | W18: Agree | X18: Agree | Y18: Somewhat Agree | Z18: Somewhat Disagree | AA18: Neutral | AB18: No | AC18: Somewhat Disagree | AD18: Disagree | AE18: Somewhat Disagree | AF18: Somewhat Disagree | AG18: Disagree | AH18: Somewhat Disagree | AI18: Somewhat Disagree | AJ18: Somewhat Disagree | AK18: Somewhat Disagree | AL18: Neutral | AM18: No | AN18: Agree | AO18: Disagree | AP18: Somewhat Agree | AQ18: Agree | AR18: Neutral | AS18: Neutral | AT18: Somewhat Disagree | AU18: 8 | AV18: 4 | AW18: 4 | AX18: Extremely High | AY18: Extremely High | AZ18: No | BB18: 4 | BC18: Tony Richards | BD18: CEO | BE18: The largest sharaholders hes substantial voting right [for example above 35%) effectively controlling the company | BG18: 45
A19: 17 | B19: 32 | C19: Female | D19: White | E19: https://drive.google.com/file/d/1L3pqy4OYfwV4RUP9OA8cD6CH6EJ_G_qS/view?usp=drive_link | F19: Adeokun Mohammed | G19: Banker | H19: kmohammed22@gmail.com | I19: 20 | J19: 08035229265 | K19: First Bank | L19: 16 years | M19: Branch Bank Manager | N19: 45 years | O19: Degree holder | Q19: Large (Between $xx and $xx) | R19: Agree | S19: Agree | T19: Somewhat Agree | U19: Neutral | V19: Agree | W19: Agree | X19: Agree | Y19: Neutral | Z19: Disagree | AA19: Disagree | AB19: No | AC19: Disagree | AD19: Disagree | AE19: Somewhat Disagree | AF19: Disagree | AG19: Strongly Disagree | AH19: Strongly Disagree | AI19: Neutral | AJ19: Neutral | AK19: Neutral | AL19: Disagree | AM19: No | AN19: Agree | AO19: Neutral | AP19: Agree | AQ19: Neutral | AR19: Somewhat Disagree | AS19: Somewhat Disagree | AT19: Somewhat Disagree | AU19: 3 | AV19: 3 | AX19: Extremely High | AY19: High | AZ19: No | BB19: 1 | BD19: CEO | BE19: The largest sharaholders hes substantial voting right [for example above 35%) effectively controlling the company | BF19: No | BG19: 62
A20: 18 | B20: 48 | C20: Female | D20: White | E20: https://drive.google.com/file/d/1Fjh3aBAsg3yJAq-njT44B6uiPZiU0wbq/view?usp=drive_link | F20: Adeokun Muhammed | G20: Banker | H20: kmohammed22@gmail.com | I20: 20 | J20: 08035229265 | K20: First Bank | L20: 16 years | M20: BM (Branch Manager) | N20: 45 years | O20: Degree plus professional certificates | P20: 15 years | Q20: Large (Between $xx and $xx) | R20: Agree | S20: Agree | T20: Somewhat Agree | U20: Somewhat Agree | V20: Agree | W20: Agree | X20: Strongly Agree | Y20: Strongly Agree | Z20: Neutral | AA20: Somewhat Disagree | AB20: No | AC20: Strongly Disagree | AD20: Disagree | AE20: Disagree | AF20: Disagree | AG20: Strongly Disagree | AH20: Disagree | AI20: Neutral | AJ20: Neutral | AK20: Somewhat Disagree | AL20: Neutral | AM20: No | AN20: Agree | AO20: Somewhat Disagree | AP20: StronglyAgree | AQ20: Agree | AR20: Agree | AS20: Agree | AT20: Neutral | AU20: 3 | AV20: 3 | AW20: 3 | AX20: Extremely High | AY20: High | AZ20: No | BD20: CEO | BE20: The largest sharaholders hes substantial voting right [for example above 35%) effectively controlling the company | BF20: No | BG20: 48
A21: 19 | B21: 30 | C21: Female | D21: White | E21: https://drive.google.com/file/d/1zqLbo20w90eg5XUJk1MocMdZg0hZdb4R/view?usp=drive_link | F21: Hassen Morick | G21: Banker / Customer | H21: morickhassen@yahoo.com | I21: None | J21: 08042578942 | K21: Fidelity Bank | L21: 4 years | M21: Operation Manager | N21: 25 years | O21: Degree plus professional certificates | Q21: Large (Between $xx and $xx) | R21: Agree | S21: Agree | T21: Disagree | U21: Somewhat Agree | V21: Agree | W21: Somewhat Agree | X21: Strongly Agree | Y21: Somewhat Agree | Z21: Agree | AA21: Disagree | AC21: Strongly Disagree | AD21: Strongly Disagree | AE21: Somewhat Agree | AF21: Disagree | AG21: Strongly Disagree | AH21: Strongly Disagree | AI21: Strongly Disagree | AJ21: Strongly Disagree | AK21: Somewhat Disagree | AL21: Agree | AN21: StronglyAgree | AO21: StronglyDisagree | AP21: StronglyAgree | AQ21: Somewhat Agree | AR21: Neutral | AS21: Somewhat Agree | AT21: Somewhat Agree | AX21: Extremely High | AY21: Extremely High | BG21: 44
A22: 20 | B22: 28 | C22: Female | D22: Hispanic | E22: https://drive.google.com/file/d/1roQnN0MW-y5BZhuQMfpJQomf46UuC9kr/view?usp=drive_link | F22: Raphael Ogeth | G22: Banker / Teller | H22: ogethraphael@gmail.com | I22: Nil | J22: 07084110097 | K22: UBA | L22: 6 years | M22: Branch Manager | N22: 37 years | O22: HND holder | P22: 11 years | Q22: Large (Between $xx and $xx) | R22: Somewhat Agree | S22: Somewhat Agree | T22: Somewhat Disagree | U22: Somewhat Disagree | V22: Somewhat Agree | W22: Agree | X22: Somewhat Agree | Y22: Somewhat Agree | Z22: Somewhat Disagree | AA22: Somewhat Disagree | AB22: No | AC22: Disagree | AD22: Disagree | AE22: Somewhat Disagree | AF22: Disagree | AG22: Strongly Disagree | AH22: Somewhat Disagree | AI22: Somewhat Disagree | AJ22: Somewhat Disagree | AK22: Somewhat Disagree | AL22: Neutral | AM22: No | AN22: Agree | AO22: Somewhat Disagree | AP22: Somewhat Agree | AQ22: Agree | AR22: Somewhat Disagree | AS22: Somewhat Disagree | AT22: Neutral | AU22: 10 | AV22: 4 | AW22: 4 | AX22: Extremely High | AY22: Extremely High | AZ22: No | BB22: 4 | BD22: CEO | BE22: The largest sharaholders hes substantial voting right [for example above 35%) effectively controlling the company | BG22: 65
A23: 21 | B23: 31 | C23: Female | D23: Black | E23: https://drive.google.com/file/d/1e4I-czRHLLKrdhFqy9dcvdpbSnPIGUOD/view?usp=drive_link | F23: Adeokun Mohammed | G23: Banker | H23: kmohammed22@gmail.com | I23: 20 | J23: 08035229265 | K23: First Bank | L23: 16 years | M23: BM (Branch Manager) | N23: 45 years | O23: Degree plus professional certificates | P23: 15 years | Q23: Large (Between $xx and $xx) | R23: Agree | S23: Agree | T23: Somewhat Agree | U23: Somewhat Agree | V23: Agree | W23: Agree | X23: Strongly Agree | Y23: Strongly Agree | Z23: Somewhat Agree | AA23: Neutral | AB23: None | AC23: Strongly Disagree | AD23: Disagree | AE23: Disagree | AF23: Disagree | AG23: Strongly Disagree | AH23: Disagree | AI23: Somewhat Disagree | AJ23: Neutral | AK23: Somewhat Disagree | AL23: Somewhat Disagree | AM23: No | AN23: Agree | AO23: Somewhat Disagree | AP23: StronglyAgree | AQ23: Agree | AR23: Agree | AS23: Agree | AT23: Neutral | AU23: 3 | AV23: 3 | AW23: 3 | AX23: Extremely High | AY23: High | AZ23: No | BB23: 4 | BD23: CEO | BE23: The largest sharaholders hes substantial voting right [for example above 35%) effectively controlling the company | BF23: None | BG23: 61
A24: 22 | B24: 29 | C24: Female | D24: White | E24: https://drive.google.com/file/d/1SOv7-KxOC7S8TzWOt50zXggsK87MVp_B/view?usp=drive_link | F24: Emeje Doshing G. | G24: Security Guard | I24: 4 | J24: 08135423361 | K24: UBA | L24: 11 years | M24: Head of Operations | N24: 37 years | O24: Diploma level | P24: 11 years | Q24: Medium (Between $xx and $xx) | R24: Agree | S24: Neutral | T24: Disagree | U24: Agree | V24: Agree | W24: Strongly Agree | X24: Disagree | Y24: Agree | Z24: Disagree | AA24: Agree | AB24: No | AC24: Agree | AD24: Disagree | AE24: Agree | AF24: Disagree | AG24: Agree | AH24: Neutral | AI24: Disagree | AJ24: Agree | AK24: Disagree | AL24: Agree | AM24: No | AN24: Agree | AO24: Disagree | AP24: Agree | AQ24: Somewhat Disagree | AR24: Agree | AS24: Agree | AT24: Neutral | AU24: 6 | AV24: 3 | AW24: 3 | AX24: High | AY24: High | AZ24: Capacity | BC24: Manager | BD24: CEO | BE24: The largest sharaholders hes substantial voting right [for example above 35%) effectively controlling the company | BF24: No | BG24: 56
A25: 23 | B25: 26 | C25: Male | D25: White | E25: https://drive.google.com/file/d/16D5T662JtkJRuQej_2FG0MkyHUmm3Nil/view?usp=drive_link | F25: Shedrack Apeh | G25: Banker/Sales | H25: shedrackapeh4@gmail.com | I25: None | J25: 08098554734 | K25: Keystone Bank | L25: 4 years | M25: Manager | N25: 29 years | O25: HND holder | P25: 4 years | Q25: Large (Between $xx and $xx) | R25: Agree | S25: Strongly Agree | T25: Somewhat Agree | U25: Neutral | V25: Somewhat Agree | W25: Strongly Agree | X25: Strongly Agree | Y25: Agree | Z25: Strongly Disagree | AA25: Disagree | AB25: No | AC25: Strongly Disagree | AD25: Disagree | AE25: Disagree | AF25: Disagree | AG25: Strongly Disagree | AH25: Disagree | AI25: Neutral | AJ25: Somewhat Disagree | AK25: Disagree | AL25: Somewhat Disagree | AM25: No | AN25: StronglyAgree | AO25: Somewhat Disagree | AP25: Agree | AQ25: Somewhat Agree | AR25: Somewhat Agree | AS25: Neutral | AT25: Neutral | AU25: 8 | AV25: 4 | AW25: 4 | AX25: Extremely High | AY25: High | AZ25: No | BB25: 4 | BC25: Loans, Ethics, Audit, Council, Marketing | BD25: CEO | BE25: The largest sharaholders hes substantial voting right [for example above 35%) effectively controlling the company | BF25: No | BG25: 82
A26: 24 | B26: 28 | C26: Female | D26: White | E26: https://drive.google.com/file/d/1N7nEDlLpImApEgKDiJ21ZdpJah24wGAZ/view?usp=drive_link | F26: Ezeanuta Blessing | G26: Banker/Customer Care | H26: blessezeanuta@gmail.com | I26: None | J26: 08140408843 | K26: United Bank for Africa | L26: 6 years | M26: Head Sales | N26: 29 years | O26: Degree holder | Q26: Medium (Between $xx and $xx) | R26: Somewhat Agree | S26: Somewhat Agree | T26: Strongly Disagree | U26: Agree | V26: Agree | W26: Agree | X26: Agree | Y26: Somewhat Agree | Z26: Agree | AA26: Somewhat Agree | AC26: Disagree | AD26: Strongly Disagree | AE26: Disagree | AF26: Strongly Disagree | AG26: Strongly Disagree | AH26: Somewhat Disagree | AI26: Strongly Disagree | AJ26: Strongly Disagree | AL26: Agree | AN26: Agree | AO26: StronglyDisagree | AP26: Agree | AQ26: Agree | AR26: Somewhat Disagree | AS26: Somewhat Agree | AT26: Somewhat Agree | AX26: Extremely High | AY26: Extremely High | BG26: 44
A27: 25 | B27: 25 | C27: Male | D27: Black | E27: https://drive.google.com/file/d/1UL2EPuVuxeTj7Sj_NPi4UNlgPdW6RSek/view?usp=drive_link | F27: Ali Hussein | G27: Banker | H27: alihussein_2003@yahoo.com | I27: 25 | J27: 08100944610 | K27: Bank | L27: 8 years | M27: Bank Manager | N27: 45 years | O27: Degree holder | P27: 12 years | Q27: Large (Between $xx and $xx) | R27: Agree | S27: Somewhat Agree | T27: Somewhat Disagree | U27: Disagree | V27: Agree | W27: Agree | X27: Agree | Y27: Somewhat Agree | Z27: Disagree | AA27: Somewhat Disagree | AB27: No | AC27: Disagree | AD27: Somewhat Disagree | AE27: Disagree | AF27: Disagree | AG27: Somewhat Disagree | AH27: Somewhat Disagree | AI27: Disagree | AJ27: Somewhat Disagree | AK27: Disagree | AL27: Somewhat Disagree | AM27: No | AN27: Agree | AO27: Disagree | AP27: Agree | AQ27: Agree | AR27: Somewhat Disagree | AS27: Somewhat Agree | AT27: Neutral | AU27: 10 | AV27: 4 | AW27: 4 | AX27: Extremely High | AY27: Extremely High | BG27: 44
A28: 26 | B28: 29 | C28: Female | D28: White | E28: https://drive.google.com/file/d/1Pr3tg1A1Vf0L7mJIYNTlcnxzbXoe-h5M/view?usp=drive_link | F28: Oluwote Ogundipe | G28: Banking/CEO | I28: 5 | J28: 08100574582 | K28: UBA | L28: 4 years | M28: Branch Manager | N28: 38 years | O28: HND holder | P28: 10 years | Q28: Large (Between $xx and $xx) | R28: Strongly Agree | S28: Agree | T28: Disagree | U28: Somewhat Disagree | V28: Strongly Agree | W28: Strongly Agree | X28: Somewhat Agree | Y28: Somewhat Agree | Z28: Disagree | AA28: Neutral | AB28: No | AC28: Somewhat Disagree | AD28: Strongly Disagree | AE28: Disagree | AF28: Disagree | AG28: Disagree | AH28: Strongly Disagree | AI28: Somewhat Disagree | AJ28: Disagree | AK28: Somewhat Disagree | AL28: Somewhat Disagree | AM28: No | AN28: StronglyAgree | AO28: StronglyDisagree | AP28: StronglyAgree | AQ28: Agree | AR28: Disagree | AS28: Neutral | AT28: Neutral | AU28: 10 | AV28: 4 | AW28: 4 | AX28: Extremely High | AY28: Extremely High | AZ28: No | BB28: 4 | BC28: Tony Elumelu | BD28: CEO | BE28: The largest sharaholders hes substantial voting right [for example above 35%) effectively controlling the company | BF28: No | BG28: 57
A29: 27 | B29: 45 | C29: Male | D29: White | E29: https://drive.google.com/file/d/1M6Uv3ouknR-csnt1D_R44ImykCWXMcX3/view?usp=drive_link | F29: Ali Hussein | G29: Banker | H29: alihussein_2003@yahoo.com | I29: 25 | J29: 08100944610 | K29: Bank | L29: 8 years | M29: Branch Manager | N29: 45 years | O29: Degree holder | P29: 12 years | Q29: Large (Between $xx and $xx) | R29: Agree | S29: Agree | T29: Somewhat Agree | U29: Somewhat Disagree | V29: Agree | W29: Agree | X29: Agree | Y29: Somewhat Disagree | Z29: Disagree | AA29: Somewhat Disagree | AB29: No | AC29: Disagree | AD29: Disagree | AE29: Somewhat Disagree | AF29: Disagree | AG29: Somewhat Disagree | AH29: Somewhat Disagree | AI29: Somewhat Disagree | AJ29: Disagree | AK29: Somewhat Disagree | AL29: Disagree | AM29: No | AN29: Agree | AO29: Disagree | AP29: Agree | AQ29: Agree | AR29: Neutral | AS29: Neutral | AT29: Neutral | AU29: 10 | AV29: 4 | AW29: 4 | AX29: Extremely High | AY29: Extremely High | AZ29: No | BB29: 4 | BC29: Tony Elumelu | BD29: CEO | BE29: The largest sharaholders hes substantial voting right [for example above 35%) effectively controlling the company | BF29: No | BG29: 57
A30: 28 | B30: 49 | C30: Male | D30: White | E30: https://drive.google.com/file/d/17EdD2baxpPaxa6wESyGNIn9nueNxxr9E/view?usp=drive_link | G30: Banker/Cashier | I30: None | K30: Wema Bank | L30: 5 years | M30: Supervisor | N30: 28 years | O30: HND holder | P30: 5 years | Q30: Large (Between $xx and $xx) | R30: Agree | S30: Somewhat Agree | T30: Disagree | U30: Somewhat Disagree | V30: Agree | W30: Strongly Agree | X30: Agree | Y30: Neutral | Z30: Disagree | AA30: Somewhat Disagree | AC30: Strongly Disagree | AD30: Disagree | AE30: Somewhat Agree | AF30: Disagree | AG30: Disagree | AH30: Disagree | AI30: Somewhat Disagree | AJ30: Somewhat Disagree | AK30: Somewhat Disagree | AL30: Disagree | AM30: No | AN30: StronglyAgree | AO30: Somewhat Disagree | AP30: Agree | AQ30: Somewhat Agree | AR30: Somewhat Disagree | AS30: Neutral | AT30: Neutral | AU30: 13 | AV30: 6 | AW30: 7 | AX30: Extremely High | AY30: High | AZ30: No | BB30: 7 | BC30: Dr. Alayemi Si, Moruf Oseni, Wole Famuyibo, Isiyaka S. Kung, Yusuf Kaura | BD30: CEO | BE30: The largest sharaholders hes substantial voting right [for example above 35%) effectively controlling the company | BF30: No | BG30: 64
A31: 29 | B31: 25 | C31: Male | D31: White | E31: https://drive.google.com/file/d/1nN_bboikhZ897AMas0fWNmaMIdNDN6jG/view?usp=drive_link | F31: Ibrahim Sadiq | G31: Banking | H31: sadiqibrahimabumi@gmail.com | J31: 08064518330 | K31: Keystone Bank Ltd | L31: 4 years | M31: Branch Manager | O31: Masters holder | P31: 4 years | Q31: Large (Between $xx and $xx) | R31: Agree | S31: Agree | T31: Neutral | U31: Neutral | V31: Agree | W31: Agree | X31: Agree | Y31: Agree | Z31: Disagree | AA31: Neutral | AB31: None | AC31: Disagree | AD31: Strongly Disagree | AE31: Disagree | AF31: Strongly Disagree | AG31: Strongly Disagree | AH31: Disagree | AI31: Disagree | AJ31: Strongly Disagree | AK31: Neutral | AL31: Disagree | AM31: None | AN31: StronglyAgree | AO31: Agree | AP31: Agree | AQ31: Agree | AR31: Neutral | AS31: Somewhat Agree | AT31: Disagree | AU31: 3 | AV31: 3 | AX31: High | AY31: High | AZ31: No | BB31: 1 | BD31: CEO | BE31: The largest sharaholders hes substantial voting right [for example above 35%) effectively controlling the company | BG31: 77
A32: 30 | B32: 47 | C32: Male | D32: White | E32: https://drive.google.com/file/d/1sF7gtxO-VUok_zZKU7QQOnNW5YsORRjM/view?usp=drive_link | G32: Banker | I32: None | K32: Zenith Bank | L32: 3 years | M32: Supervisor | N32: 26 years | O32: HND holder | P32: 3 years | Q32: Large (Between $xx and $xx) | R32: Strongly Agree | S32: Somewhat Agree | T32: Somewhat Disagree | U32: Disagree | V32: Agree | W32: Strongly Agree | X32: Agree | Y32: Somewhat Agree | Z32: Disagree | AA32: Somewhat Disagree | AB32: No | AC32: Strongly Disagree | AD32: Strongly Disagree | AE32: Disagree | AF32: Disagree | AG32: Strongly Disagree | AH32: Disagree | AI32: Disagree | AJ32: Disagree | AK32: Disagree | AL32: Somewhat Disagree | AM32: No | AN32: StronglyAgree | AO32: Disagree | AP32: StronglyAgree | AQ32: Somewhat Agree | AR32: Neutral | AS32: Neutral | AT32: Neutral | AU32: 12 | AV32: 4 | AW32: 8 | AX32: Extremely High | AY32: Extremely High | AZ32: No | BB32: 4 | BC32: Jim Ovia, Adozi Nwapa, Mustafa Bello, Adaora Umeji. | BD32: CEO | BE32: The largest sharaholders hes substantial voting right [for example above 35%) effectively controlling the company | BF32: No | BG32: 39
A33: 31 | B33: 44 | C33: Female | D33: White | E33: https://drive.google.com/file/d/1kGV66NOqE0xz3b5Qs290rTuhGmqdc7Us/view?usp=drive_link | F33: Barnabas Bonduamba | G33: Banker/Teller | H33: bonduas@gmail.com | I33: None | J33: 08031852182 | K33: United Bank for Africa | L33: 8 years | M33: Head Cashier | N33: 35 years | O33: Masters holder | P33: 10 years | Q33: Large (Between $xx and $xx) | R33: Agree | S33: Somewhat Agree | T33: Somewhat Disagree | U33: Somewhat Disagree | V33: Agree | W33: Strongly Agree | X33: Agree | Y33: Somewhat Agree | Z33: Somewhat Disagree | AA33: Somewhat Disagree | AB33: No | AC33: Somewhat Disagree | AD33: Disagree | AE33: Somewhat Disagree | AF33: Disagree | AG33: Strongly Disagree | AH33: Somewhat Disagree | AI33: Somewhat Disagree | AJ33: Somewhat Disagree | AK33: Somewhat Disagree | AL33: Disagree | AM33: No | AN33: Agree | AO33: Somewhat Disagree | AP33: Somewhat Agree | AQ33: Somewhat Agree | AR33: Somewhat Disagree | AS33: Somewhat Agree | AT33: Neutral | AU33: 8 | AV33: 2 | AW33: 4 | AX33: Extremely High | AY33: Extremely High | AZ33: No | BB33: 2 | BC33: Tony Elumelu | BD33: CEO | BE33: The largest sharaholders hes substantial voting right [for example above 35%) effectively controlling the company | BG33: 54
A34: 32 | B34: 47 | C34: Female | D34: White | E34: https://drive.google.com/file/d/1Lj7ADICgP83l0RVzrh40lKBuMYgeZ2mf/view?usp=drive_link | F34: Jarad Godwin | H34: godwinjarad@gmail.com | I34: None | J34: 07068474653 | K34: Wema Bank | L34: 8 years | M34: Head of Operations | N34: 36 years | O34: Degree holder | P34: 10 years | Q34: Large (Between $xx and $xx) | R34: Disagree | S34: StronglyDisagree | T34: StronglyDisagree | U34: Disagree | V34: StronglyDisagree | W34: Somewhat Disagree | X34: Somewhat Agree | Y34: Strongly Disagree | Z34: Agree | AA34: Strongly Agree | AC34: Somewhat Agree | AD34: Somewhat Agree | AE34: Strongly Agree | AF34: Agree | AG34: Somewhat Agree | AH34: Strongly Agree | AI34: Strongly Agree | AJ34: Agree | AK34: Agree | AL34: Strongly Disagree | AU34: 6 | AV34: 5 | AW34: 5 | AX34: Extremely Low | AY34: Low | BG34: 67
A35: 33 | B35: 24 | C35: Female | D35: White | E35: https://drive.google.com/file/d/1i0_EdzTY3jWrELUByvsTnTaVbvjYaDg3/view?usp=drive_link | F35: Elizabeth Michael | G35: Banking/Customer Care | H35: elizabeth12@gmail.com | I35: Nil | J35: 09095077027 | K35: First Bank | L35: 4 years | M35: Operation Manager | N35: 26 years | O35: Diploma level | P35: 4 years | Q35: Large (Between $xx and $xx) | R35: Strongly Agree | S35: Agree | T35: Somewhat Disagree | U35: Somewhat Disagree | V35: Strongly Agree | W35: Strongly Agree | X35: Strongly Agree | Y35: Agree | Z35: Somewhat Disagree | AA35: Somewhat Disagree | AB35: No | AC35: Strongly Disagree | AD35: Disagree | AE35: Somewhat Disagree | AF35: Disagree | AG35: Strongly Disagree | AH35: Somewhat Disagree | AI35: Somewhat Disagree | AJ35: Disagree | AK35: Somewhat Disagree | AL35: Somewhat Disagree | AM35: No | AN35: StronglyAgree | AO35: Strongly Disagree | AP35: Agree | AQ35: Agree | AR35: Somewhat Disagree | AS35: Somewhat Disagree | AT35: Neutral | AU35: 10 | AV35: 4 | AW35: 4 | AX35: High | AY35: Extremely High | AZ35: No | BB35: 4 | BC35: Oluwasegun Hubosa, Patricia lyamabo. | BD35: CEO | BE35: The largest sharaholders hes substantial voting right [for example above 35%) effectively controlling the company | BF35: No | BG35: 68
A36: 34 | B36: 29 | C36: Female | D36: White | E36: https://drive.google.com/file/d/1ShI83uetTiixKtFp2T4zGfJ3Nbayz7CW/view?usp=drive_link | G36: Banker | K36: Wema Bank | L36: 5 years | M36: Business Team Leader | O36: Degree holder | Q36: Large (Between $xx and $xx) | R36: Somewhat Agree | S36: Agree | T36: Agree | U36: Somewhat Agree | V36: Agree | W36: Agree | X36: Agree | Y36: Disagree | Z36: Disagree | AA36: Somewhat Disagree | AC36: Disagree | AD36: Disagree | AE36: Somewhat Disagree | AF36: Somewhat Disagree | AG36: Disagree | AH36: Somewhat Agree | AI36: Disagree | AJ36: Disagree | AK36: Somewhat Agree | AL36: Somewhat Disagree | AN36: Strongly Agree | AO36: Disagree | AP36: Agree | AQ36: Agree | AR36: Neutral | AS36: Disagree | AT36: Disagree | AU36: 10 | AV36: 5 | AW36: 7 | AX36: Extremely High | AY36: High | AZ36: No | BB36: 4 | BD36: Board | BF36: No | BG36: 64
A37: 35 | B37: 33 | C37: Female | D37: White | E37: https://drive.google.com/file/d/1MZSppHiQp6jKD66yH8i1bagngpGe8QOl/view?usp=drive_link | G37: Banker / Customer Care | I37: None | K37: UBA | L37: 4 years | M37: Supervisor | N37: 26 years | O37: Degree holder | P37: 4 years | Q37: Large (Between $xx and $xx) | R37: Strongly Agree | S37: Somewhat Agree | T37: Somewhat Disagree | U37: Disagree | V37: Strongly Agree | W37: Strongly Agree | X37: Agree | Y37: Somewhat Disagree | Z37: Somewhat Disagree | AA37: Somewhat Disagree | AB37: No | AC37: Strongly Disagree | AD37: Disagree | AE37: Strongly Disagree | AF37: Somewhat Disagree | AG37: Strongly Disagree | AH37: Somewhat Disagree | AI37: Somewhat Disagree | AJ37: Disagree | AK37: Somewhat Disagree | AL37: Somewhat Disagree | AM37: No | AN37: Strongly Agree | AO37: Somewhat Disagree | AP37: Strongly Agree | AQ37: Agree | AR37: Neutral | AS37: Neutral | AT37: Neutral | AU37: 4 | AV37: 4 | AW37: 4 | AX37: Extremely High | AY37: High | AZ37: No | BB37: 4 | BC37: Anthony Stanley, Oliver Alawuba, Alex Afolabi, Muyiwa Akinyemi, Manafatu Asola. | BD37: CEO | BE37: The largest sharaholders hes substantial voting right [for example above 35%) effectively controlling the company | BG37: 58
A38: 36 | B38: 38 | C38: Female | D38: White | E38: https://drive.google.com/file/d/1ZE1HpHcGWofufsL0QXip3lKhnEew-X-t/view?usp=drive_link | G38: Banking | I38: 6 | K38: Keystone Bank Ltd | L38: 5 years | M38: Manager | N38: 33 years | O38: Degree holder, Masters holder plus professional certificates | Q38: Medium (Between $xx and $xx) | R38: Somewhat Agree | S38: Agree | T38: Disagree | U38: Agree | V38: Strongly Agree | W38: Strongly Agree | X38: Strongly Agree | Y38: Somewhat Agree | Z38: Somewhat Agree | AA38: Disagree | AC38: Strongly Disagree | AD38: Strongly Disagree | AE38: Disagree | AF38: Strongly Disagree | AG38: Strongly Disagree | AH38: Disagree | AI38: Strongly Disagree | AJ38: Strongly Disagree | AK38: Disagree | AL38: Somewhat Agree | AN38: Strongly Agree | AO38: Disagree | AP38: Agree | AQ38: Somewhat Agree | AR38: Disagree | AS38: Somewhat Agree | AT38: Somewhat Agree | AX38: Extremely High | AY38: High | BG38: 46
A39: 37 | B39: 52 | C39: Female | D39: Black | E39: https://drive.google.com/file/d/15i9RZZ2-Mmo8TUwWDyKqDXzvi2O42au_/view?usp=drive_link | F39: Oche Emmanuel | G39: euumqiweloche22@gmail.com | H39: Bawis Audtor | I39: i | J39: 08032477994 | K39: huy Stone Banp | L39: 7 Years | M39: Heas of operation | N39: 34 Years | O39: Degree holder | P39: 10 years | Q39: Large (Between $xx and $xx) | R39: Agree | S39: Somewhat Agree | T39: Somewhat Disagree | U39: Somewhat Disagree | V39: Strongly Agree | W39: Strongly Agree | X39: Agree | Y39: Agree | Z39: Somewhat Disagree | AA39: Somewhat Disagree | AB39: No | AC39: Disagree | AD39: Somewhat disagree | AE39: Disagree | AF39: Disagree | AG39: Strongly Disagree | AH39: Somewhat disagree | AI39: Somewhat disagree | AJ39: Somewhat disagree | AK39: Disagree | AL39: Somewhat disagree | AM39: No | AN39: Somewhat disagree | AO39: Disagree | AP39: Somewhat disagree | AQ39: Somewhat Agree | AR39: Somewhat Disagree | AS39: Somewhat Disagree | AT39: Disagree | AU39: 10 | AV39: 4 | AW39: 4 | AX39: Extremely High | AY39: Extremely High | BD39: CEO | BE39: The largest sharaholders hes substantial voting right [for example above 35%) effectively controlling the company | BG39: 46
A40: 38 | B40: 32 | C40: Male | D40: Black | E40: https://drive.google.com/file/d/1i3rrZqDHPZ0sSWnshd7MoSZyWf1s7z5a/view?usp=drive_link | F40: Laraba Peul | G40: Banang Sales Rep | H40: larabapulsuoy123@gmail.com | I40: 8 | J40: 08068657512 | K40: GT PauR | L40: 12 Years | M40: Regualac manager | N40: 41 Years | O40: Masters holder | P40: 15 years | Q40: Large (Between $xx and $xx) | R40: Strongly Agree | S40: Somewhat Agree | T40: Somewhat Disagree | U40: Somewhat Disagree | V40: Agree | W40: Strongly Agree | X40: Somewhat Agree | Y40: Somewhat Agree | Z40: Disagree | AA40: Somewhat Disagree | AC40: Disagree | AD40: Disagree | AE40: Disagree | AF40: Strongly Disagree | AG40: Somewhat Disagree | AH40: Somewhat Disagree | AI40: Disagree | AJ40: Somewhat Disagree | AK40: Disagree | AL40: Somewhat Disagree | AM40: No | AN40: Strongly Disagree | AO40: Disagree | AP40: Agree | AQ40: Agree | AR40: Neutral | AS40: Neutral | AT40: Somewhat Disagree | AX40: High | AY40: Extremely High | AZ40: No | BD40: CEO | BE40: The largest sharaholders hes substantial voting right [for example above 35%) effectively controlling the company | BG40: 38
A41: 39 | B41: 28 | C41: Female | D41: Black | E41: https://drive.google.com/file/d/1eCgtazfmaPz_-ppAvmI774PaFvEURZoM/view?usp=drive_link | F41: Tmuewel nrguta | G41: Banh Sales an marketing | H41: rugataemmanel@yahoo.com | I41: Head Sales | J41: 0947617314 | K41: Wema Beua | L41: 5 years | M41: Heel Sedes AmaneAins Dupartursu C: | N41: 27 Years | O41: Degree holder | P41: 5 years | Q41: Large (Between $xx and $xx) | R41: Strongly Agree | S41: Somewhat Agree | T41: Somewhat Disagree | U41: Somewhat Disagree | V41: Strongly Agree | W41: Strongly Agree | X41: Agree | Y41: Agree | Z41: Disagree | AA41: Somewhat Disagree | AB41: No | AC41: Disagree | AD41: Disagree | AE41: Somewhat Disagree | AF41: Disagree | AG41: Disagree | AH41: Somewhat Disagree | AI41: Disagree | AJ41: Somewhat Disagree | AK41: Somewhat Disagree | AL41: Somewhat Disagree | AM41: No | AN41: Strongly Agree | AO41: Disagree | AP41: Agree | AQ41: Agree | AR41: Somewhat disagree | AS41: Somewhat disagree | AT41: Somewhat disagree | AX41: Extremely High | AY41: High | BA41: Nill | BD41: CEO | BE41: The largest sharaholders hes substantial voting right [for example above 35%) effectively controlling the company | BF41: No | BG41: 57
A42: 40 | B42: 29 | C42: Female | D42: White | E42: https://drive.google.com/file/d/15DbzZgbAWA9q0Eae2PpY43oqcIbsXbWg/view?usp=drive_link | F42: Stephine Lgilaunte | G42: stephinelgilaunte@ | H42: Banper Sales Marketing | I42: None | J42: 07032917904 | K42: Union Bank | L42: 2 years | M42: Head Sales | N42: 28 Years | O42: HND holder | P42: 2 years | Q42: Large (Between $xx and $xx) | R42: Strongly Agree | S42: Somewhat Agree | T42: Somewhat Agree | U42: Somewhat Disagree | V42: Agree | W42: Strongly Agree | X42: Agree | Y42: Agree | Z42: Disagree | AA42: Somewhat Disagree | AB42: Nill | AC42: Disagree | AD42: Somewhat Disagree | AE42: Disagree | AF42: Strongly Disagree | AG42: Disagree | AH42: Somewhat Disagree | AI42: Somewhat Disagree | AJ42: Somewhat Disagree | AK42: Somewhat Disagree | AL42: Somewhat Disagree | AM42: No | AN42: Agree | AO42: Disagree | AP42: Agree | AQ42: Agree | AR42: Somewhat disagree | AS42: Somewhat disagree | AT42: Somewhat disagree | AX42: Extremely High | AY42: High | AZ42: No | BD42: CEO | BE42: The largest sharaholders hes substantial voting right [for example above 35%) effectively controlling the company | BF42: No | BG42: 56
A43: 41 | B43: 51 | C43: Female | D43: White | E43: https://drive.google.com/file/d/19k1L8_pq8xFwqPPjS8Kifr1WnfvGC-rv/view?usp=drive_link | F43: Elizabeth Udeh | G43: Banking Teller | H43: elizabethudeh@gmail.com | I43: Nil | J43: 08080221687 | K43: Union Bank | L43: 5 years | M43: HeadCasher | N43: 24 Years | O43: HND holder | P43: 5 years | Q43: Large (Between $xx and $xx) | R43: Strongly Agree | S43: Somewhat Agree | T43: Somewhat Disagree | U43: Disagree | V43: Strongly Agree | W43: Strongly Agree | X43: Agree | Y43: Agree | Z43: Somewhat Disagree | AA43: Disagree | AB43: No | AC43: Disagree | AD43: Somewhat Disagree | AE43: Disagree | AF43: Disagree | AG43: Disagree | AH43: Somewhat Disagree | AI43: Disagree | AJ43: Disagree | AK43: Disagree | AL43: Somewhat Disagree | AM43: No | AN43: Strongly Agree | AO43: Disagree | AP43: Agree | AQ43: Agree | AR43: Somewhat disagree | AS43: Somewhat disagree | AT43: Somewhat disagree | AU43: 12 | AV43: 4 | AW43: 4 | AX43: High | AY43: Extremely High | AZ43: No | BB43: 3 | BD43: CEO | BE43: The largest sharaholders hes substantial voting right [for example above 35%) effectively controlling the company | BG43: 63
A44: 42 | B44: 30 | C44: Male | D44: White | E44: https://drive.google.com/file/d/17Q2NToRW6XNXmSMlBMLIzZmPmKzBaIsz/view?usp=drive_link | F44: Sadeeg Xyubabar | G44: Banker/ Auditor | H44: ayubagarsadeep@yahoo.com | I44: 2 | J44: 09019001569 | K44: First Gank Plc | L44: 8 years | M44: Regonal Head | N44: 42 Years | O44: Masters holder | P44: 15 years | Q44: Large (Between $xx and $xx) | R44: Strongly Agree | S44: Agree | T44: Somewhat Disagree | U44: Disagree | V44: Strongly Agree | W44: Strongly Agree | X44: Agree | Y44: Strongly Agree | Z44: Disagree | AA44: Disagree | AB44: No | AC44: Disagree | AD44: Somewhat Disagree | AE44: Disagree | AF44: Disagree | AG44: Strongly Disagree | AH44: Strongly Disagree | AI44: Somewhat Disagree | AJ44: Disagree | AK44: Somewhat Disagree | AL44: Somewhat Disagree | AM44: No | AN44: Strongly Agree | AO44: Strongly Agree | AP44: Strongly Agree | AQ44: Agree | AR44: Somewhat disagree | AS44: Somewhat disagree | AT44: Neutral | AU44: 12 | AV44: 4 | AW44: 4 | AX44: Extremely High | AY44: Extremely High | AZ44: No | BB44: 4 | BC44: Olusgun Zlebiosu | BD44: CEO | BE44: The largest sharaholders hes substantial voting right [for example above 35%) effectively controlling the company | BF44: No | BG44: 69
A45: 43 | B45: 53 | C45: Male | D45: Black | E45: https://drive.google.com/file/d/1dzyp3gzakuMU9dI0v547OxHv1v8VkM6l/view?usp=drive_link | F45: Oluoaseyi Asowo | G45: Banking/ Customare Care | H45: asawesayi@gmail.com | I45: Nil | J45: 01131280965 | K45: Wema Bank | L45: 7 years | M45: Operation Manager | N45: 33 Years | O45: Degree holder | P45: 7 years | Q45: Large (Between $xx and $xx) | R45: Strongly Agree | S45: Somewhat Agree | T45: Somewhat Disagree | U45: Somewhat Disagree | V45: Strongly Agree | W45: Strongly Agree | X45: Agree | Y45: Agree | Z45: Somewhat Disagree | AA45: Somewhat Disagree | AB45: No | AC45: Disagree | AD45: Disagree | AE45: Disagree | AF45: Somewhat Disagree | AG45: Somewhat Disagree | AH45: Somewhat Disagree | AI45: Somewhat Disagree | AJ45: Disagree | AK45: Somewhat Disagree | AL45: Somewhat Disagree | AM45: No | AN45: Strongly Agree | AO45: Disagree | AP45: Agree | AQ45: Agree | AR45: Somewhat disagree | AS45: Somewhat disagree | AT45: Somewhat disagree | AX45: High | AY45: Extremely High | AZ45: No | BD45: CEO | BE45: The largest sharaholders hes substantial voting right [for example above 35%) effectively controlling the company | BF45: No | BG45: 60
A46: 44 | B46: 45 | C46: Female | D46: Black | E46: https://drive.google.com/file/d/1xX0hL_DgEJFnrL4xqq3WtFxT-_jZmvY1/view?usp=drive_link | F46: Ocly Chnstiars | G46: Banker/Cso | H46: odichashari1@gmail.com | I46: Nil | J46: 08105974939 | K46: Keystone Bank | L46: Two Month | M46: Nweboy Adi Dand' | N46: 27 Years | O46: Degree plus professional certificates | Q46: Medium (Between $xx and $xx) | R46: Strongly Agree | S46: Agree | T46: Neutral | U46: Somewhat Disagree | V46: Agree | W46: Strongly Agree | X46: Agree | Y46: Neutral | Z46: Disagree | AA46: Disagree | AB46: No | AC46: Disagree | AD46: Disagree | AE46: Disagree | AF46: Strongly Disagree | AG46: Disagree | AH46: Strongly Disagree | AI46: Disagree | AJ46: Disagree | AK46: Strongly Disagree | AL46: Strongly Disagree | AM46: Nill | AN46: Agree | AO46: Neutral | AP46: Neutral | AQ46: Agree | AR46: Neutral | AS46: Agree | AT46: Disagree | AU46: 4 | AV46: 2 | AW46: 2 | AX46: Extremely High | AY46: High | AZ46: No | BA46: Nill | BB46: 4 | BD46: Bord | BE46: Two or more shareholders control the company | BG46: 49
A47: 45 | B47: 39 | C47: Female | D47: White | E47: https://drive.google.com/file/d/1wpY22eKGA_OKTPvBZvyJ1fh7w9djj5ds/view?usp=drive_link | F47: N/A | G47: Banker | H47: N/A | I47: 5 | J47: N/A | K47: Keystone Bank | L47: 3 years | M47: N/A | N47: N/A | O47: Degree plus professional certificates | P47: 3 years | Q47: Medium (Between $xx and $xx) | R47: Neutral | S47: Neutral | T47: Neutral | U47: Neutral | V47: Neutral | W47: Neutral | X47: Somewhat Agree | Y47: Neutral | Z47: Neutral | AA47: Neutral | AC47: Somewhat Disagree | AD47: Disagree | AE47: Disagree | AF47: Disagree | AG47: Strongly Disagree | AH47: Disagree | AI47: Disagree | AJ47: Disagree | AK47: Disagree | AL47: Disagree | AN47: Agree | AO47: Somewhat Agree | AP47: Agree | AQ47: Agree | AR47: Neutral | AS47: Neutral | AT47: Neutral | AU47: N/A | AV47: N/A | AW47: N/A | AX47: Average | AY47: Maybe | AZ47: Neutral | BB47: N/A | BC47: N/A | BD47: Chairman | BE47: Neutral | BF47: N/A | BG47: 47
A48: 46 | B48: 38 | C48: Female | D48: White | E48: https://drive.google.com/file/d/1vbLMTJedAeGuPjS7VO5xsUr_QYwqCqIH/view?usp=drive_link | F48: Odo Chidimma Herinxtra | G48: Rolationshop Offior | H48: Hennieodo@keystmbanking.com | I48: None | J48: 08131219062 | K48: Keystone Bank | L48: 8 Month | M48: Branceh Manager | N48: 27 Years | O48: Degree holder | P48: None | Q48: Medium (Between $xx and $xx) | R48: Agree | S48: Agree | T48: Somewhat Agree | U48: Agree | V48: Agree | W48: Agree | X48: Agree | Y48: Agree | Z48: Agree | AA48: Agree | AI48: Disagree | AJ48: Disagree | AK48: Agree | AL48: Neutral | AU48: 8 | AV48: 2 | AW48: 2 | AX48: Extremely High | AY48: Extremely High | AZ48: No | BB48: 5 | BD48: CEO | BE48: The largest sharaholders hes substantial voting right [for example above 35%) effectively controlling the company | BG48: 64
A49: 47 | B49: 32 | C49: Female | D49: Black | E49: https://drive.google.com/file/d/1RfKZtxTw8dX68oLaA1PkrF8yduCpUM9O/view?usp=drive_link | F49: Pefer Jacebade | G49: Bangking / Marketing | H49: Adeosnopeyemi23@gmail.com | I49: None | J49: 08153143011 | K49: Keystone Bank Limited | L49: 11 Month | M49: Brawch Manager | N49: 26 Years | O49: Degree plus professional certificates | P49: 11 Month | Q49: Medium (Between $xx and $xx) | R49: Somewhat Disagree | S49: Somewhat Disagree | T49: Somewhat Disagree | U49: Agree | V49: Neutral | W49: Somewhat Agree | X49: Strongly Agree | Y49: Agree | Z49: Somewhat Agree | AA49: Agree | AC49: Strongly Agree | AD49: Disagree | AE49: Somewhat Disagree | AF49: Somewhat Disagree | AG49: Strongly Disagree | AI49: Disagree | AJ49: Disagree | AK49: Agree | AL49: Disagree | AM49: None | AN49: Agree | AO49: Disagree | AP49: Agree | AQ49: Somewhat Agree | AR49: Somewhat disagree | AS49: Disagree | AT49: Disagree | AU49: 8 | AV49: 4 | AW49: 4 | AX49: Low | AY49: i Don.t Know | AZ49: No | BB49: 3 | BD49: CEO | BF49: No | BG49: 57
A50: 48 | B50: 47 | C50: Female | D50: White | E50: https://drive.google.com/file/d/1zo4QE9Mn4LIYamLmLAettgJNk6i1-znY/view?usp=drive_link | F50: Vgombah prscilla ays | G50: Banker/Marketar | H50: Yuu3y@gmail.com | J50: 08130396823 | K50: Keystone Bank Limited | L50: 8 Month | M50: Branceh Manager | N50: 23 Years | O50: Degree plus professional certificates | P50: 8 Month | Q50: Medium (Between $xx and $xx) | R50: Strongly Agree | S50: Somewhat Agree | T50: Somewhat Disagree | U50: Disagree | V50: Agree | W50: Agree | X50: Somewhat Agree | Y50: Neutral | Z50: Somewhat Disagree | AA50: Neutral | AC50: Agree | AD50: Neutral | AE50: Agree | AF50: Disagree | AG50: Disagree | AH50: Somewhat Agree | AI50: Neutral | AJ50: Disagree | AK50: Somewhat Agree | AL50: Somewhat Agree | AN50: Strongly Agree | AO50: Somewhat Disagree | AP50: Neutral | AQ50: Somewhat Agree | AR50: Somewhat Agree | AS50: Agree | AT50: Somewhat Disagree | AU50: 8 | AV50: 4 | AW50: 4 | AX50: High | AY50: Average | AZ50: Yes | BB50: 4 | BD50: CEO | BE50: The largest sharaholders hes substantial voting right [for example above 35%) effectively controlling the company | BF50: No | BG50: 55
A51: 49 | B51: 26 | C51: Female | D51: White | E51: https://drive.google.com/file/d/1GJxziUB8BrGdUuENDIWDaVp7CvrjKmxI/view?usp=drive_link | F51: ADADBI Ikwuka | G51: Marketing | H51: adaobikoli@kysknebanking.com | I51: None | J51: 08039181402 | K51: Keystone Bank Limited | L51: 2 years | M51: Kinguy Akporohwo | O51: Degree holder | P51: 10 years | Q51: Medium (Between $xx and $xx) | R51: Strongly Agree | S51: Strongly Agree | T51: Disagree | V51: Strongly Agree | W51: Strongly Agree | X51: Strongly Agree | Y51: Disagree | Z51: Disagree | AA51: Disagree | AB51: None | AC51: Disagree | AD51: Disagree | AE51: Disagree | AF51: Disagree | AG51: Disagree | AH51: Disagree | AI51: Strongly Disagree | AJ51: Strongly Disagree | AK51: Disagree | AL51: Disagree | AM51: No | AN51: Strongly Agree | AO51: Strongly Disagree | AP51: Strongly Agree | AQ51: Agree | AR51: Disagree | AS51: Disagree | AT51: Disagree | AU51: 8 | AV51: 4 | AW51: 4 | AX51: High | AY51: High | AZ51: No | BA51: No | BB51: 3 | BD51: CEO | BE51: The largest sharaholders hes substantial voting right [for example above 35%) effectively controlling the company | BF51: No | BG51: 37
A52: 50 | B52: 27 | C52: Female | D52: Black | E52: https://drive.google.com/file/d/1sduoGJmlUj8evfspij_E_wVRCM5nSWGr/view?usp=drive_link | F52: Mera Nneta Deiday | G52: Banker/ pflaronshit if Officer | H52: mentnnekq@gmail.com | I52: 6 | J52: 08142076386 | K52: Keystone Bank Limited LTD | L52: 4 years | M52: Kinguy Akporohwo | N52: 28 Years | O52: Degree holder | P52: 4 years | Q52: Medium (Between $xx and $xx) | R52: Strongly Agree | S52: Neutral | T52: Agree | U52: Agree | V52: Agree | W52: Somewhat Disagree | X52: Strongly Agree | Y52: Agree | Z52: Disagree | AA52: Strongly Disagree | AC52: Strongly Disagree | AD52: Strongly Disagree | AE52: Strongly Disagree | AF52: Strongly Disagree | AG52: Strongly Disagree | AH52: Strongly Disagree | AI52: Strongly Disagree | AJ52: Disagree | AK52: Strongly Disagree | AL52: Disagree | AN52: Strongly Agree | AO52: Agree | AP52: Agree | AQ52: Agree | AR52: Disagree | AS52: Disagree | AT52: Disagree | AU52: 4 | AV52: 4 | AX52: High | AY52: High | AZ52: No | BB52: 4 | BC52: Lawal Jibrin Ahmed, Alihaji Unara Moddo,Olaniran Otatin Ka, Acletemi Odusanya,Tijgani Aliys Ma Dahiq chad | BD52: Chairman | BE52: The largest sharaholders hes substantial voting right [for example above 35%) effectively controlling the company | BG52: 73
A53: 51 | B53: 50 | C53: Female | D53: Black | E53: https://drive.google.com/file/d/165KeJ3rB6pL2TpRWoa-hiYL7OFNa0NeI/view?usp=drive_link | F53: Olivew A Dolor | G53: Relationship Manager | H53: dolorohveth@gmail.com | I53: None | J53: 07034725220 | K53: Keystone Bank | L53: 3 Month | M53: Branceh Manager | N53: 27 Years | O53: Degree holder | P53: 3 Month | R53: Agree | S53: Agree | U53: Agree | V53: Agree | W53: Agree | Y53: Strongly Agree | Z53: Disagree | AA53: Disagree | AB53: None | AC53: Disagree | AD53: Disagree | AE53: Disagree | AF53: Disagree | AH53: Disagree | AI53: Disagree | AJ53: Disagree | AK53: Disagree | AL53: Disagree | AM53: None | AN53: Agree | AO53: Disagree | AP53: Agree | AQ53: Agree | AR53: Disagree | AS53: Neutral | AT53: Disagree | AU53: 6 | AV53: 3 | AW53: 3 | AX53: Extremely High | AY53: High | AZ53: No | BB53: 4 | BD53: CEO | BE53: Ownership is diffuse with no controiling shareholder | BF53: None | BG53: 46
A54: 52 | B54: 31 | C54: Female | D54: White | E54: https://drive.google.com/file/d/1IG9HBoVg3SfbHsC5FmNeVjBTXrvlof5B/view?usp=drive_link | F54: Paul Taraul | G54: Bamlaer/Feuer | H54: jatupaul@yahoo.com | I54: None | J54: 08063596760 | K54: United Bank For Africa | L54: 3 years | M54: Operation Manager | N54: 28 Years | O54: HND holder | P54: 3 years | Q54: Large (Between $xx and $xx) | R54: Somewhat Agree | T54: Strongly Agree | U54: Somewhat Agree | V54: Strongly Agree | W54: Strongly Agree | X54: Agree | Y54: Strongly Disagree | Z54: Strongly Disagree | AA54: Strongly Disagree | AB54: None | AC54: Strongly Disagree | AD54: Strongly Disagree | AE54: Strongly Disagree | AF54: Strongly Disagree | AH54: Somewhat Disagree | AI54: Strongly Disagree | AJ54: Strongly Disagree | AK54: Disagree | AL54: Disagree | AN54: Strongly Agree | AO54: Strongly Disagree | AP54: Somewhat Agree | AQ54: Strongly Agree | AR54: Somewhat Disagree | AS54: Somewhat Disagree | AT54: Somewhat Disagree | AU54: 14 | AV54: 2 | AW54: 2 | AX54: Extremely High | AY54: Extremely High | AZ54: No | BB54: 4 | BD54: CEO | BE54: The largest sharaholders hes substantial voting right [for example above 35%) effectively controlling the company | BF54: No | BG54: 62
A55: 53 | B55: 29 | C55: Male | D55: White | E55: https://drive.google.com/file/d/1xR1AVqNGr_u8F65g6V0pjxLM2qf62WGH/view?usp=drive_link | F55: Paul Agbaji | G55: Banker/ Customar Care | H55: ayajpaul27@gmail.com | I55: 8 | J55: 08122458890 | K55: Keystone Bank | L55: 10 years | M55: Team head | N55: 36 Years | O55: Masters holder | P55: 10 years | Q55: Large (Between $xx and $xx) | R55: Agree | S55: Strongly Agree | T55: Agree | U55: Agree | V55: Agree | W55: Agree | X55: Strongly Agree | Y55: Disagree | Z55: Disagree | AA55: Disagree | AC55: Disagree | AD55: Disagree | AE55: Disagree | AF55: Agree | AG55: Disagree | AH55: Somewhat Agree | AI55: Disagree | AJ55: Disagree | AK55: Strongly Disagree | AL55: Disagree | AN55: Agree | AO55: Disagree | AP55: Agree | AQ55: Agree | AR55: Disagree | AS55: Somewhat Agree | AT55: Somewhat Agree | AU55: 8 | AV55: 4 | AW55: 4 | AX55: High | AY55: Extremely High | AZ55: No | BB55: 4 | BD55: CEO | BE55: The largest sharaholders hes substantial voting right [for example above 35%) effectively controlling the company | BG55: 67
A56: 54 | B56: 50 | C56: Male | D56: Black | E56: https://drive.google.com/file/d/1QbR47phxvGzkYpHxzJf3ixj8yM5bHHeU/view?usp=drive_link | F56: Akinloge Folashade | G56: Baulaing / Teller | H56: akielayefdashade@gmail.com | I56: N/A | J56: 07060461938 | K56: Keystone Bank | L56: 1 years | M56: Branceh Manager | N56: 25 Years | O56: Degree holder | P56: 1 years | Q56: Medium (Between $xx and $xx) | R56: Agree | S56: Agree | T56: Disagree | U56: Agree | V56: Agree | W56: Strongly Agree | X56: Disagree | Y56: Strongly Disagree | Z56: Disagree | AA56: Strongly Disagree | AB56: Strongly Disagree | AC56: Disagree | AD56: Strongly Disagree | AE56: Disagree | AF56: Strongly Disagree | AG56: Strongly Disagree | AH56: Disagree | AI56: Agree | AJ56: Neutral | AK56: Disagree | AL56: Neutral | AM56: None | AN56: Strongly Agree | AO56: Disagree | AP56: Agree | AQ56: Neutral | AR56: Neutral | AS56: Neutral | AT56: Disagree | AU56: 8 | AV56: 4 | AW56: 4 | AX56: High | AY56: High | AZ56: Yes | BA56: No | BD56: CEO | BE56: The largest sharaholders hes substantial voting right [for example above 35%) effectively controlling the company | BG56: 42
A57: 55 | B57: 42 | C57: Female | D57: White | E57: https://drive.google.com/file/d/11uexkgLdfr75VvcZX0JocPhnkIwfdCBk/view?usp=drive_link | F57: Oche Emmanuel | G57: Banking/Auditor | H57: emmanueloch223@gmail.com | I57: 1 | J57: 08032477944 | K57: Keystone Bank | L57: 7 years | M57: Head of Operations | N57: 34 years | O57: Degree holder | P57: 10 years | Q57: Large (Between $xx and $xx) | R57: Agree | S57: Somewhat Agree | T57: Somewhat Disagree | U57: Somewhat Disagree | V57: Strongly Agree | W57: Strongly Agree | X57: Agree | Y57: Agree | Z57: Somewhat Disagree | AA57: Somewhat Disagree | AB57: No | AC57: Disagree | AD57: Somewhat Disagree | AE57: Disagree | AF57: Disagree | AG57: Strongly Disagree | AH57: Somewhat Disagree | AI57: Somewhat Disagree | AJ57: Somewhat Disagree | AK57: Disagree | AL57: Somewhat Disagree | AM57: No | AN57: Strongly Agree | AO57: Disagree | AP57: Strongly Agree | AQ57: Somewhat Agree | AR57: Somewhat Disagree | AS57: Somewhat Disagree | AT57: Disagree | AU57: 10 | AV57: 4 | AW57: 4 | AX57: Extremely High | AY57: Extremely High | BD57: CEO | BE57: The largest sharaholders hes substantial voting right [for example above 35%) effectively controlling the company | BG57: 65
A58: 56 | B58: 28 | C58: Male | D58: White | E58: https://drive.google.com/file/d/1iYUH64MYCBieu37BS3lE4MdOUj2N894c/view?usp=drive_link | F58: Laraba Paul | G58: Banking/Sales Rep | H58: larabapaulango123@gmail.com | I58: 8 | J58: 08065657512 | K58: GT Bank | L58: 12 years | M58: Regional Manager | N58: 41 years | O58: Masters holder | P58: 15 years | Q58: Large (Between $xx and $xx) | R58: Strongly Agree | S58: Somewhat Agree | T58: Somewhat Disagree | U58: Somewhat Disagree | V58: Agree | W58: Strongly Agree | X58: Somewhat Agree | Y58: Somewhat Agree | Z58: Disagree | AA58: Somewhat Disagree | AC58: Disagree | AD58: Disagree | AE58: Disagree | AF58: Strongly Disagree | AG58: Somewhat Disagree | AH58: Strongly Disagree | AI58: Disagree | AJ58: Somewhat Disagree | AK58: Disagree | AL58: Somewhat Disagree | AM58: No | AN58: Strongly Agree | AO58: Disagree | AP58: Agree | AQ58: Agree | AR58: Neutral | AS58: Neutral | AT58: Somewhat Disagree | AX58: High | AY58: Extremely High | AZ58: No | BD58: CEO | BE58: The largest sharaholders hes substantial voting right [for example above 35%) effectively controlling the company | BG58: 61
A59: 57 | B59: 35 | C59: Female | D59: Hispanic | E59: https://drive.google.com/file/d/1OXdePRWZ3H1jChi_y-0TyqONbJA67WGF/view?usp=drive_link | F59: Emmanuel Nnyuta | G59: Bank/Sales and Marketing | H59: nnyutaemmanuel@yahoo.com | I59: Head Sales | J59: 09026657314 | K59: Wema Bank | L59: 5 years | M59: Head Sales & Marketing Department | N59: 27 years | O59: Degree holder | P59: 5 years | Q59: Large (Between $xx and $xx) | R59: Strongly Agree | S59: Somewhat Agree | T59: Somewhat Disagree | U59: Somewhat Disagree | V59: Strongly Agree | W59: Strongly Agree | X59: Agree | Y59: Agree | Z59: Disagree | AA59: Somewhat Disagree | AB59: No | AC59: Disagree | AD59: Disagree | AE59: Somewhat Disagree | AF59: Disagree | AG59: Disagree | AH59: Somewhat Disagree | AI59: Disagree | AJ59: Somewhat Disagree | AK59: Somewhat Disagree | AL59: Somewhat Disagree | AM59: No | AN59: Strongly Agree | AO59: Disagree | AP59: Agree | AQ59: Agree | AR59: Somewhat Disagree | AS59: Somewhat Disagree | AT59: Somewhat Disagree | AX59: Extremely High | AY59: High | AZ59: Nil | BD59: CEO | BE59: The largest sharaholders hes substantial voting right [for example above 35%) effectively controlling the company | BF59: No | BG59: 67
A60: 58 | B60: 39 | C60: Female | D60: White | E60: https://drive.google.com/file/d/12anI2H-KHJCPoqdvw8R8c1c1li3uIthp/view?usp=drive_link | F60: Stephanie Loifunle | G60: Banker/Sales & Marketing | H60: stephanieloifunle100@gmail.com | I60: None | J60: 07032917904 | K60: Union Bank | L60: 2 years | M60: Head Sales | N60: 28 years | O60: HND holder | P60: 2 years | Q60: Large (Between $xx and $xx) | R60: Strongly Agree | S60: Somewhat Agree | T60: Somewhat Disagree | U60: Somewhat Disagree | V60: Agree | W60: Strongly Agree | X60: Agree | Y60: Agree | Z60: Disagree | AA60: Somewhat Disagree | AB60: Nil | AC60: Disagree | AD60: Somewhat Disagree | AE60: Disagree | AF60: Strongly Disagree | AG60: Disagree | AH60: Somewhat Disagree | AI60: Somewhat Disagree | AJ60: Somewhat Disagree | AK60: Somewhat Disagree | AL60: Somewhat Disagree | AM60: No | AN60: Agree | AO60: Disagree | AP60: Agree | AQ60: Agree | AR60: Somewhat Disagree | AS60: Somewhat Disagree | AT60: Somewhat Disagree | AX60: Extremely High | AY60: High | AZ60: No | BD60: CEO | BE60: The largest sharaholders hes substantial voting right [for example above 35%) effectively controlling the company | BF60: No | BG60: 58
A61: 59 | B61: 31 | C61: Male | D61: Black | E61: https://drive.google.com/file/d/1thHrqsTyAjNB4SVRst8EPjYokZTyxGb1/view?usp=drive_link | F61: Elizabeth Udeh | G61: Banking/Teller | H61: udehelizabeth@gmail.com | I61: Nil | J61: 08080221687 | K61: United Bank For Africa | L61: 5 years | M61: Head Cashier | N61: 24 years | O61: HND holder | P61: 5 years | Q61: Large (Between $xx and $xx) | R61: Strongly Agree | S61: Somewhat Agree | T61: Somewhat Disagree | U61: Disagree | V61: Strongly Agree | W61: Strongly Agree | X61: Agree | Y61: Agree | Z61: Somewhat Disagree | AA61: Disagree | AB61: No | AC61: Disagree | AD61: Somewhat Disagree | AE61: Disagree | AF61: Disagree | AG61: Disagree | AH61: Somewhat Disagree | AI61: Disagree | AJ61: Disagree | AK61: Disagree | AL61: Somewhat Disagree | AM61: No | AN61: Strongly Agree | AO61: Disagree | AP61: Agree | AQ61: Agree | AR61: Somewhat Disagree | AS61: Somewhat Disagree | AT61: Somewhat Disagree | AU61: 12 | AV61: 4 | AW61: 4 | AX61: High | AY61: Extremely High | AZ61: No | BB61: 3 | BD61: CEO | BE61: The largest sharaholders hes substantial voting right [for example above 35%) effectively controlling the company | BG61: 71
A62: 60 | B62: 38 | C62: Male | D62: White | E62: https://drive.google.com/file/d/1nTT6Pf7cq8v1mCOeqUd9H4BIr6RxQE8X/view?usp=drive_link | F62: Sadeeq Abubakar | G62: Banker/Auditor | H62: abubakarsadeeq@yahoo.com | I62: 2 | J62: 09019001569 | K62: First Bank Plc | L62: 8 years | M62: Regional Head | N62: 42 years | O62: Masters holder | P62: 15 years | Q62: Large (Between $xx and $xx) | R62: Strongly Agree | S62: Agree | T62: Somewhat Disagree | U62: Disagree | V62: Strongly Agree | W62: Strongly Agree | X62: Agree | Y62: Strongly Agree | Z62: Disagree | AA62: Disagree | AB62: No | AC62: Disagree | AD62: Somewhat Disagree | AE62: Disagree | AF62: Disagree | AG62: Strongly Disagree | AH62: Strongly Disagree | AI62: Somewhat Disagree | AJ62: Disagree | AK62: Somewhat Disagree | AL62: Somewhat Disagree | AM62: No | AN62: Strongly Agree | AO62: Strongly Disagree | AP62: Strongly Agree | AQ62: Agree | AR62: Somewhat Disagree | AS62: Somewhat Disagree | AT62: Neutral | AU62: 12 | AV62: 4 | AW62: 4 | AX62: Extremely High | AY62: Extremely High | AZ62: No | BB62: 4 | BC62: Olusegun Adebayo | BD62: CEO | BE62: The largest sharaholders hes substantial voting right [for example above 35%) effectively controlling the company | BF62: No | BG62: 65
A63: 61 | B63: 30 | C63: Female | D63: Black | E63: https://drive.google.com/file/d/1qHqvri1ZaLnEiDCkk96YCAVWOm_GhX_E/view?usp=drive_link | F63: Oluwaseyi Asonwo | G63: Banking/Customer Care | H63: asonwoseyi@gmail.com | I63: Nil | J63: 08131280965 | K63: Wema Bank | L63: 7 years | M63: Operation Manager | N63: 33 years | O63: Degree holder | P63: 7 years | Q63: Large (Between $xx and $xx) | R63: Strongly Agree | S63: Somewhat Agree | T63: Somewhat Disagree | U63: Somewhat Disagree | V63: Strongly Agree | W63: Strongly Agree | X63: Agree | Y63: Agree | Z63: Somewhat Disagree | AA63: Somewhat Disagree | AB63: No | AC63: Disagree | AD63: Disagree | AE63: Disagree | AF63: Somewhat Disagree | AG63: Somewhat Disagree | AH63: Somewhat Disagree | AI63: Somewhat Disagree | AJ63: Disagree | AK63: Somewhat Disagree | AL63: Somewhat Disagree | AM63: No | AN63: Strongly Agree | AO63: Disagree | AP63: Agree | AQ63: Agree | AR63: Somewhat Disagree | AS63: Somewhat Disagree | AT63: Somewhat Disagree | AX63: High | AY63: Extremely High | AZ63: No | BD63: CEO | BE63: The largest sharaholders hes substantial voting right [for example above 35%) effectively controlling the company | BF63: No | BG63: 88
A64: 62 | B64: 26 | C64: Male | D64: Hispanic | E64: https://drive.google.com/file/d/1-0sgt0KQx55zDxe6B2anSgySs_Msr_dY/view?usp=drive_link | F64: Ody Christians | G64: Banker/CSO | H64: odychristians1@gmail.com | I64: None | J64: 08105974939 | K64: Keystone Bank | L64: 2 months | M64: Nuhu Ad Daniel | N64: 27 years | O64: Degree plus professional certificates | Q64: Large (Between $xx and $xx) | R64: Strongly Agree | S64: Agree | T64: Neutral | U64: Somewhat Agree | V64: Agree | W64: Strongly Agree | X64: Agree | Y64: Neutral | Z64: Disagree | AA64: Disagree | AB64: No | AC64: Disagree | AD64: Disagree | AE64: Disagree | AF64: Strongly Disagree | AG64: Disagree | AH64: Strongly Disagree | AI64: Disagree | AJ64: Disagree | AK64: Disagree | AL64: Strongly Disagree | AM64: Nil | AN64: Agree | AO64: Neutral | AP64: Neutral | AQ64: Agree | AR64: Neutral | AS64: Agree | AT64: Disagree | AU64: 4 | AV64: 2 | AW64: 2 | AX64: Extremely High | AY64: High | AZ64: No | BA64: Nil | BB64: 4 | BD64: Board | BE64: Two or more shareholders control the company | BG64: 55
A65: 63 | B65: 44 | C65: Male | D65: Black | E65: https://drive.google.com/file/d/1Jz3t4n5i7FGJRasKwet6FEqcX_AQ9h4H/view?usp=drive_link | F65: N/A | G65: Banker | H65: N/A | I65: 5 | J65: N/A | K65: Keystone Bank | L65: 3 years | M65: N/A | N65: N/A | O65: Degree plus professional certificates | P65: 3 years | Q65: Medium (Between $xx and $xx) | R65: Neutral | S65: Neutral | T65: Neutral | U65: Neutral | V65: Neutral | W65: Neutral | X65: Somewhat Agree | Y65: Neutral | Z65: Neutral | AA65: Neutral | AC65: Somewhat Disagree | AD65: Disagree | AE65: Disagree | AF65: Disagree | AG65: Strongly Disagree | AH65: Disagree | AI65: Disagree | AJ65: Disagree | AK65: Disagree | AL65: Disagree | AN65: Agree | AO65: Somewhat Agree | AP65: Agree | AQ65: Agree | AR65: Neutral | AS65: Neutral | AT65: Neutral | AU65: N/A | AV65: N/A | AW65: N/A | AX65: Average | AY65: Maybe | AZ65: Neutral | BB65: N/A | BC65: N/A | BD65: Chairman | BE65: Neutral | BF65: No | BG65: 78
A66: 64 | B66: 29 | C66: Female | D66: White | E66: https://drive.google.com/file/d/1rrAoiAFOyk1Kc6k2Q6aVdGoWipC8CP0-/view?usp=drive_link | F66: Odo Chidinma Henrietta | G66: Relationship Officer | H66: henrietta.odo@kusfbanking.com | I66: None | J66: 08131219062 | K66: Keystone Bank | L66: 8 months | M66: Branch Manager | N66: 27 years | O66: Degree holder | P66: None | Q66: Medium (Between $xx and $xx) | R66: Agree | S66: Agree | T66: Somewhat Agree | U66: Agree | V66: Agree | W66: Agree | X66: Agree | Y66: Agree | Z66: Agree | AA66: Agree | AI66: Disagree | AJ66: Disagree | AK66: Agree | AL66: Neutral | AM66: None | AU66: 8 | AV66: 2 | AW66: 2 | AX66: Extremely High | AY66: Extremely High | AZ66: No | BB66: 5 | BD66: CEO | BE66: The largest sharaholders hes substantial voting right [for example above 35%) effectively controlling the company | BF66: No | BG66: 49
A67: 65 | B67: 39 | C67: Female | D67: White | E67: https://drive.google.com/file/d/18h_CKJfj9nDwhyvlima8q5-GzQRWuXCk/view?usp=drive_link | F67: Peter Jacob Ade | G67: Banking/Marketing | H67: adeomopejeni23@gmail.com | I67: None | J67: 08153143011 | K67: Keystone Bank Limited | L67: 11 months | M67: Branch Manager | N67: 26 years | O67: Degree plus professional certificates | P67: 11 month | Q67: Medium (Between $xx and $xx) | R67: Somewhat Disagree | S67: Somewhat Disagree | T67: Somewhat Agree | U67: Agree | V67: Neutral | W67: Somewhat Agree | X67: Strongly Agree | Y67: Agree | Z67: Somewhat Agree | AA67: Agree | AC67: Strongly Agree | AD67: Disagree | AE67: Somewhat Disagree | AF67: Somewhat Disagree | AG67: Strongly Agree | AI67: Disagree | AJ67: Disagree | AK67: Agree | AL67: Disagree | AN67: Agree | AO67: Disagree | AP67: Agree | AQ67: Somewhat Agree | AR67: Somewhat Disagree | AS67: Disagree | AT67: Disagree | AU67: 8 | AV67: 4 | AW67: 4 | AX67: Low | AY67: I don't know | AZ67: No | BB67: 3 | BD67: CEO | BF67: No | BG67: 54
A68: 66 | B68: 34 | C68: Male | D68: White | E68: https://drive.google.com/file/d/1FoOWORnObJ59XYWqueNlBkAkVeygYT-j/view?usp=drive_link | F68: Uzombah Priscilla Iyin | G68: Banker/Marketer | H68: iyuzy@gmail.com | J68: 08130396823 | K68: Keystone Bank | L68: 8 months | M68: Branch Manager | N68: 23 years | O68: Degree plus professional certificates | P68: 8 month | Q68: Medium (Between $xx and $xx) | R68: Strongly Agree | S68: Somewhat Agree | T68: Somewhat Agree | U68: Disagree | V68: Agree | W68: Agree | X68: Somewhat Agree | Y68: Neutral | Z68: Somewhat Disagree | AA68: Neutral | AC68: Agree | AD68: Neutral | AE68: Agree | AF68: Disagree | AG68: Disagree | AH68: Somewhat Agree | AI68: Neutral | AJ68: Disagree | AK68: Somewhat Agree | AL68: Somewhat Agree | AN68: Strongly Agree | AO68: Somewhat Disagree | AP68: Neutral | AQ68: Somewhat Agree | AR68: Somewhat Agree | AS68: Agree | AT68: Somewhat Disagree | AU68: 8 | AV68: 4 | AW68: 4 | AX68: High | AY68: Average | AZ68: Yes | BB68: 4 | BD68: CEO | BE68: The largest sharaholders hes substantial voting right [for example above 35%) effectively controlling the company | BF68: No | BG68: 64
A69: 67 | B69: 53 | C69: Female | D69: White | E69: https://drive.google.com/file/d/1katV_c7HHLLSGtpPlPujjxZjfSQ8GIT3/view?usp=drive_link | F69: Mercy Thelma Friday | G69: Banker/Relationship Officer | H69: mercythelmafriday@gmail.com | I69: 8 | J69: 08142276286 | K69: Keystone Bank Limited | L69: 4 years | M69: Kingsley Aporahino | N69: 28 years | O69: Degree holder, Degree plus professional certificates | P69: 4 years | Q69: Medium (Between $xx and $xx) | R69: Strongly Agree | S69: Neutral | T69: Agree | U69: Agree | V69: Agree | W69: Somewhat Disagree | X69: Strongly Agree | Y69: Agree | Z69: Disagree | AA69: Strongly Disagree | AC69: Strongly Disagree | AD69: Strongly Disagree | AE69: Strongly Disagree | AF69: Strongly Disagree | AG69: Strongly Disagree | AH69: Strongly Disagree | AI69: Strongly Disagree | AJ69: Disagree | AK69: Strongly Disagree | AL69: Disagree | AN69: Strongly Agree | AO69: Agree | AP69: Agree | AQ69: Agree | AR69: Disagree | AS69: Disagree | AT69: Disagree | AU69: 4 | AV69: 4 | AX69: High | AY69: High | AZ69: No | BB69: 4 | BC69: Liwal Jibrin Ahmed, Khaji Umaru Mdddito, Olaniran Olatunde, Adefemi Odusanya, Tijjani Aliyu, Ada Daniel Chadi | BD69: Chairman | BE69: The largest sharaholders hes substantial voting right [for example above 35%) effectively controlling the company | BG69: 77
A70: 68 | B70: 30 | C70: Female | D70: White | E70: https://drive.google.com/file/d/1Vwm2dbdcPK3H756FBfyyLQ1IPdioQhbz/view?usp=drive_link | F70: Oliveth N. Dolor | G70: Relationship Manager | H70: doloroliveth@gmail.com | J70: 07034725220 | K70: Keystone Bank | L70: 3 months | M70: Branch Manager | N70: 27 years | O70: Degree holder | P70: 3 month | R70: Agree | S70: Agree | U70: Agree | V70: Agree | W70: Agree | Y70: Somewhat Agree | Z70: Disagree | AA70: Disagree | AB70: None | AC70: Disagree | AD70: Disagree | AE70: Disagree | AF70: Disagree | AG70: Strongly Disagree | AH70: Disagree | AI70: Disagree | AJ70: Disagree | AK70: Disagree | AL70: Disagree | AM70: None | AN70: Agree | AO70: Disagree | AP70: Agree | AQ70: Agree | AR70: Disagree | AS70: Neutral | AT70: Disagree | AU70: 6 | AV70: 3 | AW70: 3 | AX70: Extremely High | AY70: High | AZ70: No | BB70: 4 | BD70: CEO | BE70: Ownership is diffuse with no controlling shareholder | BF70: None | BG70: 78
A71: 69 | B71: 28 | C71: Female | D71: White | E71: https://drive.google.com/file/d/1rPsbWeuDLcnK11bDLWTF9CjpW9B4qVDe/view?usp=drive_link | F71: Paul Jatau | G71: Banker/Teller | H71: jataupaul@yahoo.com | I71: None | J71: 08063596760 | K71: United Bank for Africa | L71: 3 years | M71: Operation Manager | N71: 28 years | O71: HND holder | P71: 3 years | Q71: Large (Between $xx and $xx) | R71: Somewhat Agree | S71: Agree | T71: Strongly Agree | U71: Somewhat Agree | V71: Strongly Agree | W71: Strongly Agree | X71: Agree | Y71: Strongly Disagree | Z71: Strongly Disagree | AA71: Strongly Disagree | AB71: None | AC71: Strongly Disagree | AD71: Strongly Disagree | AE71: Strongly Disagree | AF71: Strongly Disagree | AH71: Somewhat Disagree | AI71: Strongly Disagree | AJ71: Strongly Disagree | AK71: Disagree | AL71: Disagree | AN71: Strongly Agree | AO71: Strongly Disagree | AP71: Somewhat Agree | AQ71: Strongly Agree | AR71: Somewhat Disagree | AS71: Somewhat Disagree | AT71: Somewhat Disagree | AU71: 14 | AV71: 2 | AW71: 2 | AX71: Extremely High | AY71: Extremely High | AZ71: No | BB71: 4 | BD71: CEO | BE71: The largest sharaholders hes substantial voting right [for example above 35%) effectively controlling the company | BF71: No | BG71: 43
A72: 70 | B72: 30 | C72: Female | D72: Hispanic | E72: https://drive.google.com/file/d/17Np9YPQVv-eah3-LqTVV1i9HZq72AW8Z/view?usp=drive_link | F72: Paul Agaji | G72: Banker/Customer Care | H72: agajipaul27@gmail.com | I72: 8 | J72: 08122458890 | K72: Keystone Bank | L72: 10 years | M72: Team Head | N72: 36 years | O72: Masters holder | P72: 10 years | Q72: Large (Between $xx and $xx) | R72: Agree | S72: Strongly Agree | T72: Agree | U72: Agree | V72: Agree | W72: Agree | X72: Strongly Agree | Y72: Disagree | Z72: Disagree | AA72: Disagree | AC72: Disagree | AD72: Disagree | AE72: Disagree | AF72: Agree | AG72: Disagree | AH72: Somewhat Agree | AI72: Disagree | AJ72: Disagree | AK72: Strongly Disagree | AL72: Disagree | AN72: Agree | AO72: Disagree | AP72: Agree | AQ72: Agree | AR72: Disagree | AS72: Somewhat Agree | AT72: Somewhat Agree | AU72: 8 | AV72: 4 | AW72: 4 | AX72: High | AY72: Extremely High | AZ72: No | BB72: 4 | BD72: CEO | BE72: The largest sharaholders hes substantial voting right [for example above 35%) effectively controlling the company | BG72: 48
A73: 71 | B73: 50 | C73: Female | D73: White | E73: https://drive.google.com/file/d/189dQGYKdfOjtRjHv4TDXbgah7d7tplUC/view?usp=drive_link | F73: Dr. Sadiq Shuaib | G73: Nexim Bank / Operations Manager | H73: sadiqshuaib@gmail.com | I73: 24 | J73: 08069226607 | K73: Nexim Bank | L73: 15 years | M73: Head of Operations | N73: 38 years | O73: PhD holder | P73: 19 years | Q73: Large (Between $xx and $xx) | R73: Agree | S73: Somewhat Agree | T73: Agree | U73: Somewhat Agree | V73: Agree | W73: Somewhat Agree | X73: Somewhat Agree | Y73: Somewhat Agree | Z73: Disagree | AA73: Somewhat Agree | AC73: Somewhat Disagree | AD73: Somewhat Agree | AE73: Disagree | AF73: Disagree | AG73: Disagree | AH73: Somewhat Disagree | AI73: Somewhat Agree | AJ73: Somewhat Disagree | AK73: Somewhat Agree | AL73: Somewhat Disagree | AN73: Somewhat Agree | AO73: Somewhat Agree | AP73: Somewhat Agree | AQ73: Agree | AR73: Somewhat Agree | AS73: Somewhat Agree | AT73: Agree | AU73: 9 | AV73: 3 | AW73: 3 | AX73: Extremely High | AY73: Extremely High | AZ73: No | BB73: 4 | BD73: Government | BF73: No | BG73: 95
A74: 72 | B74: 26 | C74: Female | D74: White | E74: https://drive.google.com/file/d/1qEcpur1_tNPOpp0EhhjgCp4JcQG__hDn/view?usp=drive_link | F74: Mary Michael | G74: Banker/Customer Care | H74: gebi22@yahoo.com | I74: None | J74: 08088102447 | K74: Fidelity Bank | L74: 5 years | M74: Customer Loyalty Head | N74: 29 years | O74: HND holder | Q74: Large (Between $xx and $xx) | R74: Agree | S74: Agree | T74: Agree | U74: Somewhat Agree | V74: Agree | W74: Agree | X74: Strongly Agree | Y74: Strongly Disagree | Z74: Somewhat Disagree | AA74: Somewhat Agree | AB74: None | AC74: Strongly Disagree | AD74: Somewhat Disagree | AE74: Agree | AF74: Somewhat Disagree | AG74: Disagree | AH74: Disagree | AI74: Somewhat Disagree | AJ74: Somewhat Disagree | AK74: Somewhat Disagree | AL74: Somewhat Disagree | AM74: None | AN74: Strongly Agree | AO74: Somewhat Disagree | AP74: Agree | AQ74: Agree | AR74: Somewhat Disagree | AS74: Somewhat Disagree | AT74: Somewhat Disagree | AU74: 3 | AV74: 1 | AW74: 2 | AX74: Extremely High | AY74: Extremely High | AZ74: No | BB74: 5 | BD74: CEO | BE74: The largest sharaholders hes substantial voting right [for example above 35%) effectively controlling the company | BF74: No | BG74: 51
A75: 73 | B75: 53 | C75: Male | D75: Black | E75: https://drive.google.com/file/d/1BP8LAZUqcHT3M5rrz2yCrqFjAE1vCbYg/view?usp=drive_link | F75: Obaseki Obia Agba | G75: Banker/Relationship Officer | H75: agbaobaseki@keystonebanking.com | I75: None | J75: 09035989346 | K75: Keystone Bank Limited | L75: 2 years, 8 months | M75: Victoria Akakgbiu | N75: 27 years | O75: Degree holder | Q75: Medium (Between $xx and $xx) | R75: Strongly Agree | S75: Agree | T75: Neutral | U75: Somewhat Agree | V75: Agree | W75: Strongly Agree | X75: Strongly Agree | Y75: Somewhat Agree | Z75: Somewhat Disagree | AA75: Disagree | AB75: Nill | AC75: Disagree | AD75: Strongly Disagree | AE75: Strongly Disagree | AF75: Disagree | AG75: Disagree | AH75: Disagree | AI75: Disagree | AJ75: Strongly Disagree | AK75: Disagree | AL75: Strongly Disagree | AM75: NIl | AN75: Agree | AO75: Disagree | AP75: Strongly Agree | AQ75: Agree | AR75: Disagree | AS75: Disagree | AT75: Disagree | AU75: 4 | AV75: 2 | AW75: 2 | AX75: Extremely High | AY75: High | AZ75: No | BA75: N/A | BD75: Board | BE75: Ownership is diffuse with no controlling shareholder | BG75: 75
A76: 74 | B76: 33 | C76: Female | D76: White | E76: https://drive.google.com/file/d/1XVdf5vjEsellHo-JEiHrePXkGVZhYQrv/view?usp=drive_link | F76: Zainab Ajuji | G76: Banking/Relationship Officer | H76: zainabajuji@keystonebankng.com | J76: 08039656290 | K76: Keystone Bank | L76: 9 years | M76: BM (Victoria Akag) | N76: 29 years | O76: Degree plus professional certificates | P76: 9 years | Q76: Medium (Between $xx and $xx) | R76: Strongly Agree | S76: Strongly Agree | T76: Neutral | U76: Strongly Agree | V76: Strongly Agree | W76: Agree | X76: Strongly Agree | Y76: Strongly Agree | Z76: Somewhat Disagree | AA76: Agree | AB76: N/A | AC76: Neutral | AD76: Disagree | AE76: Disagree | AF76: Disagree | AG76: Disagree | AH76: Disagree | AI76: Neutral | AJ76: Disagree | AK76: Disagree | AL76: Disagree | AN76: Strongly Agree | AO76: Agree | AP76: Agree | AQ76: Agree | AR76: Agree | AS76: Agree | AT76: Agree | AU76: 4 | AV76: 2 | AW76: 2 | AX76: High | AY76: Extremely High | AZ76: No | BA76: No | BB76: 4 | BD76: Board | BE76: Family owned business group of companies | BG76: 43
A77: 75 | B77: 27 | C77: Female | D77: White | E77: https://drive.google.com/file/d/17-maykXhiiEUtcK2VpWwSDtcx-emYGfj/view?usp=drive_link | F77: Iliya Joyce Habila | G77: Banker/Teller | H77: iliyajoyce90@gmail.com | J77: 08104010525 | K77: Keystone Bank | L77: 5 months | M77: Nwulu Adi David | N77: 27 years | O77: Degree plus professional certificates | P77: 2 years | Q77: Medium (Between $xx and $xx) | R77: Strongly Agree | S77: Agree | T77: Neutral | U77: Somewhat Agree | V77: Agree | W77: Strongly Agree | X77: Agree | Y77: Neutral | Z77: Disagree | AA77: Disagree | AB77: No | AC77: Disagree | AD77: Disagree | AE77: Strongly Disagree | AF77: Disagree | AG77: Strongly Disagree | AH77: Disagree | AI77: Disagree | AJ77: Disagree | AK77: Strongly Disagree | AL77: Strongly Disagree | AM77: NIl | AN77: Agree | AO77: Neutral | AP77: Neutral | AQ77: Agree | AR77: Neutral | AS77: Agree | AT77: Disagree | AU77: 4 | AV77: 2 | AW77: 2 | AX77: Extremely High | AY77: High | AZ77: No | BA77: Nil | BB77: 4 | BD77: Board | BE77: Two or more shareholders control the company | BG77: 60
A78: 76 | B78: 31 | C78: Female | D78: White | E78: https://drive.google.com/file/d/1QIv3VA6tucwgBtn_vInVH_zKmhAVzeVh/view?usp=drive_link | F78: Sylvester Amana | G78: Banking/Customer Care | H78: amahasylvester99@gmail.com | I78: 6 | J78: 09135670399 | K78: First Bank | L78: 6 years | M78: Operation Manager | N78: 32 years | O78: Degree holder | P78: 6 years | Q78: Large (Between $xx and $xx) | R78: Strongly Agree | S78: Somewhat Agree | T78: Somewhat Disagree | U78: Somewhat Disagree | V78: Agree | W78: Strongly Agree | X78: Strongly Agree | Y78: Agree | Z78: Disagree | AA78: Somewhat Disagree | AB78: No | AC78: Disagree | AD78: Disagree | AE78: Somewhat Disagree | AF78: Strongly Disagree | AG78: Strongly Disagree | AH78: Disagree | AI78: Somewhat Disagree | AJ78: Somewhat Disagree | AK78: Disagree | AL78: Somewhat Disagree | AM78: No | AN78: Strongly Agree | AO78: Somewhat Disagree | AP78: Agree | AQ78: Agree | AR78: Somewhat Disagree | AS78: Neutral | AT78: Somewhat Disagree | AX78: High | AY78: High | AZ78: No | BD78: CEO | BE78: The largest sharaholders hes substantial voting right [for example above 35%) effectively controlling the company | BF78: No | BG78: 58
A79: 77 | B79: 24 | C79: Male | D79: Black | E79: https://drive.google.com/file/d/13JXBBm5lrLzOVnYpVXma39vgOZKFEd1d/view?usp=drive_link | F79: Fred Igbaboa | G79: Banker/Sales Rep | H79: fredmeyreal@yahoo.com | I79: No | J79: 08069740012 | K79: Eco Bank | L79: 6 years | M79: Head of Sales | N79: 31 years | O79: Degree holder | P79: 8 years | Q79: Large (Between $xx and $xx) | R79: Strongly Agree | S79: Agree | T79: Somewhat Disagree | U79: Somewhat Disagree | V79: Strongly Agree | W79: Strongly Agree | X79: Strongly Agree | Y79: Somewhat Agree | Z79: Disagree | AA79: Somewhat Disagree | AB79: No | AC79: Disagree | AD79: Somewhat Disagree | AE79: Disagree | AF79: Disagree | AG79: Strongly Disagree | AH79: Disagree | AI79: Disagree | AJ79: Disagree | AK79: Somewhat Disagree | AL79: Somewhat Disagree | AN79: Agree | AO79: Disagree | AP79: Agree | AQ79: Agree | AR79: Somewhat Disagree | AS79: Somewhat Disagree | AT79: Somewhat Disagree | AU79: 13 | AX79: Extremely High | AY79: Extremely High | BD79: CEO | BE79: The largest sharaholders hes substantial voting right [for example above 35%) effectively controlling the company | BF79: No | BG79: 65
A80: 78 | B80: 41 | C80: Male | D80: Black | E80: https://drive.google.com/file/d/1v9nmJk0xDSR0a8YUavS6x18Cs6TxM1AY/view?usp=drive_link | F80: Nnamdi Dagsola | G80: Banker/Customer | H80: nnamdidagsola@gmail.com | I80: None | J80: 07035696760 | K80: Fidelity Bank | L80: 21 years | M80: Operation Head | N80: 24 years | O80: HND holder | P80: 4 years | Q80: Large (Between $xx and $xx) | R80: Agree | S80: Agree | T80: Somewhat Disagree | U80: Somewhat Disagree | V80: Strongly Agree | W80: Strongly Agree | X80: Agree | Y80: Somewhat Agree | Z80: Somewhat Disagree | AA80: Somewhat Disagree | AB80: No | AC80: Disagree | AD80: Somewhat Disagree | AE80: Somewhat Disagree | AF80: Disagree | AG80: Strongly Disagree | AH80: Somewhat Disagree | AI80: Disagree | AJ80: Somewhat Disagree | AK80: Disagree | AL80: Somewhat Disagree | AM80: No | AN80: Agree | AO80: Disagree | AP80: Agree | AQ80: Somewhat Agree | AR80: Somewhat Disagree | AS80: Somewhat Disagree | AT80: Somewhat Disagree | AX80: High | AY80: Extremely High | BD80: CEO | BE80: The largest sharaholders hes substantial voting right [for example above 35%) effectively controlling the company | BF80: No | BG80: 79
A81: 79 | B81: 26 | C81: Female | D81: White | E81: https://drive.google.com/file/d/1ORzSggL5HUFSy2SaIapdRCOpyOU7FWHF/view?usp=drive_link | F81: Ekanwe Thomas | G81: Banking/Teller | H81: ekanwethomas22@gmail.com | I81: None | J81: 08125102991 | K81: First Bank | L81: 4 years | M81: Head Cashier | N81: 26 years | O81: Degree holder | P81: 4 years | Q81: Large (Between $xx and $xx) | R81: Strongly Agree | S81: Somewhat Agree | T81: Somewhat Disagree | U81: Somewhat Disagree | V81: Strongly Agree | W81: Strongly Agree | X81: Agree | Y81: Somewhat Agree | Z81: Disagree | AA81: Somewhat Disagree | AB81: No | AC81: Disagree | AD81: Disagree | AE81: Somewhat Disagree | AF81: Disagree | AG81: Strongly Disagree | AH81: Somewhat Disagree | AI81: Disagree | AJ81: Disagree | AK81: Somewhat Disagree | AL81: Somewhat Disagree | AM81: No | AN81: Strongly Agree | AO81: Strongly Disagree | AP81: Strongly Agree | AQ81: Somewhat Agree | AR81: Somewhat Disagree | AS81: Somewhat Disagree | AT81: Somewhat Disagree | AU81: 10 | AV81: 4 | AW81: 4 | AX81: Extremely High | AY81: High | AZ81: No | BD81: CEO | BE81: The largest sharaholders hes substantial voting right [for example above 35%) effectively controlling the company | BF81: None | BG81: 52
A82: 80 | B82: 42 | C82: Female | D82: White | E82: https://drive.google.com/file/d/1qnBFANZ5Z3_06vrHw02Qt0mgiridYeX_/view?usp=drive_link | F82: Mafeng Gwallson | G82: Banking/Sales & Marketing | H82: gwallsonmafeng22@gmail.com | I82: 5 | J82: 08039220081 | K82: Jaiz Bank | L82: 4 years | M82: Branch Manager | N82: 39 years | O82: Masters holder | P82: 12 years | Q82: Large (Between $xx and $xx) | R82: Strongly Agree | S82: Agree | T82: Somewhat Disagree | U82: Somewhat Disagree | V82: Agree | W82: Strongly Agree | X82: Agree | Y82: Agree | Z82: Disagree | AA82: Somewhat Disagree | AB82: No | AC82: Disagree | AD82: Disagree | AE82: Somewhat Disagree | AF82: Disagree | AG82: Strongly Disagree | AH82: Somewhat Disagree | AI82: Somewhat Disagree | AJ82: Somewhat Disagree | AK82: Somewhat Disagree | AL82: Somewhat Disagree | AM82: No | AN82: Agree | AO82: Disagree | AP82: Agree | AQ82: Agree | AR82: Somewhat Disagree | AS82: Somewhat Disagree | AT82: Somewhat Disagree | AU82: 8 | AV82: 2 | AW82: 2 | AX82: Extremely High | AY82: Extremely High | BB82: 3 | BD82: CEO | BE82: The largest sharaholders hes substantial voting right [for example above 35%) effectively controlling the company | BF82: No | BG82: 68
A83: 81 | B83: 49 | C83: Female | D83: Black | E83: https://drive.google.com/file/d/1LvPnAvg6_DA0q4EwpNoGH6sbhV_nV-EK/view?usp=drive_link | F83: Glory James | G83: Banking/Customer Care | H83: jamesglory@yahoo.com | I83: None | J83: 09035999906 | K83: First Bank | L83: 6 years | M83: Operation Manager | N83: 31 years | O83: Degree holder | P83: 6 years | Q83: Large (Between $xx and $xx) | R83: Strongly Agree | S83: Agree | T83: Somewhat Disagree | U83: Somewhat Disagree | V83: Agree | W83: Strongly Agree | X83: Agree | Y83: Agree | Z83: Disagree | AA83: Somewhat Disagree | AB83: No | AC83: Disagree | AD83: Disagree | AE83: Somewhat Disagree | AF83: Disagree | AG83: Disagree | AH83: Somewhat Disagree | AI83: Somewhat Disagree | AJ83: Somewhat Disagree | AK83: Disagree | AL83: Somewhat Disagree | AM83: No | AN83: Agree | AO83: Disagree | AP83: Strongly Agree | AQ83: Agree | AR83: Somewhat Disagree | AS83: Disagree | AT83: Somewhat Disagree | AU83: 10 | AV83: 5 | AW83: 5 | AX83: Extremely High | AY83: High | AZ83: No | BB83: 3 | BD83: CEO | BE83: The largest sharaholders hes substantial voting right [for example above 35%) effectively controlling the company | BF83: No | BG83: 48
A84: 82 | B84: 31 | C84: Female | D84: White | E84: https://drive.google.com/file/d/1Za8sT2ZuqO7YJHQVwxpk7T_kH24j3h0d/view?usp=drive_link | F84: Tjay Mcduke | G84: Banking/Auditor | H84: mcduketjay@gmail.com | I84: 2 | J84: 08188202070 | K84: Eco Bank | L84: 7 years | M84: Branch Manager | N84: 35 years | O84: Degree holder | P84: 8 years | Q84: Large (Between $xx and $xx) | R84: Agree | S84: Strongly Agree | T84: Somewhat Disagree | U84: Somewhat Disagree | V84: Agree | W84: Strongly Agree | X84: Strongly Agree | Y84: Agree | Z84: Disagree | AA84: Somewhat Disagree | AB84: No | AC84: Strongly Disagree | AD84: Somewhat Disagree | AE84: Somewhat Disagree | AF84: Disagree | AG84: Strongly Disagree | AH84: Disagree | AI84: Somewhat Disagree | AJ84: Somewhat Disagree | AK84: Somewhat Disagree | AL84: Somewhat Disagree | AM84: No | AN84: Strongly Agree | AO84: Disagree | AP84: Strongly Agree | AQ84: Agree | AR84: Agree | AS84: Somewhat Disagree | AT84: Neutral | AU84: 10 | AV84: 3 | AW84: 2 | AX84: Extremely High | AY84: High | AZ84: No | BD84: CEO | BE84: The largest sharaholders hes substantial voting right [for example above 35%) effectively controlling the company | BF84: None | BG84: 61
A85: 83 | B85: 48 | C85: Male | D85: Hispanic | E85: https://drive.google.com/file/d/1QfWZkwdv2GS_eCwHDJoZNWh0sny99SLM/view?usp=drive_link | F85: Ibitomi Alaba | G85: Banker/Auditor | H85: alabaibitomi@yahoo.com | I85: 2 | J85: 08134964138 | K85: First Bank | L85: 8 years | M85: Branch Manager | N85: 32 years | O85: Degree holder | P85: 8 years | Q85: Large (Between $xx and $xx) | R85: Agree | S85: Somewhat Agree | T85: Somewhat Disagree | U85: Somewhat Disagree | V85: Strongly Agree | W85: Strongly Agree | X85: Agree | Y85: Somewhat Agree | Z85: Somewhat Disagree | AA85: Somewhat Disagree | AB85: No | AC85: Disagree | AD85: Somewhat Disagree | AE85: Somewhat Disagree | AF85: Disagree | AG85: Strongly Disagree | AH85: Somewhat Disagree | AI85: Disagree | AJ85: Disagree | AK85: Somewhat Disagree | AL85: Somewhat Disagree | AM85: No | AN85: Strongly Agree | AO85: Somewhat Disagree | AP85: Agree | AQ85: Agree | AR85: Somewhat Disagree | AS85: Somewhat Disagree | AT85: Neutral | AU85: 10 | AV85: 4 | AW85: 4 | AX85: Extremely High | AY85: High | BD85: CEO | BE85: The largest sharaholders hes substantial voting right [for example above 35%) effectively controlling the company | BF85: No | BG85: 50
A86: 84 | B86: 23 | C86: Female | D86: Hispanic | E86: https://drive.google.com/file/d/1ZGY6NRY8poMIRhPATQRZIlUd7GoiOWxg/view?usp=drive_link | F86: Juliana Etim | G86: Banker/Teller | H86: etimeditiang@yahoo.com | I86: None | J86: 09032452462 | K86: Fidelity Bank | L86: 4 years | M86: Head of Operation | N86: 28 years | O86: Degree holder | P86: 4 years | Q86: Large (Between $xx and $xx) | R86: Agree | S86: Agree | T86: Somewhat Disagree | U86: Somewhat Disagree | V86: Agree | W86: Strongly Agree | X86: Strongly Agree | Y86: Agree | Z86: Somewhat Disagree | AA86: Somewhat Disagree | AB86: No | AC86: Somewhat Disagree | AD86: Somewhat Disagree | AE86: Somewhat Disagree | AF86: Disagree | AG86: Disagree | AH86: Somewhat Disagree | AI86: Somewhat Disagree | AJ86: Somewhat Disagree | AK86: Somewhat Disagree | AL86: Disagree | AM86: No | AN86: Strongly Agree | AO86: Somewhat Disagree | AP86: Strongly Agree | AQ86: Agree | AR86: Somewhat Disagree | AS86: Disagree | AT86: Somewhat Disagree | AX86: High | AY86: High | BB86: 3 | BD86: CEO | BE86: The largest sharaholders hes substantial voting right [for example above 35%) effectively controlling the company | BF86: No | BG86: 65
A87: 85 | B87: 29 | C87: Male | D87: Hispanic | E87: https://drive.google.com/file/d/19ec1vxZ3QB6wDJyp9JBWZ-8wzDdOZeYQ/view?usp=drive_link | F87: Oluwaseyi Adetutu | G87: Banking/Teller | H87: seyifutu104@gmail.com | I87: Nil | J87: 07036000026 | K87: First Bank | L87: 6 years | M87: Head Cashier | N87: 29 years | O87: Degree holder | P87: 6 years | Q87: Large (Between $xx and $xx) | R87: Strongly Agree | S87: Agree | T87: Somewhat Disagree | U87: Somewhat Disagree | V87: Strongly Agree | W87: Strongly Agree | X87: Agree | Y87: Agree | Z87: Disagree | AA87: Somewhat Disagree | AB87: No | AC87: Strongly Disagree | AD87: Somewhat Disagree | AE87: Strongly Disagree | AF87: Somewhat Disagree | AG87: Somewhat Disagree | AH87: Disagree | AI87: Somewhat Disagree | AJ87: Somewhat Disagree | AK87: Disagree | AL87: Somewhat Disagree | AM87: No | AN87: Agree | AO87: Disagree | AP87: Strongly Agree | AQ87: Agree | AR87: Somewhat Disagree | AS87: Somewhat Disagree | AT87: Neutral | AU87: 10 | AV87: 4 | AW87: 4 | AX87: High | AY87: Extremely High | AZ87: No | BB87: 4 | BC87: Ousegun Adebiosu | BD87: CEO | BE87: The largest sharaholders hes substantial voting right [for example above 35%) effectively controlling the company | BG87: 53
A88: 86 | B88: 46 | C88: Female | D88: Black | E88: https://drive.google.com/file/d/1vfnzTZpLfQjdTSjT-bc-MXpdSaybxE9E/view?usp=drive_link | F88: Raheemah Aningo | G88: Banker/Customer Care | H88: hveemahchi@gmail.com | I88: None | J88: 08036077795 | K88: United Bank of Africa | L88: 4 years | M88: Operation Head | N88: 28 years | O88: HND holder | P88: 4 years | Q88: Large (Between $xx and $xx) | R88: Strongly Agree | S88: Agree | T88: Somewhat Disagree | U88: Somewhat Disagree | V88: Strongly Agree | W88: Strongly Agree | X88: Strongly Agree | Y88: Agree | Z88: Somewhat Disagree | AA88: Somewhat Disagree | AB88: No | AC88: Disagree | AD88: Somewhat Disagree | AE88: Disagree | AF88: Disagree | AG88: Disagree | AH88: Disagree | AI88: Disagree | AJ88: Somewhat Disagree | AK88: Somewhat Disagree | AL88: Somewhat Disagree | AM88: No | AN88: Strongly Agree | AO88: Somewhat Disagree | AP88: Strongly Agree | AQ88: Agree | AR88: Somewhat Disagree | AS88: Somewhat Disagree | AT88: Somewhat Disagree | AU88: 10 | AV88: 4 | AW88: 4 | AX88: High | AY88: Extremely High | AZ88: No | BC88: Tony Elumelu | BD88: CEO | BE88: The largest sharaholders hes substantial voting right [for example above 35%) effectively controlling the company | BF88: No | BG88: 61
A89: 87 | B89: 32 | C89: Female | D89: Hispanic | E89: https://drive.google.com/file/d/15Mpe5vsHNTXMGhYGsK2tL5ourYW3NM4T/view?usp=drive_link | F89: Monday Abah | G89: Banking/Teller | H89: abahmonday10@gmail.com | I89: Nil | J89: 08073746725 | K89: Wema Bank | L89: 2 years | M89: Head Cashier | N89: 26 years | O89: Degree holder | P89: 2 years | Q89: Large (Between $xx and $xx) | R89: Strongly Agree | S89: Strongly Agree | T89: Neutral | U89: Somewhat Disagree | V89: Strongly Agree | W89: Strongly Agree | X89: Agree | Y89: Agree | Z89: Somewhat Disagree | AA89: Somewhat Disagree | AB89: No | AC89: Strongly Disagree | AD89: Somewhat Disagree | AE89: Somewhat Disagree | AF89: Disagree | AG89: Somewhat Disagree | AH89: Somewhat Disagree | AI89: Disagree | AJ89: Somewhat Disagree | AK89: Somewhat Disagree | AL89: Somewhat Disagree | AM89: No | AN89: Strongly Agree | AO89: Somewhat Disagree | AP89: Agree | AQ89: Agree | AR89: Disagree | AS89: Somewhat Disagree | AT89: Somewhat Disagree | AX89: Extremely High | AY89: High | BB89: 4 | BD89: CEO | BE89: The largest sharaholders hes substantial voting right [for example above 35%) effectively controlling the company | BF89: No | BG89: 92
A90: 88 | B90: 48 | C90: Female | D90: Hispanic | E90: https://drive.google.com/file/d/1XlrmEaYrNTxGN9IoSQPDfBBeBJWjwHfT/view?usp=drive_link | F90: Ruth Tankuku | G90: Banker | I90: 2 | J90: 08065662294 | K90: Keystone Bank | L90: 6 years | M90: Branch Manager | N90: 37 years | O90: Degree holder | P90: 7 years | Q90: Large (Between $xx and $xx) | R90: Strongly Agree | S90: Strongly Agree | T90: Strongly Agree | U90: Agree | V90: Strongly Agree | W90: Strongly Agree | X90: Strongly Agree | Y90: Agree | Z90: Strongly Agree | AA90: Agree | AB90: No | AC90: Disagree | AD90: Disagree | AE90: Disagree | AF90: Strongly Disagree | AG90: Strongly Disagree | AH90: Strongly Disagree | AI90: Disagree | AJ90: Strongly Disagree | AK90: Neutral | AL90: Somewhat Disagree | AM90: No | AN90: Strongly Agree | AO90: Disagree | AP90: Agree | AQ90: Agree | AR90: Somewhat Disagree | AS90: Neutral | AT90: Neutral | AU90: 9 | AV90: 2 | AW90: 2 | AX90: High | AY90: High | AZ90: No | BB90: 4 | BD90: CEO | BE90: The largest sharaholders hes substantial voting right [for example above 35%) effectively controlling the company | BF90: No | BG90: 50
A91: 89 | B91: 31 | C91: Female | D91: White | E91: https://drive.google.com/file/d/1FlurtY8FXkhlWBHcX1MA88PBo4JaYmSk/view?usp=drive_link | F91: Isaac Agbole | G91: Banking/Teller | H91: agboleisaac@yahoo.com | I91: Nil | J91: 08118294399 | K91: Wema Bank | L91: 3 years | M91: Operation Manager | N91: 25 years | O91: HND holder | P91: 3 years | Q91: Large (Between $xx and $xx) | R91: Strongly Agree | S91: Somewhat Agree | T91: Somewhat Disagree | U91: Disagree | V91: Agree | W91: Strongly Agree | X91: Agree | Y91: Agree | Z91: Somewhat Disagree | AA91: Somewhat Disagree | AB91: No | AC91: Disagree | AD91: Disagree | AE91: Disagree | AF91: Disagree | AG91: Strongly Disagree | AH91: Somewhat Disagree | AI91: Somewhat Disagree | AJ91: Somewhat Disagree | AK91: Disagree | AL91: Somewhat Disagree | AM91: No | AN91: Strongly Agree | AO91: Somewhat Disagree | AP91: Agree | AQ91: Agree | AR91: Somewhat Disagree | AS91: Somewhat Disagree | AT91: Neutral | AX91: Extremely High | AY91: High | AZ91: No | BD91: CEO | BE91: The largest sharaholders hes substantial voting right [for example above 35%) effectively controlling the company | BF91: No | BG91: 77
A92: 90 | B92: 28 | C92: Male | D92: White | E92: https://drive.google.com/file/d/1GAqw2W6EPICPBqLydfg1rPL2XerhYySD/view?usp=drive_link | F92: James Onah | G92: Banking/Teller | H92: onahjames@yahoo.com | I92: None | J92: 08034397659 | K92: Wema Bank | L92: 8 years | M92: Operation Head | N92: 30 years | O92: Degree holder | P92: 8 years | Q92: Large (Between $xx and $xx) | R92: Strongly Agree | S92: Agree | T92: Somewhat Disagree | U92: Somewhat Disagree | V92: Strongly Agree | W92: Strongly Agree | X92: Agree | Y92: Agree | Z92: Disagree | AA92: Disagree | AB92: No | AC92: Strongly Disagree | AD92: Disagree | AE92: Disagree | AF92: Disagree | AG92: Strongly Disagree | AH92: Somewhat Disagree | AI92: Somewhat Disagree | AJ92: Disagree | AK92: Disagree | AL92: Somewhat Disagree | AM92: No | AN92: Agree | AO92: Strongly Disagree | AP92: Strongly Agree | AQ92: Agree | AR92: Somewhat Disagree | AS92: Disagree | AT92: Somewhat Disagree | AX92: High | AY92: Extremely High | BD92: CEO | BE92: The largest sharaholders hes substantial voting right [for example above 35%) effectively controlling the company | BF92: No | BG92: 58
A93: 91 | B93: 48 | C93: Female | D93: Black | E93: https://drive.google.com/file/d/1Wf-14RIhbLMqphqFOoINlFdZEj9uftrK/view?usp=drive_link | F93: Sunday Oladele | G93: Banking/Teller | H93: oladelesunny@gmail.com | I93: None | J93: 0806940063 | K93: Wema Bank | L93: 4 years | M93: Head of Operation | N93: 28 years | O93: HND holder | P93: 4 years | Q93: Large (Between $xx and $xx) | R93: Strongly Agree | S93: Agree | T93: Somewhat Disagree | U93: Somewhat Disagree | V93: Strongly Agree | W93: Agree | X93: Strongly Agree | Y93: Agree | Z93: Disagree | AA93: Disagree | AB93: No | AC93: Disagree | AD93: Disagree | AE93: Somewhat Disagree | AF93: Somewhat Disagree | AG93: Strongly Disagree | AH93: Disagree | AI93: Somewhat Disagree | AJ93: Somewhat Disagree | AK93: Disagree | AL93: Somewhat Disagree | AM93: No | AN93: Strongly Agree | AO93: Disagree | AP93: Strongly Agree | AQ93: Agree | AR93: Somewhat Disagree | AS93: Disagree | AT93: Somewhat Disagree | AU93: 10 | AV93: 4 | AW93: Nil | AX93: High | AY93: Extremely High | AZ93: No | BB93: 4 | BD93: CEO | BE93: The largest sharaholders hes substantial voting right [for example above 35%) effectively controlling the company | BF93: No | BG93: 54
A94: 92 | B94: 29 | C94: Female | D94: White | E94: https://drive.google.com/file/d/1D27rX_RnLhryI-LoSMXq-lF1m1gLQD7N/view?usp=drive_link | F94: Folape Iteyinwa | G94: Banking/Customer Care | H94: iteyinwafolape@garba.com | I94: 2 | J94: 08033345000 | K94: Zenith Bank | L94: 7 years | M94: Branch Manager | N94: 34 years | O94: Masters holder | P94: 14 years | Q94: Large (Between $xx and $xx) | R94: Agree | S94: Agree | T94: Somewhat Disagree | U94: Somewhat Disagree | V94: Strongly Agree | W94: Strongly Agree | X94: Agree | Y94: Somewhat Agree | Z94: Somewhat Disagree | AA94: Somewhat Disagree | AB94: No | AC94: Disagree | AD94: Somewhat Disagree | AE94: Disagree | AF94: Somewhat Disagree | AG94: Strongly Agree | AH94: Somewhat Disagree | AI94: Disagree | AJ94: Somewhat Disagree | AK94: Somewhat Disagree | AL94: Somewhat Disagree | AM94: None | AN94: Agree | AO94: Disagree | AP94: Agree | AQ94: Agree | AR94: Somewhat Disagree | AS94: Somewhat Disagree | AT94: Somewhat Disagree | AV94: 4 | AW94: 4 | AX94: High | AY94: Extremely High | BD94: CEO | BE94: The largest sharaholders hes substantial voting right [for example above 35%) effectively controlling the company | BF94: No | BG94: 93
A95: 93 | B95: 26 | C95: Female | D95: Black | E95: https://drive.google.com/file/d/1-UTPrC6QsXNCVAof6smuZyKjMnTJuV13/view?usp=drive_link | F95: Ibrahim Gimba | G95: Banking/Teller | H95: gimbaibahim55@gmail.com | I95: Nil | J95: 08036267893 | K95: First Bank Plc | L95: 2 years | M95: Head Cashier | N95: 26 years | O95: Degree holder | P95: 2 years | Q95: Large (Between $xx and $xx) | R95: Strongly Agree | S95: Somewhat Agree | T95: Somewhat Disagree | U95: Somewhat Disagree | V95: Strongly Agree | W95: Strongly Agree | X95: Agree | Y95: Agree | Z95: Somewhat Disagree | AA95: Somewhat Disagree | AB95: No | AC95: Disagree | AD95: Somewhat Disagree | AE95: Somewhat Disagree | AF95: Disagree | AG95: Strongly Disagree | AH95: Disagree | AI95: Somewhat Disagree | AJ95: Somewhat Disagree | AK95: Somewhat Disagree | AL95: Somewhat Disagree | AM95: No | AN95: Strongly Agree | AO95: Disagree | AP95: Agree | AQ95: Agree | AR95: Somewhat Disagree | AS95: Somewhat Disagree | AT95: Somewhat Disagree | AX95: Extremely High | AY95: High | AZ95: No | BB95: 3 | BD95: CEO | BE95: The largest sharaholders hes substantial voting right [for example above 35%) effectively controlling the company | BG95: 84
A96: 94 | B96: 27 | C96: Female | D96: White | E96: https://drive.google.com/file/d/16d_273x19lzOekyFzoj2L4t4EpWh3I85/view?usp=drive_link | F96: Busayo Adeoye | G96: Banking/Teller | H96: adeoyebusayo@gmail.com | J96: 08036100694 | K96: Wema Bank | L96: 1 years | M96: Head Cashier | N96: 26 years | O96: Degree holder | P96: 2 years | Q96: Large (Between $xx and $xx) | R96: Agree | S96: Somewhat Agree | T96: Somewhat Disagree | U96: Somewhat Disagree | V96: Agree | W96: Strongly Agree | X96: Agree | Y96: Agree | Z96: Disagree | AA96: Somewhat Disagree | AB96: No | AC96: Strongly Disagree | AD96: Disagree | AE96: Disagree | AF96: Disagree | AG96: Strongly Disagree | AH96: Disagree | AI96: Disagree | AJ96: Somewhat Disagree | AK96: Disagree | AL96: Somewhat Disagree | AM96: No | AN96: Strongly Agree | AO96: Disagree | AP96: Strongly Agree | AQ96: Agree | AR96: Somewhat Disagree | AS96: Somewhat Disagree | AT96: Somewhat Disagree | AU96: 10 | AV96: 3 | AW96: 3 | AX96: Extremely High | AY96: Extremely High | AZ96: No | BB96: 5 | BD96: CEO | BE96: The largest sharaholders hes substantial voting right [for example above 35%) effectively controlling the company | BF96: No | BG96: 56
A97: 95 | B97: 26 | C97: Female | D97: White | E97: https://drive.google.com/file/d/1M_TNe_0pLhM-JHFWjxjblrwjIg6EK7Pt/view?usp=drive_link | F97: Naima Dassa | G97: Banker/Customer | H97: naimadassa@gmail.com | I97: None | J97: 07035696760 | K97: Fidelity Bank | L97: 4 years | M97: Operation Head | N97: 24 years | O97: HND holder | P97: 5 years | Q97: Large (Between $xx and $xx) | R97: Agree | S97: Somewhat Agree | T97: Somewhat Disagree | U97: Somewhat Disagree | V97: Agree | W97: Strongly Agree | X97: Agree | Y97: Somewhat Agree | Z97: Disagree | AA97: Disagree | AB97: No | AC97: Disagree | AD97: Somewhat Disagree | AE97: Somewhat Disagree | AF97: Disagree | AG97: Disagree | AH97: Somewhat Disagree | AI97: Disagree | AJ97: Somewhat Disagree | AK97: Somewhat Disagree | AL97: Somewhat Disagree | AM97: No | AN97: Strongly Agree | AO97: Disagree | AP97: Agree | AQ97: Agree | AR97: Somewhat Disagree | AS97: Somewhat Disagree | AT97: Neutral | AU97: 10 | AV97: 4 | AW97: 4 | AX97: Extremely High | AY97: High | AZ97: No | BB97: 5 | BD97: CEO | BE97: The largest sharaholders hes substantial voting right [for example above 35%) effectively controlling the company | BF97: No | BG97: 45
A98: 96 | B98: 26 | C98: Female | D98: White | E98: https://drive.google.com/file/d/1Fok1IExCJYJGHcmn2ebfOOUXL361KFl_/view?usp=drive_link | F98: Ademu Manifan | G98: Banking/Cashier | H98: manifanademu1@gmail.com | I98: No | J98: 08109978004 | K98: Sterling Bank | L98: 4 years | M98: Head of Operation | N98: 26 years | O98: HND holder | P98: 4 years | Q98: Large (Between $xx and $xx) | R98: Agree | S98: Somewhat Agree | T98: Disagree | U98: Somewhat Disagree | V98: Agree | W98: Strongly Agree | X98: Agree | Y98: Somewhat Agree | Z98: Somewhat Disagree | AA98: Somewhat Disagree | AB98: No | AC98: Disagree | AD98: Somewhat Disagree | AE98: Disagree | AF98: Somewhat Disagree | AG98: Disagree | AH98: Somewhat Disagree | AI98: Disagree | AJ98: Somewhat Disagree | AK98: Disagree | AL98: Somewhat Disagree | AM98: No | AN98: Agree | AO98: Disagree | AP98: Strongly Agree | AQ98: Agree | AR98: Neutral | AS98: Somewhat Disagree | AT98: Somewhat Disagree | AU98: 10 | AV98: 2 | AW98: 2 | AX98: High | AY98: Extremely High | AZ98: No | BB98: 4 | BD98: CEO | BE98: The largest sharaholders hes substantial voting right [for example above 35%) effectively controlling the company | BF98: None | BG98: 66
A99: 97 | B99: 43 | C99: Female | D99: Hispanic | E99: https://drive.google.com/file/d/17vUyni0BmD6o8Wpsi7Jnf54idhvqX7KZ/view?usp=drive_link | F99: Ekema Emmanuel | G99: Banking/Customer Care | H99: emmanuelekema@yahoo.com | I99: None | J99: 09068860628 | K99: Fidelity Bank | L99: 5 years | M99: Operation Manager | N99: 30 years | O99: Degree holder | P99: 5 years | Q99: Large (Between $xx and $xx) | R99: Strongly Agree | S99: Somewhat Agree | T99: Somewhat Disagree | U99: Somewhat Disagree | V99: Strongly Agree | W99: Strongly Agree | X99: Agree | Y99: Agree | Z99: Disagree | AA99: Somewhat Disagree | AB99: No | AC99: Disagree | AD99: Somewhat Disagree | AE99: Disagree | AF99: Disagree | AG99: Strongly Disagree | AH99: Disagree | AI99: Somewhat Disagree | AJ99: Disagree | AK99: Somewhat Disagree | AL99: Somewhat Disagree | AM99: No | AN99: Strongly Agree | AO99: Disagree | AP99: Agree | AQ99: Somewhat Disagree | AR99: Somewhat Disagree | AS99: Somewhat Disagree | AT99: Somewhat Disagree | AX99: High | AY99: High | AZ99: No | BD99: CEO | BE99: The largest sharaholders hes substantial voting right [for example above 35%) effectively controlling the company | BF99: No | BG99: 54
A100: 98 | B100: 50 | C100: Female | D100: Black | E100: https://drive.google.com/file/d/1XeJMLm-kodKLZLO7Fhfk-e3xLiGWImJS/view?usp=drive_link | F100: Ameli Gabriel | G100: Banking/Teller | H100: gabrielameli55@gmail.com | I100: None | J100: 07061586138 | K100: United Bank for Africa | L100: 5 years | M100: Head Cashier | N100: 29 years | O100: Degree holder | P100: 6 years | Q100: Large (Between $xx and $xx) | R100: Strongly Agree | S100: Somewhat Agree | T100: Somewhat Disagree | U100: Disagree | V100: Agree | W100: Strongly Agree | X100: Strongly Agree | Y100: Agree | Z100: Strongly Agree | AA100: Somewhat Disagree | AB100: No | AC100: Strongly Disagree | AD100: Disagree | AE100: Somewhat Disagree | AF100: Disagree | AG100: Strongly Disagree | AH100: Disagree | AI100: Disagree | AJ100: Somewhat Disagree | AK100: Somewhat Disagree | AL100: Somewhat Disagree | AM100: No | AN100: Strongly Agree | AO100: Disagree | AP100: Strongly Agree | AQ100: Agree | AR100: Disagree | AS100: Somewhat Disagree | AT100: Somewhat Disagree | AU100: 10 | AV100: 4 | AW100: 4 | AX100: High | AY100: Extremely High | AZ100: No | BC100: Tony Elumelu | BD100: CEO | BE100: The largest sharaholders hes substantial voting right [for example above 35%) effectively controlling the company | BG100: 37
...

Sheet ID2

Sheet Key ID2
A3: Name | C3: Respondent ID
A4: role | C4: Respondent Role
A5: email | C5: Respondent Email
A6: reporttoyou | C6: How many people does the respondant report to?
A7: teleohoneNum | C7: Responant telephone Number
A8: organisation | C8: Name of Organisation
A9: yearsinorg | C9: How long have you been in your organisation?
A10: WhoyUReport | C10: Who do you report to?
A11: ageinorg | C11: Respondent age
A12: eduQualifi
A13: yearinFin
A14: Bank Size | C14: Respondent age
A15: sex | C15: Respondent sex
A16: race | C16: Respondent race
A17: BME | C17: Respondent BME Status, 1= BME, 0= non BME
A18: Educ | C18: Respondent Education level, 1 = graduate degree, 0=no graduate degree
A19: Questions | B19: Latent Variable | C19: Twenty Questions on derpression expressed when learning statistics | D19: StronglyDisagree | E19: Disagree | F19: Neutral | G19: Agree | H19: StronglyAgree
D20: 1 | E20: 2 | F20: 3 | G20: 4 | H20: 5
A21: qu1 | B21: Affective | C21: Statistics makes you feel sad
A22: qu2 | C22: Statistics makes you feel pessimistic about the future
A23: qu3 | C23: Statistics makes you feel like a failure
A24: qu4 | C24: Statistics makes you feel dissatisfied
A25: qu5 | C25: Statistics makes you feel guilty or unworthy
A26: qu6 | C26: Statistics makes you feel that I am being punished
A27: qu7 | C27: Statistics makes you feel disappointed in myself
A28: qu8 | C28: Statistics makes you feel am very critical of myself
A29: qu9 | C29: Statistics makes you feel like harming myself
A30: qu10 | C30: Statistics makes you feel crying more than usual
A31: qu11 | B31: Physical | C31: Statistics makes you become annoyed or irritated easily
A32: qu12 | C32: Statistics makes you have lost interest in other people
A33: qu13 | C33: Statistics makes you have trouble making decision
A34: qu14 | C34: Statistics makes you feel unattractive
A35: qu15 | C35: Statistics makes you feel like not working
A36: qu16 | C36: Statistics makes you have trouble sleeping
A37: qu17 | C37: Statistics makes you feel tired or fatigue
A38: qu18 | C38: Statistics makes my appetite lower than usual
A39: qu19 | C39: Statistics makes you concerned about your health
A40: qu20 | C40: Statistics makes you experience decrease in libido
A41: TotalScore

Sheet Copy of Data
E1: Name | F1: Role | G1: Email address
A2: id | B2: age | C2: sex | D2: race | E2: qu1 | F2: qu2 | G2: qu3 | H2: qu4 | I2: qu5 | J2: qu6 | K2: qu7 | L2: qu8 | M2: qu9 | N2: qu10 | O2: qu11 | P2: qu12 | Q2: qu13 | R2: qu14 | S2: qu15 | T2: qu16 | U2: qu17 | V2: qu18 | W2: qu19 | X2: qu20 | Y2: TotalScore
A3: 1 | B3: 49 | C3: Male | D3: White | F3: Banker | G3: Neutral | H3: Neutral | I3: Neutral | J3: Neutral | K3: Neutral | L3: Neutral | M3: Neutral | N3: Disagree | O3: Neutral | P3: Neutral | Q3: Neutral | R3: Disagree | S3: Disagree | T3: Neutral | U3: Neutral | V3: Disagree | W3: Neutral | X3: StronglyDisagree | Y3: 54
A4: 2 | B4: 52 | C4: Female | D4: White | E4: Neutral | F4: Disagree | G4: Neutral | H4: Neutral | I4: Disagree | J4: Disagree | K4: Disagree | L4: Neutral | M4: Neutral | N4: Neutral | O4: Neutral | P4: Neutral | Q4: Neutral | R4: Neutral | S4: Neutral | T4: Neutral | U4: Neutral | V4: Neutral | W4: Neutral | X4: Disagree | Y4: 55
A5: 3 | B5: 31 | C5: Male | D5: Hispanic | E5: Neutral | F5: Disagree | G5: Disagree | H5: Neutral | I5: Disagree | J5: Disagree | K5: Neutral | L5: Disagree | M5: Neutral | N5: Disagree | O5: Agree | P5: Agree | Q5: Neutral | R5: Agree | S5: Neutral | T5: Neutral | U5: Neutral | V5: Agree | W5: Agree | X5: Disagree | Y5: 58
A6: 4 | B6: 28 | C6: Male | D6: Black | E6: Agree | F6: Neutral | G6: Neutral | H6: Neutral | I6: Neutral | J6: Disagree | K6: Neutral | L6: Neutral | M6: Neutral | N6: Neutral | O6: Neutral | P6: Neutral | Q6: Agree | R6: Neutral | S6: Neutral | T6: Neutral | U6: Agree | V6: Neutral | W6: Neutral | X6: Neutral | Y6: 62
A7: 5 | B7: 29 | C7: Male | D7: White | E7: Agree | F7: Disagree | G7: Agree | H7: Agree | I7: Neutral | J7: Agree | K7: Agree | L7: Agree | M7: Agree | N7: Agree | O7: Neutral | P7: Neutral | Q7: Neutral | R7: StronglyDisagree | S7: Disagree | T7: Neutral | U7: Neutral | V7: Neutral | W7: Neutral | X7: StronglyDisagree | Y7: 62
A8: 6 | B8: 50 | C8: Female | D8: Black | E8: Neutral | F8: Disagree | G8: Neutral | H8: Disagree | I8: Disagree | J8: Disagree | K8: Neutral | L8: Neutral | M8: Disagree | N8: Neutral | O8: Neutral | P8: Neutral | Q8: Neutral | R8: Disagree | S8: Neutral | T8: Neutral | U8: Neutral | V8: Neutral | W8: Neutral | X8: Neutral | Y8: 54
A9: 7 | B9: 31 | C9: Female | D9: White | E9: Disagree | F9: StronglyDisagree | G9: Disagree | H9: Disagree | I9: Disagree | J9: Disagree | K9: Disagree | L9: StronglyDisagree | M9: Disagree | N9: Disagree | O9: Neutral | P9: Agree | Q9: Neutral | R9: Disagree | S9: Neutral | T9: Agree | U9: Neutral | V9: Neutral | W9: Neutral | X9: Neutral | Y9: 49
A10: 8 | B10: 24 | C10: Female | D10: Black | E10: Neutral | F10: Neutral | G10: Neutral | H10: Neutral | I10: Neutral | J10: Agree | K10: Neutral | L10: Neutral | M10: Neutral | N10: Agree | O10: Agree | P10: Neutral | Q10: Neutral | R10: Neutral | S10: Neutral | T10: Neutral | U10: Agree | V10: Neutral | W10: Agree | X10: Disagree | Y10: 64
A11: 9 | B11: 32 | C11: Female | D11: Black | E11: Agree | F11: Agree | G11: Agree | H11: Agree | I11: Neutral | J11: Agree | K11: Neutral | L11: Neutral | M11: Neutral | N11: Agree | O11: Neutral | P11: Neutral | Q11: Agree | R11: Disagree | S11: Neutral | T11: Neutral | U11: Neutral | V11: Neutral | W11: Agree | X11: Disagree | Y11: 66
A12: 10 | B12: 33 | C12: Female | D12: White | E12: Neutral | F12: Agree | G12: Agree | H12: Agree | I12: Agree | J12: Agree | K12: Agree | L12: Agree | M12: Agree | N12: Agree | O12: Disagree | P12: Disagree | Q12: Neutral | R12: StronglyDisagree | S12: Disagree | T12: Disagree | U12: Disagree | V12: Disagree | W12: Neutral | X12: StronglyDisagree | Y12: 59
A13: 11 | B13: 46 | C13: Female | D13: White | E13: Neutral | F13: Neutral | G13: Agree | H13: Neutral | I13: Neutral | J13: Neutral | K13: Agree | L13: Neutral | M13: Neutral | N13: Agree | O13: Disagree | P13: Neutral | Q13: Neutral | R13: Disagree | S13: Neutral | T13: Neutral | U13: Neutral | V13: Neutral | W13: Neutral | X13: StronglyDisagree | Y13: 59
A14: 12 | B14: 39 | C14: Female | D14: White | E14: StronglyAgree | F14: Agree | G14: StronglyAgree | H14: Agree | I14: StronglyAgree | J14: Agree | K14: Agree | L14: StronglyAgree | M14: StronglyAgree | N14: StronglyAgree | O14: Agree | P14: StronglyAgree | Q14: Agree | R14: Neutral | S14: Agree | T14: Agree | U14: Agree | V14: Agree | W14: Neutral | X14: Neutral | Y14: 84
A15: 13 | B15: 46 | C15: Male | D15: Black | E15: Neutral | F15: Neutral | G15: Neutral | H15: Neutral | I15: Neutral | J15: Agree | K15: Agree | L15: Neutral | M15: Neutral | N15: Neutral | O15: Neutral | P15: Neutral | Q15: Neutral | R15: Disagree | S15: Neutral | T15: Neutral | U15: Disagree | V15: Neutral | W15: Disagree | X15: Disagree | Y15: 58
... A1002: 1000 | B1002: 30 | C1002: Female | D1002: Black | E1002: Agree | F1002: Neutral | G1002: Agree | H1002: Agree | I1002: Agree | J1002: Agree | K1002: Agree | L1002: StronglyAgree | M1002: Agree | N1002: Agree | O1002: Agree | P1002: StronglyAgree | Q1002: StronglyAgree | R1002: Agree | S1002: StronglyAgree | T1002: StronglyAgree | U1002: StronglyAgree | V1002: StronglyAgree | W1002: StronglyAgree | X1002: Agree | Y1002: 87

Sheet Data 1
A1: StronglyDisagree | B1: id | C1: age | D1: sex | E1: race | F1: qu1 | G1: qu2 | H1: qu3 | I1: qu4 | J1: qu5 | K1: qu6 | L1: qu7 | M1: qu8 | N1: qu9 | O1: qu10 | P1: qu11 | Q1: qu12 | R1: qu13 | S1: qu14 | T1: qu15 | U1: qu16 | V1: qu17 | W1: qu18 | X1: qu19 | Y1: qu20 | Z1: TotalScore
A2: Disagree | B2: 1 | C2: 49 | D2: Male | E2: White | F2: =MATCH(Data!F3,$A$1:$A$5,0) -> #N/A | G2: =MATCH(Data!G3,$A$1:$A$5,0) -> #N/A | H2: =MATCH(Data!H3,$A$1:$A$5,0) -> #N/A | I2: =MATCH(Data!I3,$A$1:$A$5,0) -> #N/A | J2: =MATCH(Data!J3,$A$1:$A$5,0) -> #N/A | K2: =MATCH(Data!K3,$A$1:$A$5,0) -> #N/A | L2: =MATCH(Data!L3,$A$1:$A$5,0) -> #N/A | M2: =MATCH(Data!M3,$A$1:$A$5,0) -> #N/A | ... Y2: =MATCH(Data!Y3,$A$1:$A$5,0) -> 4 | Z2: =SUM(F2:Y2) -> #N/A
A3: Neutral | B3: 2 | C3: 52 | D3: Female | E3: White | F3: =MATCH(Data!F4,$A$1:$A$5,0) -> #N/A | G3: =MATCH(Data!G4,$A$1:$A$5,0) -> #N/A | H3: =MATCH(Data!H4,$A$1:$A$5,0) -> #N/A | I3: =MATCH(Data!I4,$A$1:$A$5,0) -> #N/A | J3: =MATCH(Data!J4,$A$1:$A$5,0) -> #N/A | K3: =MATCH(Data!K4,$A$1:$A$5,0) -> #N/A | L3: =MATCH(Data!L4,$A$1:$A$5,0) -> #N/A | M3: =MATCH(Data!M4,$A$1:$A$5,0) -> #N/A | ... Y3: =MATCH(Data!Y4,$A$1:$A$5,0) -> #N/A | Z3: =SUM(F3:Y3) -> #N/A
A4: Agree | B4: 3 | C4: 31 | D4: Male | E4: Hispanic | F4: =MATCH(Data!F5,$A$1:$A$5,0) -> #N/A | G4: =MATCH(Data!G5,$A$1:$A$5,0) -> #N/A | H4: =MATCH(Data!H5,$A$1:$A$5,0) -> #N/A | I4: =MATCH(Data!I5,$A$1:$A$5,0) -> #N/A | J4: =MATCH(Data!J5,$A$1:$A$5,0) -> #N/A | K4: =MATCH(Data!K5,$A$1:$A$5,0) -> #N/A | L4: =MATCH(Data!L5,$A$1:$A$5,0) -> #N/A | M4: =MATCH(Data!M5,$A$1:$A$5,0) -> #N/A | ... Y4: =MATCH(Data!Y5,$A$1:$A$5,0) -> #N/A | Z4: =SUM(F4:Y4) -> #N/A
A5: StronglyAgree | B5: 4 | C5: 28 | D5: Male | E5: Black | F5: =MATCH(Data!F6,$A$1:$A$5,0) -> #N/A | G5: =MATCH(Data!G6,$A$1:$A$5,0) -> #N/A | H5: =MATCH(Data!H6,$A$1:$A$5,0) -> #N/A | I5: =MATCH(Data!I6,$A$1:$A$5,0) -> #N/A | J5: =MATCH(Data!J6,$A$1:$A$5,0) -> #N/A | K5: =MATCH(Data!K6,$A$1:$A$5,0) -> #N/A | L5: =MATCH(Data!L6,$A$1:$A$5,0) -> #N/A | M5: =MATCH(Data!M6,$A$1:$A$5,0) -> #N/A | ... Y5: =MATCH(Data!Y6,$A$1:$A$5,0) -> #N/A | Z5: =SUM(F5:Y5) -> #N/A
B6: 5 | C6: 29 | D6: Male | E6: White | F6: =MATCH(Data!F7,$A$1:$A$5,0) -> #N/A | G6: =MATCH(Data!G7,$A$1:$A$5,0) -> #N/A | H6: =MATCH(Data!H7,$A$1:$A$5,0) -> #N/A | I6: =MATCH(Data!I7,$A$1:$A$5,0) -> #N/A | J6: =MATCH(Data!J7,$A$1:$A$5,0) -> #N/A | K6: =MATCH(Data!K7,$A$1:$A$5,0) -> #N/A | L6: =MATCH(Data!L7,$A$1:$A$5,0) -> #N/A | M6: =MATCH(Data!M7,$A$1:$A$5,0) -> #N/A | ... Y6: =MATCH(Data!Y7,$A$1:$A$5,0) -> #N/A | Z6: =SUM(F6:Y6) -> #N/A
B7: 6 | C7: 50 | D7: Female | E7: Black | F7: =MATCH(Data!F8,$A$1:$A$5,0) -> #N/A | G7: =MATCH(Data!G8,$A$1:$A$5,0) -> #N/A | H7: =MATCH(Data!H8,$A$1:$A$5,0) -> #N/A | I7: =MATCH(Data!I8,$A$1:$A$5,0) -> #N/A | J7: =MATCH(Data!J8,$A$1:$A$5,0) -> #N/A | K7: =MATCH(Data!K8,$A$1:$A$5,0) -> #N/A | L7: =MATCH(Data!L8,$A$1:$A$5,0) -> #N/A | M7: =MATCH(Data!M8,$A$1:$A$5,0) -> #N/A | ... Y7: =MATCH(Data!Y8,$A$1:$A$5,0) -> 3 | Z7: =SUM(F7:Y7) -> #N/A
B8: 7 | C8: 31 | D8: Female | E8: White | F8: =MATCH(Data!F9,$A$1:$A$5,0) -> #N/A | G8: =MATCH(Data!G9,$A$1:$A$5,0) -> #N/A | H8: =MATCH(Data!H9,$A$1:$A$5,0) -> #N/A | I8: =MATCH(Data!I9,$A$1:$A$5,0) -> #N/A | J8: =MATCH(Data!J9,$A$1:$A$5,0) -> #N/A | K8: =MATCH(Data!K9,$A$1:$A$5,0) -> #N/A | L8: =MATCH(Data!L9,$A$1:$A$5,0) -> #N/A | M8: =MATCH(Data!M9,$A$1:$A$5,0) -> #N/A | ... Y8: =MATCH(Data!Y9,$A$1:$A$5,0) -> #N/A | Z8: =SUM(F8:Y8) -> #N/A
B9: 8 | C9: 24 | D9: Female | E9: Black | F9: =MATCH(Data!F10,$A$1:$A$5,0) -> #N/A | G9: =MATCH(Data!G10,$A$1:$A$5,0) -> #N/A | H9: =MATCH(Data!H10,$A$1:$A$5,0) -> #N/A | I9: =MATCH(Data!I10,$A$1:$A$5,0) -> #N/A | J9: =MATCH(Data!J10,$A$1:$A$5,0) -> #N/A | K9: =MATCH(Data!K10,$A$1:$A$5,0) -> #N/A | L9: =MATCH(Data!L10,$A$1:$A$5,0) -> #N/A | M9: =MATCH(Data!M10,$A$1:$A$5,0) -> #N/A | ... Y9: =MATCH(Data!Y10,$A$1:$A$5,0) -> #N/A | Z9: =SUM(F9:Y9) -> #N/A
B10: 9 | C10: 32 | D10: Female | E10: Black | F10: =MATCH(Data!F11,$A$1:$A$5,0) -> #N/A | G10: =MATCH(Data!G11,$A$1:$A$5,0) -> #N/A | H10: =MATCH(Data!H11,$A$1:$A$5,0) -> #N/A | I10: =MATCH(Data!I11,$A$1:$A$5,0) -> #N/A | J10: =MATCH(#REF!,$A$1:$A$5,0) -> #REF! | K10: =MATCH(Data!K11,$A$1:$A$5,0) -> #N/A | L10: =MATCH(Data!L11,$A$1:$A$5,0) -> #N/A | M10: =MATCH(Data!M11,$A$1:$A$5,0) -> #N/A | N10: =MATCH(Data!N11,$A$1:$A$5,0) -> #N/A | O10: =MATCH(Data!O11,$A$1:$A$5,0) -> #N/A | P10: =MATCH(Data!P11,$A$1:$A$5,0) -> #N/A | Q10: =MATCH(Data!Q11,$A$1:$A$5,0) -> #N/A | R10: =MATCH(Data!R11,$A$1:$A$5,0) -> 4 | ... Y10: =MATCH(Data!Y11,$A$1:$A$5,0) -> 4 | Z10: =SUM(F10:Y10) -> #N/A
B11: 10 | C11: 33 | D11: Female | E11: White | F11: =MATCH(Data!F12,$A$1:$A$5,0) -> #N/A | G11: =MATCH(Data!G12,$A$1:$A$5,0) -> #N/A | H11: =MATCH(Data!H12,$A$1:$A$5,0) -> #N/A | I11: =MATCH(Data!I12,$A$1:$A$5,0) -> #N/A | J11: =MATCH(Data!J11,$A$1:$A$5,0) -> #N/A | K11: =MATCH(Data!K12,$A$1:$A$5,0) -> #N/A | L11: =MATCH(Data!L12,$A$1:$A$5,0) -> #N/A | M11: =MATCH(Data!M12,$A$1:$A$5,0) -> #N/A | N11: =MATCH(Data!N12,$A$1:$A$5,0) -> #N/A | O11: =MATCH(Data!O12,$A$1:$A$5,0) -> #N/A | P11: =MATCH(Data!P12,$A$1:$A$5,0) -> #N/A | Q11: =MATCH(Data!Q12,$A$1:$A$5,0) -> #N/A | R11: =MATCH(Data!R12,$A$1:$A$5,0) -> 4 | ... Y11: =MATCH(Data!Y12,$A$1:$A$5,0) -> 4 | Z11: =SUM(F11:Y11) -> #N/A
B12: 11 | C12: 46 | D12: Female | E12: White | F12: =MATCH(Data!F13,$A$1:$A$5,0) -> #N/A | G12: =MATCH(Data!G13,$A$1:$A$5,0) -> #N/A | H12: =MATCH(Data!H13,$A$1:$A$5,0) -> #N/A | I12: =MATCH(Data!I13,$A$1:$A$5,0) -> #N/A | J12: =MATCH(Data!J13,$A$1:$A$5,0) -> #N/A | K12: =MATCH(Data!K13,$A$1:$A$5,0) -> #N/A | L12: =MATCH(Data!L13,$A$1:$A$5,0) -> #N/A | M12: =MATCH(Data!M13,$A$1:$A$5,0) -> #N/A | ... Y12: =MATCH(Data!Y13,$A$1:$A$5,0) -> 4 | Z12: =SUM(F12:Y12) -> #N/A
B13: 12 | C13: 39 | D13: Female | E13: White | F13: =MATCH(Data!F14,$A$1:$A$5,0) -> #N/A | G13: =MATCH(Data!G14,$A$1:$A$5,0) -> #N/A | H13: =MATCH(Data!H14,$A$1:$A$5,0) -> #N/A | I13: =MATCH(Data!I14,$A$1:$A$5,0) -> #N/A | J13: =MATCH(Data!J14,$A$1:$A$5,0) -> #N/A | K13: =MATCH(Data!K14,$A$1:$A$5,0) -> #N/A | L13: =MATCH(Data!L14,$A$1:$A$5,0) -> #N/A | M13: =MATCH(Data!M14,$A$1:$A$5,0) -> #N/A | ... Y13: =MATCH(Data!Y14,$A$1:$A$5,0) -> 4 | Z13: =SUM(F13:Y13) -> #N/A
B14: 13 | C14: 46 | D14: Male | E14: Black | F14: =MATCH(Data!F15,$A$1:$A$5,0) -> #N/A | G14: =MATCH(Data!G15,$A$1:$A$5,0) -> #N/A | H14: =MATCH(Data!H15,$A$1:$A$5,0) -> #N/A | I14: =MATCH(Data!I15,$A$1:$A$5,0) -> #N/A | J14: =MATCH(Data!J15,$A$1:$A$5,0) -> #N/A | K14: =MATCH(Data!K15,$A$1:$A$5,0) -> #N/A | L14: =MATCH(Data!L15,$A$1:$A$5,0) -> #N/A | M14: =MATCH(Data!M15,$A$1:$A$5,0) -> #N/A | ... Y14: =MATCH(Data!Y15,$A$1:$A$5,0) -> 3 | Z14: =SUM(F14:Y14) -> #N/A
B15: 14 | C15: 41 | D15: Male | E15: White | F15: =MATCH(Data!F16,$A$1:$A$5,0) -> #N/A | G15: =MATCH(Data!G16,$A$1:$A$5,0) -> #N/A | H15: =MATCH(Data!H16,$A$1:$A$5,0) -> #N/A | I15: =MATCH(Data!I16,$A$1:$A$5,0) -> #N/A | J15: =MATCH(Data!J16,$A$1:$A$5,0) -> #N/A | K15: =MATCH(Data!K16,$A$1:$A$5,0) -> #N/A | L15: =MATCH(Data!L16,$A$1:$A$5,0) -> #N/A | M15: =MATCH(Data!M16,$A$1:$A$5,0) -> #N/A | ... Y15: =MATCH(Data!Y16,$A$1:$A$5,0) -> #N/A | Z15: =SUM(F15:Y15) -> #N/A
B16: 15 | C16: 28 | D16: Female | E16: Black | F16: =MATCH(Data!F17,$A$1:$A$5,0) -> #N/A | G16: =MATCH(Data!G17,$A$1:$A$5,0) -> #N/A | H16: =MATCH(Data!H17,$A$1:$A$5,0) -> #N/A | I16: =MATCH(Data!I17,$A$1:$A$5,0) -> #N/A | J16: =MATCH(Data!J17,$A$1:$A$5,0) -> #N/A | K16: =MATCH(Data!K17,$A$1:$A$5,0) -> #N/A | L16: =MATCH(Data!L17,$A$1:$A$5,0) -> #N/A | M16: =MATCH(Data!M17,$A$1:$A$5,0) -> #N/A | ... Y16: =MATCH(Data!Y17,$A$1:$A$5,0) -> #N/A | Z16: =SUM(F16:Y16) -> #N/A
B17: 16 | C17: 37 | D17: Male | E17: White | F17: =MATCH(Data!F18,$A$1:$A$5,0) -> #N/A | G17: =MATCH(Data!G18,$A$1:$A$5,0) -> #N/A | H17: =MATCH(Data!H18,$A$1:$A$5,0) -> #N/A | I17: =MATCH(Data!I18,$A$1:$A$5,0) -> #N/A | J17: =MATCH(Data!J18,$A$1:$A$5,0) -> #N/A | K17: =MATCH(Data!K18,$A$1:$A$5,0) -> #N/A | L17: =MATCH(Data!L18,$A$1:$A$5,0) -> #N/A | M17: =MATCH(Data!M18,$A$1:$A$5,0) -> #N/A | ... Y17: =MATCH(Data!Y18,$A$1:$A$5,0) -> #N/A | Z17: =SUM(F17:Y17) -> #N/A
B18: 17 | C18: 32 | D18: Female | E18: White | F18: =MATCH(Data!F19,$A$1:$A$5,0) -> #N/A | G18: =MATCH(Data!G19,$A$1:$A$5,0) -> #N/A | H18: =MATCH(Data!H19,$A$1:$A$5,0) -> #N/A | I18: =MATCH(Data!I19,$A$1:$A$5,0) -> #N/A | J18: =MATCH(Data!J19,$A$1:$A$5,0) -> #N/A | K18: =MATCH(Data!K19,$A$1:$A$5,0) -> #N/A | L18: =MATCH(Data!L19,$A$1:$A$5,0) -> #N/A | M18: =MATCH(Data!M19,$A$1:$A$5,0) -> #N/A | ... Y18: =MATCH(Data!Y19,$A$1:$A$5,0) -> 3 | Z18: =SUM(F18:Y18) -> #N/A
B19: 18 | C19: 48 | D19: Female | E19: White | F19: =MATCH(Data!F20,$A$1:$A$5,0) -> #N/A | G19: =MATCH(Data!G20,$A$1:$A$5,0) -> #N/A | H19: =MATCH(Data!H20,$A$1:$A$5,0) -> #N/A | I19: =MATCH(Data!I20,$A$1:$A$5,0) -> #N/A | J19: =MATCH(Data!J20,$A$1:$A$5,0) -> #N/A | K19: =MATCH(Data!K20,$A$1:$A$5,0) -> #N/A | L19: =MATCH(Data!L20,$A$1:$A$5,0) -> #N/A | M19: =MATCH(Data!M20,$A$1:$A$5,0) -> #N/A | ... Y19: =MATCH(Data!Y20,$A$1:$A$5,0) -> #N/A | Z19: =SUM(F19:Y19) -> #N/A
B20: 19 | C20: 30 | D20: Female | E20: White | F20: =MATCH(Data!F21,$A$1:$A$5,0) -> #N/A | G20: =MATCH(Data!G21,$A$1:$A$5,0) -> #N/A | H20: =MATCH(Data!H21,$A$1:$A$5,0) -> #N/A | I20: =MATCH(Data!I21,$A$1:$A$5,0) -> #N/A | J20: =MATCH(Data!J21,$A$1:$A$5,0) -> #N/A | K20: =MATCH(Data!K21,$A$1:$A$5,0) -> #N/A | L20: =MATCH(Data!L21,$A$1:$A$5,0) -> #N/A | M20: =MATCH(Data!M21,$A$1:$A$5,0) -> #N/A | ... Y20: =MATCH(Data!Y21,$A$1:$A$5,0) -> #N/A | Z20: =SUM(F20:Y20) -> #N/A
B21: 20 | C21: 28 | D21: Female | E21: Hispanic | F21: =MATCH(Data!F22,$A$1:$A$5,0) -> #N/A | G21: =MATCH(Data!G22,$A$1:$A$5,0) -> #N/A | H21: =MATCH(Data!H22,$A$1:$A$5,0) -> #N/A | I21: =MATCH(Data!I22,$A$1:$A$5,0) -> #N/A | J21: =MATCH(Data!J22,$A$1:$A$5,0) -> #N/A | K21: =MATCH(Data!K22,$A$1:$A$5,0) -> #N/A | L21: =MATCH(Data!L22,$A$1:$A$5,0) -> #N/A | M21: =MATCH(Data!M22,$A$1:$A$5,0) -> #N/A | ... Y21: =MATCH(Data!Y22,$A$1:$A$5,0) -> #N/A | Z21: =SUM(F21:Y21) -> #N/A
B22: 21 | C22: 31 | D22: Female | E22: Black | F22: =MATCH(Data!F23,$A$1:$A$5,0) -> #N/A | G22: =MATCH(Data!G23,$A$1:$A$5,0) -> #N/A | H22: =MATCH(Data!H23,$A$1:$A$5,0) -> #N/A | I22: =MATCH(Data!I23,$A$1:$A$5,0) -> #N/A | J22: =MATCH(Data!J23,$A$1:$A$5,0) -> #N/A | K22: =MATCH(Data!K23,$A$1:$A$5,0) -> #N/A | L22: =MATCH(Data!L23,$A$1:$A$5,0) -> #N/A | M22: =MATCH(Data!M23,$A$1:$A$5,0) -> #N/A | ... Y22: =MATCH(Data!Y23,$A$1:$A$5,0) -> #N/A | Z22: =SUM(F22:Y22) -> #N/A
B23: 22 | C23: 29 | D23: Female | E23: White | F23: =MATCH(Data!F24,$A$1:$A$5,0) -> #N/A | G23: =MATCH(Data!G24,$A$1:$A$5,0) -> #N/A | H23: =MATCH(Data!H24,$A$1:$A$5,0) -> #N/A | I23: =MATCH(Data!I24,$A$1:$A$5,0) -> #N/A | J23: =MATCH(Data!J24,$A$1:$A$5,0) -> #N/A | K23: =MATCH(#REF!,$A$1:$A$5,0) -> #REF! | L23: =MATCH(Data!K24,$A$1:$A$5,0) -> #N/A | M23: =MATCH(Data!M24,$A$1:$A$5,0) -> #N/A | N23: =MATCH(Data!N24,$A$1:$A$5,0) -> #N/A | O23: =MATCH(Data!O24,$A$1:$A$5,0) -> #N/A | P23: =MATCH(Data!P24,$A$1:$A$5,0) -> #N/A | Q23: =MATCH(Data!Q24,$A$1:$A$5,0) -> #N/A | R23: =MATCH(Data!R24,$A$1:$A$5,0) -> 4 | S23: =MATCH(Data!S24,$A$1:$A$5,0) -> 3 | T23: =MATCH(Data!T24,$A$1:$A$5,0) -> 2 | ... Y23: =MATCH(Data!Y24,$A$1:$A$5,0) -> 4 | Z23: =SUM(F23:Y23) -> #N/A
B24: 23 | C24: 26 | D24: Male | E24: White | F24: =MATCH(Data!F25,$A$1:$A$5,0) -> #N/A | G24: =MATCH(Data!G25,$A$1:$A$5,0) -> #N/A | H24: =MATCH(Data!H25,$A$1:$A$5,0) -> #N/A | I24: =MATCH(Data!I25,$A$1:$A$5,0) -> #N/A | J24: =MATCH(Data!J25,$A$1:$A$5,0) -> #N/A | K24: =MATCH(Data!K25,$A$1:$A$5,0) -> #N/A | L24: =MATCH(Data!L25,$A$1:$A$5,0) -> #N/A | M24: =MATCH(Data!M25,$A$1:$A$5,0) -> #N/A | ... Y24: =MATCH(Data!Y25,$A$1:$A$5,0) -> 4 | Z24: =SUM(F24:Y24) -> #N/A
B25: 24 | C25: 28 | D25: Female | E25: White | F25: =MATCH(Data!F26,$A$1:$A$5,0) -> #N/A | G25: =MATCH(Data!G26,$A$1:$A$5,0) -> #N/A | H25: =MATCH(Data!H26,$A$1:$A$5,0) -> #N/A | I25: =MATCH(Data!I26,$A$1:$A$5,0) -> #N/A | J25: =MATCH(Data!J26,$A$1:$A$5,0) -> #N/A | K25: =MATCH(Data!K26,$A$1:$A$5,0) -> #N/A | L25: =MATCH(Data!L26,$A$1:$A$5,0) -> #N/A | M25: =MATCH(Data!M26,$A$1:$A$5,0) -> #N/A | ... Y25: =MATCH(Data!Y26,$A$1:$A$5,0) -> #N/A | Z25: =SUM(F25:Y25) -> #N/A
B26: 25 | C26: 25 | D26: Male | E26: Black | F26: =MATCH(Data!F27,$A$1:$A$5,0) -> #N/A | G26: =MATCH(Data!G27,$A$1:$A$5,0) -> #N/A | H26: =MATCH(Data!H27,$A$1:$A$5,0) -> #N/A | I26: =MATCH(Data!I27,$A$1:$A$5,0) -> #N/A | J26: =MATCH(Data!J27,$A$1:$A$5,0) -> #N/A | K26: =MATCH(Data!K27,$A$1:$A$5,0) -> #N/A | L26: =MATCH(Data!L27,$A$1:$A$5,0) -> #N/A | M26: =MATCH(Data!M27,$A$1:$A$5,0) -> #N/A | ... Y26: =MATCH(Data!Y27,$A$1:$A$5,0) -> #N/A | Z26: =SUM(F26:Y26) -> #N/A
B27: 26 | C27: 29 | D27: Female | E27: White | F27: =MATCH(Data!F28,$A$1:$A$5,0) -> #N/A | G27: =MATCH(Data!G28,$A$1:$A$5,0) -> #N/A | H27: =MATCH(Data!H28,$A$1:$A$5,0) -> #N/A | I27: =MATCH(Data!I28,$A$1:$A$5,0) -> #N/A | J27: =MATCH(Data!J28,$A$1:$A$5,0) -> #N/A | K27: =MATCH(Data!K28,$A$1:$A$5,0) -> #N/A | L27: =MATCH(Data!L28,$A$1:$A$5,0) -> #N/A | M27: =MATCH(Data!M28,$A$1:$A$5,0) -> #N/A | ... Y27: =MATCH(Data!Y28,$A$1:$A$5,0) -> #N/A | Z27: =SUM(F27:Y27) -> #N/A
B28: 27 | C28: 45 | D28: Male | E28: White | F28: =MATCH(Data!F29,$A$1:$A$5,0) -> #N/A | G28: =MATCH(Data!G29,$A$1:$A$5,0) -> #N/A | H28: =MATCH(Data!H29,$A$1:$A$5,0) -> #N/A | I28: =MATCH(Data!I29,$A$1:$A$5,0) -> #N/A | J28: =MATCH(Data!J29,$A$1:$A$5,0) -> #N/A | K28: =MATCH(Data!K29,$A$1:$A$5,0) -> #N/A | L28: =MATCH(Data!L29,$A$1:$A$5,0) -> #N/A | M28: =MATCH(Data!M29,$A$1:$A$5,0) -> #N/A | ... Y28: =MATCH(Data!Y29,$A$1:$A$5,0) -> #N/A | Z28: =SUM(F28:Y28) -> #N/A
B29: 28 | C29: 49 | D29: Male | E29: White | F29: =MATCH(Data!F30,$A$1:$A$5,0) -> #N/A | G29: =MATCH(Data!G30,$A$1:$A$5,0) -> #N/A | H29: =MATCH(Data!H30,$A$1:$A$5,0) -> #N/A | I29: =MATCH(Data!I30,$A$1:$A$5,0) -> #N/A | J29: =MATCH(Data!J30,$A$1:$A$5,0) -> #N/A | K29: =MATCH(Data!K30,$A$1:$A$5,0) -> #N/A | L29: =MATCH(Data!L30,$A$1:$A$5,0) -> #N/A | M29: =MATCH(Data!M30,$A$1:$A$5,0) -> #N/A | ... Y29: =MATCH(Data!Y30,$A$1:$A$5,0) -> 3 | Z29: =SUM(F29:Y29) -> #N/A
B30: 29 | C30: 25 | D30: Male | E30: White | F30: =MATCH(Data!F31,$A$1:$A$5,0) -> #N/A | G30: =MATCH(Data!G31,$A$1:$A$5,0) -> #N/A | H30: =MATCH(Data!H31,$A$1:$A$5,0) -> #N/A | I30: =MATCH(Data!I31,$A$1:$A$5,0) -> #N/A | J30: =MATCH(Data!J31,$A$1:$A$5,0) -> #N/A | K30: =MATCH(Data!K31,$A$1:$A$5,0) -> #N/A | L30: =MATCH(Data!L31,$A$1:$A$5,0) -> #N/A | M30: =MATCH(Data!M31,$A$1:$A$5,0) -> #N/A | ... Y30: =MATCH(Data!Y31,$A$1:$A$5,0) -> 4 | Z30: =SUM(F30:Y30) -> #N/A
B31: 30 | C31: 47 | D31: Male | E31: White | F31: =MATCH(Data!F32,$A$1:$A$5,0) -> #N/A | G31: =MATCH(Data!G32,$A$1:$A$5,0) -> #N/A | H31: =MATCH(Data!H32,$A$1:$A$5,0) -> #N/A | I31: =MATCH(Data!I32,$A$1:$A$5,0) -> #N/A | J31: =MATCH(Data!J32,$A$1:$A$5,0) -> #N/A | K31: =MATCH(Data!K32,$A$1:$A$5,0) -> #N/A | L31: =MATCH(Data!L32,$A$1:$A$5,0) -> #N/A | M31: =MATCH(Data!M32,$A$1:$A$5,0) -> #N/A | ... Y31: =MATCH(Data!Y32,$A$1:$A$5,0) -> #N/A | Z31: =SUM(F31:Y31) -> #N/A
B32: 31 | C32: 44 | D32: Female | E32: White | F32: =MATCH(Data!F33,$A$1:$A$5,0) -> #N/A | G32: =MATCH(Data!G33,$A$1:$A$5,0) -> #N/A | H32: =MATCH(Data!H33,$A$1:$A$5,0) -> #N/A | I32: =MATCH(Data!I33,$A$1:$A$5,0) -> #N/A | J32: =MATCH(Data!J33,$A$1:$A$5,0) -> #N/A | K32: =MATCH(Data!K33,$A$1:$A$5,0) -> #N/A | L32: =MATCH(Data!L33,$A$1:$A$5,0) -> #N/A | M32: =MATCH(Data!M33,$A$1:$A$5,0) -> #N/A | ... Y32: =MATCH(Data!Y33,$A$1:$A$5,0) -> #N/A | Z32: =SUM(F32:Y32) -> #N/A
B33: 32 | C33: 47 | D33: Female | E33: White | F33: =MATCH(Data!F34,$A$1:$A$5,0) -> #N/A | G33: =MATCH(Data!G34,$A$1:$A$5,0) -> #N/A | H33: =MATCH(Data!H34,$A$1:$A$5,0) -> #N/A | I33: =MATCH(Data!I34,$A$1:$A$5,0) -> #N/A | J33: =MATCH(Data!J34,$A$1:$A$5,0) -> #N/A | K33: =MATCH(Data!K34,$A$1:$A$5,0) -> #N/A | L33: =MATCH(Data!L34,$A$1:$A$5,0) -> #N/A | M33: =MATCH(Data!M34,$A$1:$A$5,0) -> #N/A | ... Y33: =MATCH(Data!Y34,$A$1:$A$5,0) -> #N/A | Z33: =SUM(F33:Y33) -> #N/A
B34: 33 | C34: 24 | D34: Female | E34: White | F34: =MATCH(Data!F35,$A$1:$A$5,0) -> #N/A | G34: =MATCH(Data!G35,$A$1:$A$5,0) -> #N/A | H34: =MATCH(Data!H35,$A$1:$A$5,0) -> #N/A | I34: =MATCH(Data!I35,$A$1:$A$5,0) -> #N/A | J34: =MATCH(Data!J35,$A$1:$A$5,0) -> #N/A | K34: =MATCH(Data!K35,$A$1:$A$5,0) -> #N/A | L34: =MATCH(Data!L35,$A$1:$A$5,0) -> #N/A | M34: =MATCH(Data!M35,$A$1:$A$5,0) -> #N/A | ... Y34: =MATCH(Data!Y35,$A$1:$A$5,0) -> 4 | Z34: =SUM(F34:Y34) -> #N/A
B35: 34 | C35: 29 | D35: Female | E35: White | F35: =MATCH(Data!F36,$A$1:$A$5,0) -> #N/A | G35: =MATCH(Data!G36,$A$1:$A$5,0) -> #N/A | H35: =MATCH(Data!H36,$A$1:$A$5,0) -> #N/A | I35: =MATCH(Data!I36,$A$1:$A$5,0) -> #N/A | J35: =MATCH(Data!J36,$A$1:$A$5,0) -> #N/A | K35: =MATCH(Data!K36,$A$1:$A$5,0) -> #N/A | L35: =MATCH(Data!L36,$A$1:$A$5,0) -> #N/A | M35: =MATCH(Data!M36,$A$1:$A$5,0) -> #N/A | ... Y35: =MATCH(Data!Y36,$A$1:$A$5,0) -> 2 | Z35: =SUM(F35:Y35) -> #N/A
... B37: 36 | C37: 38 | D37: Female | E37: White | F37: =MATCH(Data!F38,$A$1:$A$5,0) -> #N/A | G37: =MATCH(Data!G38,$A$1:$A$5,0) -> #N/A | H37: =MATCH(Data!H38,$A$1:$A$5,0) -> #N/A | I37: =MATCH(Data!I38,$A$1:$A$5,0) -> #N/A | J37: =MATCH(Data!J38,$A$1:$A$5,0) -> #N/A | K37: =MATCH(Data!K38,$A$1:$A$5,0) -> #N/A | L37: =MATCH(Data!L38,$A$1:$A$5,0) -> #N/A | M37: =MATCH(Data!M38,$A$1:$A$5,0) -> #N/A | ... Y37: =MATCH(Data!Y38,$A$1:$A$5,0) -> #N/A | Z37: =SUM(F37:Y37) -> #N/A
B38: 37 | C38: 52 | D38: Female | E38: Black | F38: =MATCH(#REF!,$A$1:$A$5,0) -> #REF! | G38: =MATCH(#REF!,$A$1:$A$5,0) -> #REF! | H38: =MATCH(#REF!,$A$1:$A$5,0) -> #REF! | I38: =MATCH(#REF!,$A$1:$A$5,0) -> #REF! | J38: =MATCH(#REF!,$A$1:$A$5,0) -> #REF! | K38: =MATCH(#REF!,$A$1:$A$5,0) -> #REF! | L38: =MATCH(#REF!,$A$1:$A$5,0) -> #REF! | M38: =MATCH(#REF!,$A$1:$A$5,0) -> #REF! | ... Y38: =MATCH(#REF!,$A$1:$A$5,0) -> #REF! | Z38: =SUM(F38:Y38) -> #REF!
B39: 38 | C39: 32 | D39: Male | E39: Black | F39: =MATCH(#REF!,$A$1:$A$5,0) -> #REF! | G39: =MATCH(#REF!,$A$1:$A$5,0) -> #REF! | H39: =MATCH(#REF!,$A$1:$A$5,0) -> #REF! | I39: =MATCH(#REF!,$A$1:$A$5,0) -> #REF! | J39: =MATCH(#REF!,$A$1:$A$5,0) -> #REF! | K39: =MATCH(#REF!,$A$1:$A$5,0) -> #REF! | L39: =MATCH(#REF!,$A$1:$A$5,0) -> #REF! | M39: =MATCH(#REF!,$A$1:$A$5,0) -> #REF! | ... Y39: =MATCH(#REF!,$A$1:$A$5,0) -> #REF! | Z39: =SUM(F39:Y39) -> #REF!
B40: 39 | C40: 28 | D40: Female | E40: Black | F40: =MATCH(#REF!,$A$1:$A$5,0) -> #REF! | G40: =MATCH(#REF!,$A$1:$A$5,0) -> #REF! | H40: =MATCH(#REF!,$A$1:$A$5,0) -> #REF! | I40: =MATCH(#REF!,$A$1:$A$5,0) -> #REF! | J40: =MATCH(#REF!,$A$1:$A$5,0) -> #REF! | K40: =MATCH(#REF!,$A$1:$A$5,0) -> #REF! | L40: =MATCH(#REF!,$A$1:$A$5,0) -> #REF! | M40: =MATCH(#REF!,$A$1:$A$5,0) -> #REF! | ... Y40: =MATCH(#REF!,$A$1:$A$5,0) -> #REF! | Z40: =SUM(F40:Y40) -> #REF!
B41: 40 | C41: 29 | D41: Female | E41: White | F41: =MATCH(#REF!,$A$1:$A$5,0) -> #REF! | G41: =MATCH(#REF!,$A$1:$A$5,0) -> #REF! | H41: =MATCH(#REF!,$A$1:$A$5,0) -> #REF! | I41: =MATCH(#REF!,$A$1:$A$5,0) -> #REF! | J41: =MATCH(#REF!,$A$1:$A$5,0) -> #REF! | K41: =MATCH(#REF!,$A$1:$A$5,0) -> #REF! | L41: =MATCH(#REF!,$A$1:$A$5,0) -> #REF! | M41: =MATCH(#REF!,$A$1:$A$5,0) -> #REF! | ... Y41: =MATCH(#REF!,$A$1:$A$5,0) -> #REF! | Z41: =SUM(F41:Y41) -> #REF!
B42: 41 | C42: 51 | D42: Female | E42: White | F42: =MATCH(#REF!,$A$1:$A$5,0) -> #REF! | G42: =MATCH(#REF!,$A$1:$A$5,0) -> #REF! | H42: =MATCH(#REF!,$A$1:$A$5,0) -> #REF! | I42: =MATCH(#REF!,$A$1:$A$5,0) -> #REF! | J42: =MATCH(#REF!,$A$1:$A$5,0) -> #REF! | K42: =MATCH(#REF!,$A$1:$A$5,0) -> #REF! | L42: =MATCH(#REF!,$A$1:$A$5,0) -> #REF! | M42: =MATCH(#REF!,$A$1:$A$5,0) -> #REF! | ... Y42: =MATCH(#REF!,$A$1:$A$5,0) -> #REF! | Z42: =SUM(F42:Y42) -> #REF!
B43: 42 | C43: 30 | D43: Male | E43: White | F43: =MATCH(#REF!,$A$1:$A$5,0) -> #REF! | G43: =MATCH(#REF!,$A$1:$A$5,0) -> #REF! | H43: =MATCH(#REF!,$A$1:$A$5,0) -> #REF! | I43: =MATCH(#REF!,$A$1:$A$5,0) -> #REF! | J43: =MATCH(#REF!,$A$1:$A$5,0) -> #REF! | K43: =MATCH(#REF!,$A$1:$A$5,0) -> #REF! | L43: =MATCH(#REF!,$A$1:$A$5,0) -> #REF! | M43: =MATCH(#REF!,$A$1:$A$5,0) -> #REF! | ... Y43: =MATCH(#REF!,$A$1:$A$5,0) -> #REF! | Z43: =SUM(F43:Y43) -> #REF!
B44: 43 | C44: 53 | D44: Male | E44: Black | F44: =MATCH(#REF!,$A$1:$A$5,0) -> #REF! | G44: =MATCH(#REF!,$A$1:$A$5,0) -> #REF! | H44: =MATCH(#REF!,$A$1:$A$5,0) -> #REF! | I44: =MATCH(#REF!,$A$1:$A$5,0) -> #REF! | J44: =MATCH(#REF!,$A$1:$A$5,0) -> #REF! | K44: =MATCH(#REF!,$A$1:$A$5,0) -> #REF! | L44: =MATCH(#REF!,$A$1:$A$5,0) -> #REF! | M44: =MATCH(#REF!,$A$1:$A$5,0) -> #REF! | ... Y44: =MATCH(#REF!,$A$1:$A$5,0) -> #REF! | Z44: =SUM(F44:Y44) -> #REF!
B45: 44 | C45: 45 | D45: Female | E45: Black | F45: =MATCH(#REF!,$A$1:$A$5,0) -> #REF! | G45: =MATCH(#REF!,$A$1:$A$5,0) -> #REF! | H45: =MATCH(#REF!,$A$1:$A$5,0) -> #REF! | I45: =MATCH(#REF!,$A$1:$A$5,0) -> #REF! | J45: =MATCH(#REF!,$A$1:$A$5,0) -> #REF! | K45: =MATCH(#REF!,$A$1:$A$5,0) -> #REF! | L45: =MATCH(#REF!,$A$1:$A$5,0) -> #REF! | M45: =MATCH(#REF!,$A$1:$A$5,0) -> #REF! | ... Y45: =MATCH(#REF!,$A$1:$A$5,0) -> #REF! | Z45: =SUM(F45:Y45) -> #REF!
B46: 45 | C46: 39 | D46: Female | E46: White | F46: =MATCH(#REF!,$A$1:$A$5,0) -> #REF! | G46: =MATCH(#REF!,$A$1:$A$5,0) -> #REF! | H46: =MATCH(#REF!,$A$1:$A$5,0) -> #REF! | I46: =MATCH(#REF!,$A$1:$A$5,0) -> #REF! | J46: =MATCH(#REF!,$A$1:$A$5,0) -> #REF! | K46: =MATCH(#REF!,$A$1:$A$5,0) -> #REF! | L46: =MATCH(#REF!,$A$1:$A$5,0) -> #REF! | M46: =MATCH(#REF!,$A$1:$A$5,0) -> #REF! | ... Y46: =MATCH(#REF!,$A$1:$A$5,0) -> #REF! | Z46: =SUM(F46:Y46) -> #REF!
B47: 46 | C47: 38 | D47: Female | E47: White | F47: =MATCH(#REF!,$A$1:$A$5,0) -> #REF! | G47: =MATCH(#REF!,$A$1:$A$5,0) -> #REF! | H47: =MATCH(#REF!,$A$1:$A$5,0) -> #REF! | I47: =MATCH(#REF!,$A$1:$A$5,0) -> #REF! | J47: =MATCH(#REF!,$A$1:$A$5,0) -> #REF! | K47: =MATCH(#REF!,$A$1:$A$5,0) -> #REF! | L47: =MATCH(#REF!,$A$1:$A$5,0) -> #REF! | M47: =MATCH(#REF!,$A$1:$A$5,0) -> #REF! | ... Y47: =MATCH(#REF!,$A$1:$A$5,0) -> #REF! | Z47: =SUM(F47:Y47) -> #REF!
B48: 47 | C48: 32 | D48: Female | E48: Black | F48: =MATCH(#REF!,$A$1:$A$5,0) -> #REF! | G48: =MATCH(#REF!,$A$1:$A$5,0) -> #REF! | H48: =MATCH(#REF!,$A$1:$A$5,0) -> #REF! | I48: =MATCH(#REF!,$A$1:$A$5,0) -> #REF! | J48: =MATCH(#REF!,$A$1:$A$5,0) -> #REF! | K48: =MATCH(#REF!,$A$1:$A$5,0) -> #REF! | L48: =MATCH(#REF!,$A$1:$A$5,0) -> #REF! | M48: =MATCH(#REF!,$A$1:$A$5,0) -> #REF! | ... Y48: =MATCH(#REF!,$A$1:$A$5,0) -> #REF! | Z48: =SUM(F48:Y48) -> #REF!
B49: 48 | C49: 47 | D49: Female | E49: White | F49: =MATCH(#REF!,$A$1:$A$5,0) -> #REF! | G49: =MATCH(#REF!,$A$1:$A$5,0) -> #REF! | H49: =MATCH(#REF!,$A$1:$A$5,0) -> #REF! | I49: =MATCH(#REF!,$A$1:$A$5,0) -> #REF! | J49: =MATCH(#REF!,$A$1:$A$5,0) -> #REF! | K49: =MATCH(#REF!,$A$1:$A$5,0) -> #REF! | L49: =MATCH(#REF!,$A$1:$A$5,0) -> #REF! | M49: =MATCH(#REF!,$A$1:$A$5,0) -> #REF! | ... Y49: =MATCH(#REF!,$A$1:$A$5,0) -> #REF! | Z49: =SUM(F49:Y49) -> #REF!
B50: 49 | C50: 26 | D50: Female | E50: White | F50: =MATCH(#REF!,$A$1:$A$5,0) -> #REF! | G50: =MATCH(#REF!,$A$1:$A$5,0) -> #REF! | H50: =MATCH(#REF!,$A$1:$A$5,0) -> #REF! | I50: =MATCH(#REF!,$A$1:$A$5,0) -> #REF! | J50: =MATCH(#REF!,$A$1:$A$5,0) -> #REF! | K50: =MATCH(#REF!,$A$1:$A$5,0) -> #REF! | L50: =MATCH(#REF!,$A$1:$A$5,0) -> #REF! | M50: =MATCH(#REF!,$A$1:$A$5,0) -> #REF! | ... Y50: =MATCH(#REF!,$A$1:$A$5,0) -> #REF! | Z50: =SUM(F50:Y50) -> #REF!
B51: 50 | C51: 27 | D51: Female | E51: Black | F51: =MATCH(Data!F39,$A$1:$A$5,0) -> #N/A | G51: =MATCH(Data!G39,$A$1:$A$5,0) -> #N/A | H51: =MATCH(Data!H39,$A$1:$A$5,0) -> #N/A | I51: =MATCH(Data!I39,$A$1:$A$5,0) -> #N/A | J51: =MATCH(Data!J39,$A$1:$A$5,0) -> #N/A | K51: =MATCH(Data!K39,$A$1:$A$5,0) -> #N/A | L51: =MATCH(Data!L39,$A$1:$A$5,0) -> #N/A | M51: =MATCH(Data!M39,$A$1:$A$5,0) -> #N/A | ... O51: =MATCH(Data!O39,$A$1:$A$5,0) -> #N/A | P51: =MATCH(Data!Q39,$A$1:$A$5,0) -> #N/A | Q51: =MATCH(Data!R39,$A$1:$A$5,0) -> 4 | R51: =MATCH(Data!S39,$A$1:$A$5,0) -> #N/A | S51: =MATCH(Data!T39,$A$1:$A$5,0) -> #N/A | T51: =MATCH(Data!U39,$A$1:$A$5,0) -> #N/A | U51: =MATCH(Data!V39,$A$1:$A$5,0) -> #N/A | V51: =MATCH(Data!W39,$A$1:$A$5,0) -> #N/A | W51: =MATCH(Data!X39,$A$1:$A$5,0) -> 4 | ... Y51: =MATCH(Data!Z39,$A$1:$A$5,0) -> #N/A | Z51: =SUM(F51:Y51) -> #N/A
B52: 51 | C52: 50 | D52: Female | E52: Black | F52: =MATCH(Data!F40,$A$1:$A$5,0) -> #N/A | G52: =MATCH(Data!G40,$A$1:$A$5,0) -> #N/A | H52: =MATCH(Data!H40,$A$1:$A$5,0) -> #N/A | I52: =MATCH(Data!I40,$A$1:$A$5,0) -> #N/A | J52: =MATCH(Data!J40,$A$1:$A$5,0) -> #N/A | K52: =MATCH(Data!K40,$A$1:$A$5,0) -> #N/A | L52: =MATCH(Data!L40,$A$1:$A$5,0) -> #N/A | M52: =MATCH(Data!M40,$A$1:$A$5,0) -> #N/A | ... Y52: =MATCH(Data!Y40,$A$1:$A$5,0) -> #N/A | Z52: =SUM(F52:Y52) -> #N/A
B53: 52 | C53: 31 | D53: Female | E53: White | F53: =MATCH(Data!F41,$A$1:$A$5,0) -> #N/A | G53: =MATCH(Data!G41,$A$1:$A$5,0) -> #N/A | H53: =MATCH(Data!H41,$A$1:$A$5,0) -> #N/A | I53: =MATCH(Data!I41,$A$1:$A$5,0) -> #N/A | J53: =MATCH(Data!J41,$A$1:$A$5,0) -> #N/A | K53: =MATCH(Data!K41,$A$1:$A$5,0) -> #N/A | L53: =MATCH(Data!L41,$A$1:$A$5,0) -> #N/A | M53: =MATCH(Data!M41,$A$1:$A$5,0) -> #N/A | ... Y53: =MATCH(Data!Y41,$A$1:$A$5,0) -> 4 | Z53: =SUM(F53:Y53) -> #N/A
B54: 53 | C54: 29 | D54: Male | E54: White | F54: =MATCH(Data!F42,$A$1:$A$5,0) -> #N/A | G54: =MATCH(#REF!,$A$1:$A$5,0) -> #REF! | H54: =MATCH(Data!G42,$A$1:$A$5,0) -> #N/A | I54: =MATCH(Data!H42,$A$1:$A$5,0) -> #N/A | J54: =MATCH(Data!J42,$A$1:$A$5,0) -> #N/A | K54: =MATCH(Data!K42,$A$1:$A$5,0) -> #N/A | L54: =MATCH(Data!L42,$A$1:$A$5,0) -> #N/A | M54: =MATCH(Data!M42,$A$1:$A$5,0) -> #N/A | N54: =MATCH(Data!N42,$A$1:$A$5,0) -> #N/A | O54: =MATCH(Data!O42,$A$1:$A$5,0) -> #N/A | P54: =MATCH(Data!P42,$A$1:$A$5,0) -> #N/A | Q54: =MATCH(Data!Q42,$A$1:$A$5,0) -> #N/A | ... U54: =MATCH(Data!U42,$A$1:$A$5,0) -> #N/A | V54: =MATCH(#REF!,$A$1:$A$5,0) -> #REF! | W54: =MATCH(Data!V42,$A$1:$A$5,0) -> 4 | X54: =MATCH(Data!W42,$A$1:$A$5,0) -> #N/A | Y54: =MATCH(Data!X42,$A$1:$A$5,0) -> 4 | Z54: =SUM(F54:Y54) -> #N/A
B55: 54 | C55: 50 | D55: Male | E55: Black | F55: =MATCH(Data!F43,$A$1:$A$5,0) -> #N/A | G55: =MATCH(Data!G43,$A$1:$A$5,0) -> #N/A | H55: =MATCH(Data!H43,$A$1:$A$5,0) -> #N/A | I55: =MATCH(Data!I43,$A$1:$A$5,0) -> #N/A | J55: =MATCH(Data!J43,$A$1:$A$5,0) -> #N/A | K55: =MATCH(Data!K43,$A$1:$A$5,0) -> #N/A | L55: =MATCH(Data!L43,$A$1:$A$5,0) -> #N/A | M55: =MATCH(Data!M43,$A$1:$A$5,0) -> #N/A | ... Y55: =MATCH(Data!Y43,$A$1:$A$5,0) -> 4 | Z55: =SUM(F55:Y55) -> #N/A
B56: 55 | C56: 42 | D56: Female | E56: White | F56: =MATCH(Data!F44,$A$1:$A$5,0) -> #N/A | G56: =MATCH(Data!G44,$A$1:$A$5,0) -> #N/A | H56: =MATCH(Data!H44,$A$1:$A$5,0) -> #N/A | I56: =MATCH(Data!I44,$A$1:$A$5,0) -> #N/A | J56: =MATCH(Data!J44,$A$1:$A$5,0) -> #N/A | K56: =MATCH(Data!K44,$A$1:$A$5,0) -> #N/A | L56: =MATCH(Data!L44,$A$1:$A$5,0) -> #N/A | M56: =MATCH(Data!M44,$A$1:$A$5,0) -> #N/A | ... Y56: =MATCH(Data!Y44,$A$1:$A$5,0) -> #N/A | Z56: =SUM(F56:Y56) -> #N/A
B57: 56 | C57: 28 | D57: Male | E57: White | F57: =MATCH(Data!F45,$A$1:$A$5,0) -> #N/A | G57: =MATCH(Data!G45,$A$1:$A$5,0) -> #N/A | H57: =MATCH(Data!H45,$A$1:$A$5,0) -> #N/A | I57: =MATCH(Data!I45,$A$1:$A$5,0) -> #N/A | J57: =MATCH(Data!J45,$A$1:$A$5,0) -> #N/A | K57: =MATCH(Data!K45,$A$1:$A$5,0) -> #N/A | L57: =MATCH(Data!L45,$A$1:$A$5,0) -> #N/A | M57: =MATCH(Data!M45,$A$1:$A$5,0) -> #N/A | ... Y57: =MATCH(Data!Y45,$A$1:$A$5,0) -> 4 | Z57: =SUM(F57:Y57) -> #N/A
B58: 57 | C58: 35 | D58: Female | E58: Hispanic | F58: =MATCH(Data!F46,$A$1:$A$5,0) -> #N/A | G58: =MATCH(Data!G46,$A$1:$A$5,0) -> #N/A | H58: =MATCH(Data!H46,$A$1:$A$5,0) -> #N/A | I58: =MATCH(Data!I46,$A$1:$A$5,0) -> #N/A | J58: =MATCH(Data!J46,$A$1:$A$5,0) -> #N/A | K58: =MATCH(Data!K46,$A$1:$A$5,0) -> #N/A | L58: =MATCH(Data!L46,$A$1:$A$5,0) -> #N/A | M58: =MATCH(Data!M46,$A$1:$A$5,0) -> #N/A | ... Y58: =MATCH(Data!Y46,$A$1:$A$5,0) -> 3 | Z58: =SUM(F58:Y58) -> #N/A
B59: 58 | C59: 39 | D59: Female | E59: White | F59: =MATCH(Data!F47,$A$1:$A$5,0) -> #N/A | G59: =MATCH(Data!G47,$A$1:$A$5,0) -> #N/A | H59: =MATCH(Data!H47,$A$1:$A$5,0) -> #N/A | I59: =MATCH(Data!I47,$A$1:$A$5,0) -> #N/A | J59: =MATCH(Data!J47,$A$1:$A$5,0) -> #N/A | K59: =MATCH(Data!K47,$A$1:$A$5,0) -> #N/A | L59: =MATCH(Data!L47,$A$1:$A$5,0) -> #N/A | M59: =MATCH(Data!M47,$A$1:$A$5,0) -> #N/A | ... Y59: =MATCH(Data!Y47,$A$1:$A$5,0) -> 3 | Z59: =SUM(F59:Y59) -> #N/A
B60: 59 | C60: 31 | D60: Male | E60: Black | F60: =MATCH(Data!F48,$A$1:$A$5,0) -> #N/A | G60: =MATCH(Data!G48,$A$1:$A$5,0) -> #N/A | H60: =MATCH(Data!H48,$A$1:$A$5,0) -> #N/A | I60: =MATCH(Data!I48,$A$1:$A$5,0) -> #N/A | J60: =MATCH(Data!J48,$A$1:$A$5,0) -> #N/A | K60: =MATCH(Data!K48,$A$1:$A$5,0) -> #N/A | L60: =MATCH(Data!L48,$A$1:$A$5,0) -> #N/A | M60: =MATCH(Data!M48,$A$1:$A$5,0) -> #N/A | ... Y60: =MATCH(Data!Y48,$A$1:$A$5,0) -> 4 | Z60: =SUM(F60:Y60) -> #N/A
B61: 60 | C61: 38 | D61: Male | E61: White | F61: =MATCH(Data!F49,$A$1:$A$5,0) -> #N/A | G61: =MATCH(Data!G49,$A$1:$A$5,0) -> #N/A | H61: =MATCH(Data!H49,$A$1:$A$5,0) -> #N/A | I61: =MATCH(Data!I49,$A$1:$A$5,0) -> #N/A | J61: =MATCH(Data!J49,$A$1:$A$5,0) -> #N/A | K61: =MATCH(Data!K49,$A$1:$A$5,0) -> #N/A | L61: =MATCH(Data!L49,$A$1:$A$5,0) -> #N/A | M61: =MATCH(Data!M49,$A$1:$A$5,0) -> #N/A | ... Y61: =MATCH(Data!Y49,$A$1:$A$5,0) -> 4 | Z61: =SUM(F61:Y61) -> #N/A
B62: 61 | C62: 30 | D62: Female | E62: Black | F62: =MATCH(Data!F50,$A$1:$A$5,0) -> #N/A | G62: =MATCH(Data!G50,$A$1:$A$5,0) -> #N/A | H62: =MATCH(Data!H50,$A$1:$A$5,0) -> #N/A | I62: =MATCH(Data!I50,$A$1:$A$5,0) -> #N/A | J62: =MATCH(Data!J50,$A$1:$A$5,0) -> #N/A | K62: =MATCH(Data!K50,$A$1:$A$5,0) -> #N/A | L62: =MATCH(Data!L50,$A$1:$A$5,0) -> #N/A | M62: =MATCH(Data!M50,$A$1:$A$5,0) -> #N/A | ... Y62: =MATCH(Data!Y50,$A$1:$A$5,0) -> 3 | Z62: =SUM(F62:Y62) -> #N/A
B63: 62 | C63: 26 | D63: Male | E63: Hispanic | F63: =MATCH(Data!F51,$A$1:$A$5,0) -> #N/A | G63: =MATCH(Data!G51,$A$1:$A$5,0) -> #N/A | H63: =MATCH(Data!H51,$A$1:$A$5,0) -> #N/A | I63: =MATCH(Data!I51,$A$1:$A$5,0) -> #N/A | J63: =MATCH(Data!J51,$A$1:$A$5,0) -> #N/A | K63: =MATCH(Data!K51,$A$1:$A$5,0) -> #N/A | L63: =MATCH(Data!L51,$A$1:$A$5,0) -> #N/A | M63: =MATCH(Data!M51,$A$1:$A$5,0) -> #N/A | ... Y63: =MATCH(Data!Y51,$A$1:$A$5,0) -> 2 | Z63: =SUM(F63:Y63) -> #N/A
B64: 63 | C64: 44 | D64: Male | E64: Black | F64: =MATCH(Data!F52,$A$1:$A$5,0) -> #N/A | G64: =MATCH(Data!G52,$A$1:$A$5,0) -> #N/A | H64: =MATCH(Data!H52,$A$1:$A$5,0) -> #N/A | I64: =MATCH(Data!I52,$A$1:$A$5,0) -> #N/A | J64: =MATCH(Data!J52,$A$1:$A$5,0) -> #N/A | K64: =MATCH(Data!K52,$A$1:$A$5,0) -> #N/A | L64: =MATCH(Data!L52,$A$1:$A$5,0) -> #N/A | M64: =MATCH(Data!M52,$A$1:$A$5,0) -> #N/A | ... Y64: =MATCH(Data!Y52,$A$1:$A$5,0) -> 4 | Z64: =SUM(F64:Y64) -> #N/A
B65: 64 | C65: 29 | D65: Female | E65: White | F65: =MATCH(Data!F53,$A$1:$A$5,0) -> #N/A | G65: =MATCH(Data!G53,$A$1:$A$5,0) -> #N/A | H65: =MATCH(Data!H53,$A$1:$A$5,0) -> #N/A | I65: =MATCH(Data!I53,$A$1:$A$5,0) -> #N/A | J65: =MATCH(Data!J53,$A$1:$A$5,0) -> #N/A | K65: =MATCH(Data!K53,$A$1:$A$5,0) -> #N/A | L65: =MATCH(Data!L53,$A$1:$A$5,0) -> #N/A | M65: =MATCH(Data!M53,$A$1:$A$5,0) -> #N/A | ... Y65: =MATCH(Data!Y53,$A$1:$A$5,0) -> #N/A | Z65: =SUM(F65:Y65) -> #N/A
B66: 65 | C66: 39 | D66: Female | E66: White | F66: =MATCH(Data!F54,$A$1:$A$5,0) -> #N/A | G66: =MATCH(Data!G54,$A$1:$A$5,0) -> #N/A | H66: =MATCH(Data!H54,$A$1:$A$5,0) -> #N/A | I66: =MATCH(Data!I54,$A$1:$A$5,0) -> #N/A | J66: =MATCH(Data!J54,$A$1:$A$5,0) -> #N/A | K66: =MATCH(Data!K54,$A$1:$A$5,0) -> #N/A | L66: =MATCH(Data!L54,$A$1:$A$5,0) -> #N/A | M66: =MATCH(Data!M54,$A$1:$A$5,0) -> #N/A | ... Y66: =MATCH(Data!Y54,$A$1:$A$5,0) -> #N/A | Z66: =SUM(F66:Y66) -> #N/A
B67: 66 | C67: 34 | D67: Male | E67: White | F67: =MATCH(Data!F55,$A$1:$A$5,0) -> #N/A | G67: =MATCH(Data!G55,$A$1:$A$5,0) -> #N/A | H67: =MATCH(Data!H55,$A$1:$A$5,0) -> #N/A | I67: =MATCH(Data!I55,$A$1:$A$5,0) -> #N/A | J67: =MATCH(Data!J55,$A$1:$A$5,0) -> #N/A | K67: =MATCH(Data!K55,$A$1:$A$5,0) -> #N/A | L67: =MATCH(Data!L55,$A$1:$A$5,0) -> #N/A | M67: =MATCH(Data!M55,$A$1:$A$5,0) -> #N/A | ... Q67: =MATCH(Data!Q55,$A$1:$A$5,0) -> #N/A | R67: =MATCH(#REF!,$A$1:$A$5,0) -> #REF! | S67: =MATCH(Data!R55,$A$1:$A$5,0) -> 4 | T67: =MATCH(Data!S55,$A$1:$A$5,0) -> #N/A | U67: =MATCH(Data!T55,$A$1:$A$5,0) -> 4 | V67: =MATCH(Data!U55,$A$1:$A$5,0) -> 4 | W67: =MATCH(Data!V55,$A$1:$A$5,0) -> 4 | X67: =MATCH(Data!W55,$A$1:$A$5,0) -> 4 | Y67: =MATCH(Data!X55,$A$1:$A$5,0) -> #N/A | Z67: =SUM(F67:Y67) -> #N/A
B68: 67 | C68: 53 | D68: Female | E68: White | F68: =MATCH(Data!F56,$A$1:$A$5,0) -> #N/A | G68: =MATCH(Data!G56,$A$1:$A$5,0) -> #N/A | H68: =MATCH(Data!H56,$A$1:$A$5,0) -> #N/A | I68: =MATCH(Data!I56,$A$1:$A$5,0) -> #N/A | J68: =MATCH(Data!J56,$A$1:$A$5,0) -> #N/A | K68: =MATCH(Data!K56,$A$1:$A$5,0) -> #N/A | L68: =MATCH(Data!L56,$A$1:$A$5,0) -> #N/A | M68: =MATCH(Data!M56,$A$1:$A$5,0) -> #N/A | ... Y68: =MATCH(Data!Y56,$A$1:$A$5,0) -> #N/A | Z68: =SUM(F68:Y68) -> #N/A
B69: 68 | C69: 30 | D69: Female | E69: White | F69: =MATCH(Data!F68,$A$1:$A$5,0) -> #N/A | G69: =MATCH(Data!G68,$A$1:$A$5,0) -> #N/A | H69: =MATCH(Data!H68,$A$1:$A$5,0) -> #N/A | I69: =MATCH(Data!I68,$A$1:$A$5,0) -> #N/A | J69: =MATCH(Data!J68,$A$1:$A$5,0) -> #N/A | K69: =MATCH(Data!K68,$A$1:$A$5,0) -> #N/A | L69: =MATCH(Data!L68,$A$1:$A$5,0) -> #N/A | M69: =MATCH(Data!M68,$A$1:$A$5,0) -> #N/A | ... Y69: =MATCH(Data!Y68,$A$1:$A$5,0) -> 3 | Z69: =SUM(F69:Y69) -> #N/A
B70: 69 | C70: 28 | D70: Female | E70: White | F70: =MATCH(Data!F69,$A$1:$A$5,0) -> #N/A | G70: =MATCH(Data!G69,$A$1:$A$5,0) -> #N/A | H70: =MATCH(Data!H69,$A$1:$A$5,0) -> #N/A | I70: =MATCH(Data!I69,$A$1:$A$5,0) -> #N/A | J70: =MATCH(Data!J69,$A$1:$A$5,0) -> #N/A | K70: =MATCH(Data!K69,$A$1:$A$5,0) -> #N/A | L70: =MATCH(Data!L69,$A$1:$A$5,0) -> #N/A | M70: =MATCH(Data!M69,$A$1:$A$5,0) -> #N/A | ... Y70: =MATCH(Data!Y69,$A$1:$A$5,0) -> 4 | Z70: =SUM(F70:Y70) -> #N/A
B71: 70 | C71: 30 | D71: Female | E71: Hispanic | F71: =MATCH(Data!F70,$A$1:$A$5,0) -> #N/A | G71: =MATCH(Data!G70,$A$1:$A$5,0) -> #N/A | H71: =MATCH(Data!H70,$A$1:$A$5,0) -> #N/A | I71: =MATCH(Data!I70,$A$1:$A$5,0) -> #N/A | J71: =MATCH(Data!J70,$A$1:$A$5,0) -> #N/A | K71: =MATCH(Data!K70,$A$1:$A$5,0) -> #N/A | L71: =MATCH(Data!L70,$A$1:$A$5,0) -> #N/A | M71: =MATCH(Data!M70,$A$1:$A$5,0) -> #N/A | ... Y71: =MATCH(Data!Y70,$A$1:$A$5,0) -> #N/A | Z71: =SUM(F71:Y71) -> #N/A
B72: 71 | C72: 50 | D72: Female | E72: White | F72: =MATCH(Data!F71,$A$1:$A$5,0) -> #N/A | G72: =MATCH(Data!G71,$A$1:$A$5,0) -> #N/A | H72: =MATCH(Data!H71,$A$1:$A$5,0) -> #N/A | I72: =MATCH(Data!I71,$A$1:$A$5,0) -> #N/A | J72: =MATCH(Data!J71,$A$1:$A$5,0) -> #N/A | K72: =MATCH(Data!K71,$A$1:$A$5,0) -> #N/A | L72: =MATCH(Data!L71,$A$1:$A$5,0) -> #N/A | M72: =MATCH(Data!M71,$A$1:$A$5,0) -> #N/A | ... Y72: =MATCH(Data!Y71,$A$1:$A$5,0) -> #N/A | Z72: =SUM(F72:Y72) -> #N/A
B73: 72 | C73: 26 | D73: Female | E73: White | F73: =MATCH(Data!F72,$A$1:$A$5,0) -> #N/A | G73: =MATCH(Data!G72,$A$1:$A$5,0) -> #N/A | H73: =MATCH(Data!H72,$A$1:$A$5,0) -> #N/A | I73: =MATCH(Data!I72,$A$1:$A$5,0) -> #N/A | J73: =MATCH(Data!J72,$A$1:$A$5,0) -> #N/A | K73: =MATCH(Data!K72,$A$1:$A$5,0) -> #N/A | L73: =MATCH(Data!L72,$A$1:$A$5,0) -> #N/A | M73: =MATCH(Data!M72,$A$1:$A$5,0) -> #N/A | ... Y73: =MATCH(Data!Y72,$A$1:$A$5,0) -> 2 | Z73: =SUM(F73:Y73) -> #N/A
B74: 73 | C74: 53 | D74: Male | E74: Black | F74: =MATCH(Data!F73,$A$1:$A$5,0) -> #N/A | G74: =MATCH(Data!G73,$A$1:$A$5,0) -> #N/A | H74: =MATCH(Data!H73,$A$1:$A$5,0) -> #N/A | I74: =MATCH(Data!I73,$A$1:$A$5,0) -> #N/A | J74: =MATCH(Data!J73,$A$1:$A$5,0) -> #N/A | K74: =MATCH(Data!K73,$A$1:$A$5,0) -> #N/A | L74: =MATCH(Data!L73,$A$1:$A$5,0) -> #N/A | M74: =MATCH(Data!M73,$A$1:$A$5,0) -> #N/A | ... Y74: =MATCH(Data!Y73,$A$1:$A$5,0) -> #N/A | Z74: =SUM(F74:Y74) -> #N/A
B75: 74 | C75: 33 | D75: Female | E75: White | F75: =MATCH(Data!F74,$A$1:$A$5,0) -> #N/A | G75: =MATCH(Data!G74,$A$1:$A$5,0) -> #N/A | H75: =MATCH(Data!H74,$A$1:$A$5,0) -> #N/A | I75: =MATCH(Data!I74,$A$1:$A$5,0) -> #N/A | J75: =MATCH(Data!J74,$A$1:$A$5,0) -> #N/A | K75: =MATCH(Data!K74,$A$1:$A$5,0) -> #N/A | L75: =MATCH(Data!L74,$A$1:$A$5,0) -> #N/A | M75: =MATCH(Data!M74,$A$1:$A$5,0) -> #N/A | ... Y75: =MATCH(Data!Y74,$A$1:$A$5,0) -> #N/A | Z75: =SUM(F75:Y75) -> #N/A
B76: 75 | C76: 27 | D76: Female | E76: White | F76: =MATCH(Data!F75,$A$1:$A$5,0) -> #N/A | G76: =MATCH(Data!G75,$A$1:$A$5,0) -> #N/A | H76: =MATCH(Data!H75,$A$1:$A$5,0) -> #N/A | I76: =MATCH(Data!I75,$A$1:$A$5,0) -> #N/A | J76: =MATCH(Data!J75,$A$1:$A$5,0) -> #N/A | K76: =MATCH(Data!K75,$A$1:$A$5,0) -> #N/A | L76: =MATCH(Data!L75,$A$1:$A$5,0) -> #N/A | M76: =MATCH(Data!M75,$A$1:$A$5,0) -> #N/A | ... Y76: =MATCH(Data!Y75,$A$1:$A$5,0) -> #N/A | Z76: =SUM(F76:Y76) -> #N/A
B77: 76 | C77: 31 | D77: Female | E77: White | F77: =MATCH(Data!F76,$A$1:$A$5,0) -> #N/A | G77: =MATCH(Data!G76,$A$1:$A$5,0) -> #N/A | H77: =MATCH(Data!H76,$A$1:$A$5,0) -> #N/A | I77: =MATCH(Data!I76,$A$1:$A$5,0) -> #N/A | J77: =MATCH(Data!J76,$A$1:$A$5,0) -> #N/A | K77: =MATCH(Data!K76,$A$1:$A$5,0) -> #N/A | L77: =MATCH(Data!L76,$A$1:$A$5,0) -> #N/A | M77: =MATCH(Data!M76,$A$1:$A$5,0) -> #N/A | ... Y77: =MATCH(Data!Y76,$A$1:$A$5,0) -> #N/A | Z77: =SUM(F77:Y77) -> #N/A
B78: 77 | C78: 24 | D78: Male | E78: Black | F78: =MATCH(Data!F77,$A$1:$A$5,0) -> #N/A | G78: =MATCH(Data!G77,$A$1:$A$5,0) -> #N/A | H78: =MATCH(Data!H77,$A$1:$A$5,0) -> #N/A | I78: =MATCH(Data!I77,$A$1:$A$5,0) -> #N/A | J78: =MATCH(Data!J77,$A$1:$A$5,0) -> #N/A | K78: =MATCH(Data!K77,$A$1:$A$5,0) -> #N/A | L78: =MATCH(Data!L77,$A$1:$A$5,0) -> #N/A | M78: =MATCH(Data!M77,$A$1:$A$5,0) -> #N/A | ... Y78: =MATCH(Data!Y77,$A$1:$A$5,0) -> 3 | Z78: =SUM(F78:Y78) -> #N/A
B79: 78 | C79: 41 | D79: Male | E79: Black | F79: =MATCH(Data!F78,$A$1:$A$5,0) -> #N/A | G79: =MATCH(Data!G78,$A$1:$A$5,0) -> #N/A | H79: =MATCH(Data!H78,$A$1:$A$5,0) -> #N/A | I79: =MATCH(Data!I78,$A$1:$A$5,0) -> #N/A | J79: =MATCH(Data!J78,$A$1:$A$5,0) -> #N/A | K79: =MATCH(Data!K78,$A$1:$A$5,0) -> #N/A | L79: =MATCH(Data!L78,$A$1:$A$5,0) -> #N/A | M79: =MATCH(Data!M78,$A$1:$A$5,0) -> #N/A | ... Y79: =MATCH(Data!Y78,$A$1:$A$5,0) -> 4 | Z79: =SUM(F79:Y79) -> #N/A
B80: 79 | C80: 26 | D80: Female | E80: White | F80: =MATCH(Data!F79,$A$1:$A$5,0) -> #N/A | G80: =MATCH(Data!G79,$A$1:$A$5,0) -> #N/A | H80: =MATCH(Data!H79,$A$1:$A$5,0) -> #N/A | I80: =MATCH(Data!I79,$A$1:$A$5,0) -> #N/A | J80: =MATCH(Data!J79,$A$1:$A$5,0) -> #N/A | K80: =MATCH(Data!K79,$A$1:$A$5,0) -> #N/A | L80: =MATCH(Data!L79,$A$1:$A$5,0) -> #N/A | M80: =MATCH(Data!M79,$A$1:$A$5,0) -> #N/A | ... Y80: =MATCH(Data!Y79,$A$1:$A$5,0) -> #N/A | Z80: =SUM(F80:Y80) -> #N/A
... B97: 96 | C97: 26 | D97: Female | E97: White | F97: =MATCH(Data!F96,$A$1:$A$5,0) -> #N/A | G97: =MATCH(Data!G96,$A$1:$A$5,0) -> #N/A | H97: =MATCH(Data!H96,$A$1:$A$5,0) -> #N/A | I97: =MATCH(Data!I96,$A$1:$A$5,0) -> #N/A | J97: =MATCH(Data!J96,$A$1:$A$5,0) -> #N/A | K97: =MATCH(Data!K96,$A$1:$A$5,0) -> #N/A | L97: =MATCH(Data!L96,$A$1:$A$5,0) -> #N/A | M97: =MATCH(Data!M96,$A$1:$A$5,0) -> #N/A | ... Y97: =MATCH(Data!Y96,$A$1:$A$5,0) -> 4 | Z97: =SUM(F97:Y97) -> #N/A
B98: 97 | C98: 43 | D98: Female | E98: Hispanic | F98: =MATCH(Data!F97,$A$1:$A$5,0) -> #N/A | G98: =MATCH(Data!G97,$A$1:$A$5,0) -> #N/A | H98: =MATCH(Data!H97,$A$1:$A$5,0) -> #N/A | I98: =MATCH(Data!I97,$A$1:$A$5,0) -> #N/A | J98: =MATCH(Data!J97,$A$1:$A$5,0) -> #N/A | K98: =MATCH(Data!K97,$A$1:$A$5,0) -> #N/A | L98: =MATCH(Data!L97,$A$1:$A$5,0) -> #N/A | M98: =MATCH(Data!M97,$A$1:$A$5,0) -> #N/A | ... R98: =MATCH(Data!R97,$A$1:$A$5,0) -> 4 | S98: =MATCH(Data!Y97,$A$1:$A$5,0) -> #N/A | T98: =MATCH(Data!T97,$A$1:$A$5,0) -> #N/A | U98: =MATCH(Data!U97,$A$1:$A$5,0) -> #N/A | V98: =MATCH(Data!V97,$A$1:$A$5,0) -> 4 | W98: =MATCH(Data!W97,$A$1:$A$5,0) -> #N/A | X98: =MATCH(Data!X97,$A$1:$A$5,0) -> 4 | Y98: =MATCH(#REF!,$A$1:$A$5,0) -> #REF! | Z98: =SUM(F98:Y98) -> #N/A
B99: 98 | C99: 50 | D99: Female | E99: Black | F99: =MATCH(Data!F98,$A$1:$A$5,0) -> #N/A | G99: =MATCH(Data!G98,$A$1:$A$5,0) -> #N/A | H99: =MATCH(Data!H98,$A$1:$A$5,0) -> #N/A | I99: =MATCH(Data!I98,$A$1:$A$5,0) -> #N/A | J99: =MATCH(Data!J98,$A$1:$A$5,0) -> #N/A | K99: =MATCH(Data!K98,$A$1:$A$5,0) -> #N/A | L99: =MATCH(Data!L98,$A$1:$A$5,0) -> #N/A | M99: =MATCH(Data!M98,$A$1:$A$5,0) -> #N/A | ... Y99: =MATCH(Data!Y98,$A$1:$A$5,0) -> #N/A | Z99: =SUM(F99:Y99) -> #N/A
B100: 99 | C100: 42 | D100: Female | E100: White | F100: =MATCH(Data!F99,$A$1:$A$5,0) -> #N/A | G100: =MATCH(Data!G99,$A$1:$A$5,0) -> #N/A | H100: =MATCH(Data!H99,$A$1:$A$5,0) -> #N/A | I100: =MATCH(Data!I99,$A$1:$A$5,0) -> #N/A | J100: =MATCH(Data!J99,$A$1:$A$5,0) -> #N/A | K100: =MATCH(Data!K99,$A$1:$A$5,0) -> #N/A | L100: =MATCH(Data!L99,$A$1:$A$5,0) -> #N/A | M100: =MATCH(Data!M99,$A$1:$A$5,0) -> #N/A | ... Y100: =MATCH(Data!Y99,$A$1:$A$5,0) -> 4 | Z100: =SUM(F100:Y100) -> #N/A
B101: 100 | C101: 29 | D101: Female | E101: Black | F101: =MATCH(Data!F100,$A$1:$A$5,0) -> #N/A | G101: =MATCH(Data!G100,$A$1:$A$5,0) -> #N/A | H101: =MATCH(Data!H100,$A$1:$A$5,0) -> #N/A | I101: =MATCH(Data!I100,$A$1:$A$5,0) -> #N/A | J101: =MATCH(Data!J100,$A$1:$A$5,0) -> #N/A | K101: =MATCH(Data!K100,$A$1:$A$5,0) -> #N/A | L101: =MATCH(Data!L100,$A$1:$A$5,0) -> #N/A | M101: =MATCH(Data!M100,$A$1:$A$5,0) -> #N/A | ... Y101: =MATCH(Data!Y100,$A$1:$A$5,0) -> 4 | Z101: =SUM(F101:Y101) -> #N/A
B102: 101 | C102: 48 | D102: Male | E102: Black | F102: =MATCH(Data!F101,$A$1:$A$5,0) -> #N/A | G102: =MATCH(Data!G101,$A$1:$A$5,0) -> #N/A | H102: =MATCH(Data!H101,$A$1:$A$5,0) -> #N/A | I102: =MATCH(Data!I101,$A$1:$A$5,0) -> #N/A | J102: =MATCH(Data!J101,$A$1:$A$5,0) -> #N/A | K102: =MATCH(Data!K101,$A$1:$A$5,0) -> #N/A | L102: =MATCH(Data!L101,$A$1:$A$5,0) -> #N/A | M102: =MATCH(Data!M101,$A$1:$A$5,0) -> #N/A | ... Y102: =MATCH(Data!Y101,$A$1:$A$5,0) -> #N/A | Z102: =SUM(F102:Y102) -> #N/A
B103: 102 | C103: 39 | D103: Female | E103: Black | F103: =MATCH(Data!F102,$A$1:$A$5,0) -> #N/A | G103: =MATCH(Data!G102,$A$1:$A$5,0) -> #N/A | H103: =MATCH(Data!H102,$A$1:$A$5,0) -> #N/A | I103: =MATCH(Data!I102,$A$1:$A$5,0) -> #N/A | J103: =MATCH(Data!J102,$A$1:$A$5,0) -> #N/A | K103: =MATCH(Data!K102,$A$1:$A$5,0) -> #N/A | L103: =MATCH(Data!L102,$A$1:$A$5,0) -> #N/A | M103: =MATCH(Data!M102,$A$1:$A$5,0) -> #N/A | ... Y103: =MATCH(Data!Y102,$A$1:$A$5,0) -> #N/A | Z103: =SUM(F103:Y103) -> #N/A
B104: 103 | C104: 30 | D104: Male | E104: Black | F104: =MATCH(Data!F103,$A$1:$A$5,0) -> #N/A | G104: =MATCH(Data!G103,$A$1:$A$5,0) -> #N/A | H104: =MATCH(Data!H103,$A$1:$A$5,0) -> #N/A | I104: =MATCH(Data!I103,$A$1:$A$5,0) -> #N/A | J104: =MATCH(Data!J103,$A$1:$A$5,0) -> #N/A | K104: =MATCH(Data!K103,$A$1:$A$5,0) -> #N/A | L104: =MATCH(Data!L103,$A$1:$A$5,0) -> #N/A | M104: =MATCH(Data!M103,$A$1:$A$5,0) -> #N/A | ... Y104: =MATCH(Data!Y103,$A$1:$A$5,0) -> 3 | Z104: =SUM(F104:Y104) -> #N/A
B105: 104 | C105: 30 | D105: Female | E105: White | F105: =MATCH(#REF!,$A$1:$A$5,0) -> #REF! | G105: =MATCH(#REF!,$A$1:$A$5,0) -> #REF! | H105: =MATCH(#REF!,$A$1:$A$5,0) -> #REF! | I105: =MATCH(#REF!,$A$1:$A$5,0) -> #REF! | J105: =MATCH(#REF!,$A$1:$A$5,0) -> #REF! | K105: =MATCH(#REF!,$A$1:$A$5,0) -> #REF! | L105: =MATCH(#REF!,$A$1:$A$5,0) -> #REF! | M105: =MATCH(#REF!,$A$1:$A$5,0) -> #REF! | ... Y105: =MATCH(#REF!,$A$1:$A$5,0) -> #REF! | Z105: =SUM(F105:Y105) -> #REF!
B106: 105 | C106: 50 | D106: Male | E106: White | F106: =MATCH(Data!F104,$A$1:$A$5,0) -> #N/A | G106: =MATCH(Data!G104,$A$1:$A$5,0) -> #N/A | H106: =MATCH(Data!H104,$A$1:$A$5,0) -> #N/A | I106: =MATCH(Data!I104,$A$1:$A$5,0) -> #N/A | J106: =MATCH(Data!J104,$A$1:$A$5,0) -> #N/A | K106: =MATCH(Data!K104,$A$1:$A$5,0) -> #N/A | L106: =MATCH(Data!L104,$A$1:$A$5,0) -> #N/A | M106: =MATCH(Data!M104,$A$1:$A$5,0) -> #N/A | ... Y106: =MATCH(Data!Y104,$A$1:$A$5,0) -> 2 | Z106: =SUM(F106:Y106) -> #N/A
B107: 106 | C107: 25 | D107: Female | E107: White | F107: =MATCH(Data!F105,$A$1:$A$5,0) -> #N/A | G107: =MATCH(Data!G105,$A$1:$A$5,0) -> #N/A | H107: =MATCH(Data!H105,$A$1:$A$5,0) -> #N/A | I107: =MATCH(Data!I105,$A$1:$A$5,0) -> #N/A | J107: =MATCH(Data!J105,$A$1:$A$5,0) -> #N/A | K107: =MATCH(Data!K105,$A$1:$A$5,0) -> #N/A | L107: =MATCH(Data!L105,$A$1:$A$5,0) -> #N/A | M107: =MATCH(Data!M105,$A$1:$A$5,0) -> #N/A | ... Y107: =MATCH(Data!Y105,$A$1:$A$5,0) -> #N/A | Z107: =SUM(F107:Y107) -> #N/A
B108: 107 | C108: 50 | D108: Female | E108: Black | F108: =MATCH(Data!F106,$A$1:$A$5,0) -> #N/A | G108: =MATCH(Data!G106,$A$1:$A$5,0) -> #N/A | H108: =MATCH(Data!H106,$A$1:$A$5,0) -> #N/A | I108: =MATCH(Data!I106,$A$1:$A$5,0) -> #N/A | J108: =MATCH(Data!J106,$A$1:$A$5,0) -> #N/A | K108: =MATCH(Data!K106,$A$1:$A$5,0) -> #N/A | L108: =MATCH(Data!L106,$A$1:$A$5,0) -> #N/A | M108: =MATCH(Data!M106,$A$1:$A$5,0) -> #N/A | ... Y108: =MATCH(Data!Y106,$A$1:$A$5,0) -> 4 | Z108: =SUM(F108:Y108) -> #N/A
B109: 108 | C109: 28 | D109: Female | E109: Black | F109: =MATCH(Data!F107,$A$1:$A$5,0) -> #N/A | G109: =MATCH(Data!G107,$A$1:$A$5,0) -> #N/A | H109: =MATCH(Data!H107,$A$1:$A$5,0) -> #N/A | I109: =MATCH(Data!I107,$A$1:$A$5,0) -> #N/A | J109: =MATCH(Data!J107,$A$1:$A$5,0) -> #N/A | K109: =MATCH(Data!K107,$A$1:$A$5,0) -> #N/A | L109: =MATCH(Data!L107,$A$1:$A$5,0) -> #N/A | M109: =MATCH(Data!M107,$A$1:$A$5,0) -> #N/A | ... Y109: =MATCH(Data!Y107,$A$1:$A$5,0) -> #N/A | Z109: =SUM(F109:Y109) -> #N/A
B110: 109 | C110: 44 | D110: Female | E110: Black | F110: =MATCH(Data!F108,$A$1:$A$5,0) -> #N/A | G110: =MATCH(Data!G108,$A$1:$A$5,0) -> #N/A | H110: =MATCH(Data!H108,$A$1:$A$5,0) -> #N/A | I110: =MATCH(Data!I108,$A$1:$A$5,0) -> #N/A | J110: =MATCH(Data!J108,$A$1:$A$5,0) -> #N/A | K110: =MATCH(Data!K108,$A$1:$A$5,0) -> #N/A | L110: =MATCH(Data!L108,$A$1:$A$5,0) -> #N/A | M110: =MATCH(Data!M108,$A$1:$A$5,0) -> #N/A | ... Y110: =MATCH(Data!Y108,$A$1:$A$5,0) -> #N/A | Z110: =SUM(F110:Y110) -> #N/A
B111: 110 | C111: 44 | D111: Female | E111: Hispanic | F111: =MATCH(Data!F109,$A$1:$A$5,0) -> #N/A | G111: =MATCH(Data!G109,$A$1:$A$5,0) -> #N/A | H111: =MATCH(Data!H109,$A$1:$A$5,0) -> #N/A | I111: =MATCH(Data!I109,$A$1:$A$5,0) -> #N/A | J111: =MATCH(Data!J109,$A$1:$A$5,0) -> #N/A | K111: =MATCH(Data!K109,$A$1:$A$5,0) -> #N/A | L111: =MATCH(Data!L109,$A$1:$A$5,0) -> #N/A | M111: =MATCH(Data!M109,$A$1:$A$5,0) -> #N/A | ... Y111: =MATCH(Data!Y109,$A$1:$A$5,0) -> #N/A | Z111: =SUM(F111:Y111) -> #N/A
B112: 111 | C112: 37 | D112: Male | E112: Black | F112: =MATCH(Data!F110,$A$1:$A$5,0) -> #N/A | G112: =MATCH(Data!G110,$A$1:$A$5,0) -> #N/A | H112: =MATCH(Data!H110,$A$1:$A$5,0) -> #N/A | I112: =MATCH(Data!I110,$A$1:$A$5,0) -> #N/A | J112: =MATCH(Data!J110,$A$1:$A$5,0) -> #N/A | K112: =MATCH(Data!K110,$A$1:$A$5,0) -> #N/A | L112: =MATCH(Data!L110,$A$1:$A$5,0) -> #N/A | M112: =MATCH(Data!M110,$A$1:$A$5,0) -> #N/A | ... Y112: =MATCH(Data!Y110,$A$1:$A$5,0) -> #N/A | Z112: =SUM(F112:Y112) -> #N/A
B113: 112 | C113: 28 | D113: Male | E113: White | F113: =MATCH(Data!F111,$A$1:$A$5,0) -> #N/A | G113: =MATCH(Data!G111,$A$1:$A$5,0) -> #N/A | H113: =MATCH(Data!H111,$A$1:$A$5,0) -> #N/A | I113: =MATCH(Data!I111,$A$1:$A$5,0) -> #N/A | J113: =MATCH(Data!J111,$A$1:$A$5,0) -> #N/A | K113: =MATCH(Data!K111,$A$1:$A$5,0) -> #N/A | L113: =MATCH(Data!L111,$A$1:$A$5,0) -> #N/A | M113: =MATCH(Data!M111,$A$1:$A$5,0) -> #N/A | ... Y113: =MATCH(Data!Y111,$A$1:$A$5,0) -> 3 | Z113: =SUM(F113:Y113) -> #N/A
B114: 113 | C114: 27 | D114: Female | E114: Black | F114: =MATCH(Data!F112,$A$1:$A$5,0) -> #N/A | G114: =MATCH(Data!G112,$A$1:$A$5,0) -> #N/A | H114: =MATCH(Data!H112,$A$1:$A$5,0) -> #N/A | I114: =MATCH(Data!I112,$A$1:$A$5,0) -> #N/A | J114: =MATCH(Data!J112,$A$1:$A$5,0) -> #N/A | K114: =MATCH(Data!K112,$A$1:$A$5,0) -> #N/A | L114: =MATCH(Data!L112,$A$1:$A$5,0) -> #N/A | M114: =MATCH(Data!M112,$A$1:$A$5,0) -> #N/A | ... Y114: =MATCH(Data!Y112,$A$1:$A$5,0) -> 4 | Z114: =SUM(F114:Y114) -> #N/A
B115: 114 | C115: 57 | D115: Female | E115: Hispanic | F115: =MATCH(Data!F113,$A$1:$A$5,0) -> #N/A | G115: =MATCH(Data!G113,$A$1:$A$5,0) -> #N/A | H115: =MATCH(Data!H113,$A$1:$A$5,0) -> #N/A | I115: =MATCH(Data!I113,$A$1:$A$5,0) -> #N/A | J115: =MATCH(Data!J113,$A$1:$A$5,0) -> #N/A | K115: =MATCH(Data!K113,$A$1:$A$5,0) -> #N/A | L115: =MATCH(Data!L113,$A$1:$A$5,0) -> #N/A | M115: =MATCH(Data!M113,$A$1:$A$5,0) -> #N/A | ... W115: =MATCH(Data!W113,$A$1:$A$5,0) -> #N/A | X115: =MATCH(#REF!,$A$1:$A$5,0) -> #REF! | Y115: =MATCH(#REF!,$A$1:$A$5,0) -> #REF! | Z115: =SUM(F115:Y115) -> #N/A
B116: 115 | C116: 29 | D116: Female | E116: White | F116: =MATCH(Data!F114,$A$1:$A$5,0) -> #N/A | G116: =MATCH(Data!G114,$A$1:$A$5,0) -> #N/A | H116: =MATCH(Data!H114,$A$1:$A$5,0) -> #N/A | I116: =MATCH(Data!I114,$A$1:$A$5,0) -> #N/A | J116: =MATCH(Data!J114,$A$1:$A$5,0) -> #N/A | K116: =MATCH(Data!K114,$A$1:$A$5,0) -> #N/A | L116: =MATCH(Data!L114,$A$1:$A$5,0) -> #N/A | M116: =MATCH(Data!M114,$A$1:$A$5,0) -> #N/A | ... Y116: =MATCH(Data!Y114,$A$1:$A$5,0) -> 3 | Z116: =SUM(F116:Y116) -> #N/A
B117: 116 | C117: 47 | D117: Female | E117: White | F117: =MATCH(Data!F115,$A$1:$A$5,0) -> #N/A | G117: =MATCH(Data!G115,$A$1:$A$5,0) -> #N/A | H117: =MATCH(Data!H115,$A$1:$A$5,0) -> #N/A | I117: =MATCH(Data!I115,$A$1:$A$5,0) -> #N/A | J117: =MATCH(Data!J115,$A$1:$A$5,0) -> #N/A | K117: =MATCH(Data!K115,$A$1:$A$5,0) -> #N/A | L117: =MATCH(Data!L115,$A$1:$A$5,0) -> #N/A | M117: =MATCH(Data!M115,$A$1:$A$5,0) -> #N/A | ... Y117: =MATCH(Data!Y115,$A$1:$A$5,0) -> #N/A | Z117: =SUM(F117:Y117) -> #N/A
...

Sheet Data2
A1: id | B1: age | C1: sex | D1: race | E1: BME | F1: Educ | G1: qu1 | H1: qu2 | I1: qu3 | J1: qu4 | K1: qu5 | L1: qu6 | M1: qu7 | N1: qu8 | O1: qu9 | P1: qu10 | Q1: qu11 | R1: qu12 | S1: qu13 | T1: qu14 | U1: qu15 | V1: qu16 | W1: qu17 | X1: qu18 | Y1: qu19 | Z1: qu20 | AA1: TotalScore
A2: 1 | B2: 49 | C2: Male | D2: White | E2: 0 | F2: =RANDBETWEEN(0,1) -> 1 | G2: 3 | H2: 3 | I2: 3 | J2: 3 | K2: 3 | L2: 3 | M2: 3 | N2: 3 | O2: 3 | P2: 2 | Q2: 3 | R2: 3 | S2: 3 | T2: 2 | U2: 2 | V2: 3 | W2: 3 | X2: 2 | Y2: 3 | Z2: 1 | AA2: 54
A3: 2 | B3: 52 | C3: Female | D3: White | E3: 0 | F3: =RANDBETWEEN(0,1) -> 1 | G3: 3 | H3: 2 | I3: 3 | J3: 3 | K3: 2 | L3: 2 | M3: 2 | N3: 3 | O3: 3 | P3: 3 | Q3: 3 | R3: 3 | S3: 3 | T3: 3 | U3: 3 | V3: 3 | W3: 3 | X3: 3 | Y3: 3 | Z3: 2 | AA3: 55
A4: 3 | B4: 31 | C4: Male | D4: Hispanic | E4: 1 | F4: =RANDBETWEEN(0,1) -> 0 | G4: 3 | H4: 2 | I4: 2 | J4: 3 | K4: 2 | L4: 2 | M4: 3 | N4: 2 | O4: 3 | P4: 2 | Q4: 4 | R4: 4 | S4: 3 | T4: 4 | U4: 3 | V4: 3 | W4: 3 | X4: 4 | Y4: 4 | Z4: 2 | AA4: 58
A5: 4 | B5: 28 | C5: Male | D5: Black | E5: 1 | F5: =RANDBETWEEN(0,1) -> 0 | G5: 4 | H5: 3 | I5: 3 | J5: 3 | K5: 3 | L5: 2 | M5: 3 | N5: 3 | O5: 3 | P5: 3 | Q5: 3 | R5: 3 | S5: 4 | T5: 3 | U5: 3 | V5: 3 | W5: 4 | X5: 3 | Y5: 3 | Z5: 3 | AA5: 62
A6: 5 | B6: 29 | C6: Male | D6: White | E6: 0 | F6: =RANDBETWEEN(0,1) -> 0 | G6: 4 | H6: 2 | I6: 4 | J6: 4 | K6: 3 | L6: 4 | M6: 4 | N6: 4 | O6: 4 | P6: 4 | Q6: 3 | R6: 3 | S6: 3 | T6: 1 | U6: 2 | V6: 3 | W6: 3 | X6: 3 | Y6: 3 | Z6: 1 | AA6: 62
A7: 6 | B7: 50 | C7: Female | D7: Black | E7: 1 | F7: =RANDBETWEEN(0,1) -> 0 | G7: 3 | H7: 2 | I7: 3 | J7: 2 | K7: 2 | L7: 2 | M7: 3 | N7: 3 | O7: 2 | P7: 3 | Q7: 3 | R7: 3 | S7: 3 | T7: 2 | U7: 3 | V7: 3 | W7: 3 | X7: 3 | Y7: 3 | Z7: 3 | AA7: 54
A8: 7 | B8: 31 | C8: Female | D8: White | E8: 0 | F8: =RANDBETWEEN(0,1) -> 1 | G8: 2 | H8: 1 | I8: 2 | J8: 2 | K8: 2 | L8: 2 | M8: 2 | N8: 1 | O8: 2 | P8: 2 | Q8: 3 | R8: 4 | S8: 3 | T8: 2 | U8: 3 | V8: 4 | W8: 3 | X8: 3 | Y8: 3 | Z8: 3 | AA8: 49
A9: 8 | B9: 24 | C9: Female | D9: Black | E9: 1 | F9: =RANDBETWEEN(0,1) -> 1 | G9: 3 | H9: 3 | I9: 3 | J9: 3 | K9: 3 | L9: 4 | M9: 3 | N9: 3 | O9: 3 | P9: 4 | Q9: 4 | R9: 3 | S9: 3 | T9: 3 | U9: 3 | V9: 3 | W9: 4 | X9: 3 | Y9: 4 | Z9: 2 | AA9: 64
A10: 9 | B10: 32 | C10: Female | D10: Black | E10: 1 | F10: =RANDBETWEEN(0,1) -> 0 | G10: 4 | H10: 4 | I10: 4 | J10: 4 | K10: 3 | L10: 4 | M10: 3 | N10: 3 | O10: 3 | P10: 4 | Q10: 3 | R10: 3 | S10: 4 | T10: 2 | U10: 3 | V10: 3 | W10: 3 | X10: 3 | Y10: 4 | Z10: 2 | AA10: 66
A11: 10 | B11: 33 | C11: Female | D11: White | E11: 0 | F11: =RANDBETWEEN(0,1) -> 0 | G11: 3 | H11: 4 | I11: 4 | J11: 4 | K11: 4 | L11: 4 | M11: 4 | N11: 4 | O11: 4 | P11: 4 | Q11: 2 | R11: 2 | S11: 3 | T11: 1 | U11: 2 | V11: 2 | W11: 2 | X11: 2 | Y11: 3 | Z11: 1 | AA11: 59
A12: 11 | B12: 46 | C12: Female | D12: White | E12: 0 | F12: =RANDBETWEEN(0,1) -> 1 | G12: 3 | H12: 3 | I12: 4 | J12: 3 | K12: 3 | L12: 3 | M12: 4 | N12: 3 | O12: 3 | P12: 4 | Q12: 2 | R12: 3 | S12: 3 | T12: 2 | U12: 3 | V12: 3 | W12: 3 | X12: 3 | Y12: 3 | Z12: 1 | AA12: 59
A13: 12 | B13: 39 | C13: Female | D13: White | E13: 0 | F13: =RANDBETWEEN(0,1) -> 1 | G13: 5 | H13: 4 | I13: 5 | J13: 4 | K13: 5 | L13: 4 | M13: 4 | N13: 5 | O13: 5 | P13: 5 | Q13: 4 | R13: 5 | S13: 4 | T13: 3 | U13: 4 | V13: 4 | W13: 4 | X13: 4 | Y13: 3 | Z13: 3 | AA13: 84
... A1001: 1000 | B1001: 30 | C1001: Female | D1001: Black | E1001: 1 | F1001: =RANDBETWEEN(0,1) -> 1 | G1001: 4 | H1001: 3 | I1001: 4 | J1001: 4 | K1001: 4 | L1001: 4 | M1001: 4 | N1001: 5 | O1001: 4 | P1001: 4 | Q1001: 4 | R1001: 5 | S1001: 5 | T1001: 4 | U1001: 5 | V1001: 5 | W1001: 5 | X1001: 5 | Y1001: 5 | Z1001: 4 | AA1001: 87

Sheet ArtificalData
A1: id | B1: age | C1: sex | D1: race | E1: BME | F1: Educ | G1: qu1 | H1: qu2 | I1: qu3 | J1: qu4 | K1: qu5 | L1: qu6 | M1: qu7 | N1: qu8 | O1: qu9 | P1: qu10 | Q1: qu11 | R1: qu12 | S1: qu13 | T1: qu14 | U1: qu15 | V1: qu16 | W1: qu17 | X1: qu18 | Y1: qu19 | Z1: qu20 | AA1: TotalScore
A2: 1 | B2: 49 | C2: Male | D2: White | E2: 0 | F2: =RANDBETWEEN(0,1) -> 0 | G2: =ARRAY_CONSTRAIN(ARRAYFORMULA(INDEX([1]Data2!G2:G1001,RANDBETWEEN(1,ROWS([1]Data2!G2:G1001)))), 1, 1) -> #ERROR! | H2: =ARRAY_CONSTRAIN(ARRAYFORMULA(INDEX([1]Data2!H2:H1001,RANDBETWEEN(1,ROWS([1]Data2!H2:H1001)))), 1, 1) -> #ERROR! | I2: =ARRAY_CONSTRAIN(ARRAYFORMULA(INDEX([1]Data2!I2:I1001,RANDBETWEEN(1,ROWS([1]Data2!I2:I1001)))), 1, 1) -> #ERROR! | J2: =ARRAY_CONSTRAIN(ARRAYFORMULA(INDEX([1]Data2!J2:J1001,RANDBETWEEN(1,ROWS([1]Data2!J2:J1001)))), 1, 1) -> #ERROR! | K2: =ARRAY_CONSTRAIN(ARRAYFORMULA(INDEX([1]Data2!K2:K1001,RANDBETWEEN(1,ROWS([1]Data2!K2:K1001)))), 1, 1) -> #ERROR! | L2: =ARRAY_CONSTRAIN(ARRAYFORMULA(INDEX([1]Data2!L2:L1001,RANDBETWEEN(1,ROWS([1]Data2!L2:L1001)))), 1, 1) -> #ERROR! | M2: =ARRAY_CONSTRAIN(ARRAYFORMULA(INDEX([1]Data2!M2:M1001,RANDBETWEEN(1,ROWS([1]Data2!M2:M1001)))), 1, 1) -> #ERROR! | N2: =ARRAY_CONSTRAIN(ARRAYFORMULA(INDEX([1]Data2!N2:N1001,RANDBETWEEN(1,ROWS([1]Data2!N2:N1001)))), 1, 1) -> #ERROR! | ... Z2: =ARRAY_CONSTRAIN(ARRAYFORMULA(INDEX([1]Data2!Z2:Z1001,RANDBETWEEN(1,ROWS([1]Data2!Z2:Z1001)))), 1, 1) -> #ERROR! | AA2: =SUM(G2:Z2) -> #ERROR!
A3: 2 | B3: 52 | C3: Female | D3: White | E3: 0 | F3: =RANDBETWEEN(0,1) -> 1 | G3: =ARRAY_CONSTRAIN(ARRAYFORMULA(INDEX([1]Data2!G3:G1002,RANDBETWEEN(1,ROWS([1]Data2!G3:G1002)))), 1, 1) -> #ERROR! | H3: =ARRAY_CONSTRAIN(ARRAYFORMULA(INDEX([1]Data2!H3:H1002,RANDBETWEEN(1,ROWS([1]Data2!H3:H1002)))), 1, 1) -> #ERROR! | I3: =ARRAY_CONSTRAIN(ARRAYFORMULA(INDEX([1]Data2!I3:I1002,RANDBETWEEN(1,ROWS([1]Data2!I3:I1002)))), 1, 1) -> #ERROR! | J3: =ARRAY_CONSTRAIN(ARRAYFORMULA(INDEX([1]Data2!J3:J1002,RANDBETWEEN(1,ROWS([1]Data2!J3:J1002)))), 1, 1) -> #ERROR! | K3: =ARRAY_CONSTRAIN(ARRAYFORMULA(INDEX([1]Data2!K3:K1002,RANDBETWEEN(1,ROWS([1]Data2!K3:K1002)))), 1, 1) -> #ERROR! | L3: =ARRAY_CONSTRAIN(ARRAYFORMULA(INDEX([1]Data2!L3:L1002,RANDBETWEEN(1,ROWS([1]Data2!L3:L1002)))), 1, 1) -> #ERROR! | M3: =ARRAY_CONSTRAIN(ARRAYFORMULA(INDEX([1]Data2!M3:M1002,RANDBETWEEN(1,ROWS([1]Data2!M3:M1002)))), 1, 1) -> #ERROR! | N3: =ARRAY_CONSTRAIN(ARRAYFORMULA(INDEX([1]Data2!N3:N1002,RANDBETWEEN(1,ROWS([1]Data2!N3:N1002)))), 1, 1) -> #ERROR! | ... Z3: =ARRAY_CONSTRAIN(ARRAYFORMULA(INDEX([1]Data2!Z3:Z1002,RANDBETWEEN(1,ROWS([1]Data2!Z3:Z1002)))), 1, 1) -> #ERROR! | AA3: =SUM(G3:Z3) -> #ERROR!
A4: 3 | B4: 31 | C4: Male | D4: Hispanic | E4: 1 | F4: =RANDBETWEEN(0,1) -> 1 | G4: =ARRAY_CONSTRAIN(ARRAYFORMULA(INDEX([1]Data2!G4:G1003,RANDBETWEEN(1,ROWS([1]Data2!G4:G1003)))), 1, 1) -> #ERROR! | H4: =ARRAY_CONSTRAIN(ARRAYFORMULA(INDEX([1]Data2!H4:H1003,RANDBETWEEN(1,ROWS([1]Data2!H4:H1003)))), 1, 1) -> #ERROR! | I4: =ARRAY_CONSTRAIN(ARRAYFORMULA(INDEX([1]Data2!I4:I1003,RANDBETWEEN(1,ROWS([1]Data2!I4:I1003)))), 1, 1) -> #ERROR! | J4: =ARRAY_CONSTRAIN(ARRAYFORMULA(INDEX([1]Data2!J4:J1003,RANDBETWEEN(1,ROWS([1]Data2!J4:J1003)))), 1, 1) -> #ERROR! | K4: =ARRAY_CONSTRAIN(ARRAYFORMULA(INDEX([1]Data2!K4:K1003,RANDBETWEEN(1,ROWS([1]Data2!K4:K1003)))), 1, 1) -> #ERROR! | L4: =ARRAY_CONSTRAIN(ARRAYFORMULA(INDEX([1]Data2!L4:L1003,RANDBETWEEN(1,ROWS([1]Data2!L4:L1003)))), 1, 1) -> #ERROR! | M4: =ARRAY_CONSTRAIN(ARRAYFORMULA(INDEX([1]Data2!M4:M1003,RANDBETWEEN(1,ROWS([1]Data2!M4:M1003)))), 1, 1) -> #ERROR! | N4: =ARRAY_CONSTRAIN(ARRAYFORMULA(INDEX([1]Data2!N4:N1003,RANDBETWEEN(1,ROWS([1]Data2!N4:N1003)))), 1, 1) -> #ERROR! | ... Z4: =ARRAY_CONSTRAIN(ARRAYFORMULA(INDEX([1]Data2!Z4:Z1003,RANDBETWEEN(1,ROWS([1]Data2!Z4:Z1003)))), 1, 1) -> #ERROR! | AA4: =SUM(G4:Z4) -> #ERROR!
A5: 4 | B5: 28 | C5: Male | D5: Black | E5: 1 | F5: =RANDBETWEEN(0,1) -> 0 | G5: =ARRAY_CONSTRAIN(ARRAYFORMULA(INDEX([1]Data2!G5:G1004,RANDBETWEEN(1,ROWS([1]Data2!G5:G1004)))), 1, 1) -> #ERROR! | H5: =ARRAY_CONSTRAIN(ARRAYFORMULA(INDEX([1]Data2!H5:H1004,RANDBETWEEN(1,ROWS([1]Data2!H5:H1004)))), 1, 1) -> #ERROR! | I5: =ARRAY_CONSTRAIN(ARRAYFORMULA(INDEX([1]Data2!I5:I1004,RANDBETWEEN(1,ROWS([1]Data2!I5:I1004)))), 1, 1) -> #ERROR! | J5: =ARRAY_CONSTRAIN(ARRAYFORMULA(INDEX([1]Data2!J5:J1004,RANDBETWEEN(1,ROWS([1]Data2!J5:J1004)))), 1, 1) -> #ERROR! | K5: =ARRAY_CONSTRAIN(ARRAYFORMULA(INDEX([1]Data2!K5:K1004,RANDBETWEEN(1,ROWS([1]Data2!K5:K1004)))), 1, 1) -> #ERROR! | L5: =ARRAY_CONSTRAIN(ARRAYFORMULA(INDEX([1]Data2!L5:L1004,RANDBETWEEN(1,ROWS([1]Data2!L5:L1004)))), 1, 1) -> #ERROR! | M5: =ARRAY_CONSTRAIN(ARRAYFORMULA(INDEX([1]Data2!M5:M1004,RANDBETWEEN(1,ROWS([1]Data2!M5:M1004)))), 1, 1) -> #ERROR! | N5: =ARRAY_CONSTRAIN(ARRAYFORMULA(INDEX([1]Data2!N5:N1004,RANDBETWEEN(1,ROWS([1]Data2!N5:N1004)))), 1, 1) -> #ERROR! | ... Z5: =ARRAY_CONSTRAIN(ARRAYFORMULA(INDEX([1]Data2!Z5:Z1004,RANDBETWEEN(1,ROWS([1]Data2!Z5:Z1004)))), 1, 1) -> #ERROR! | AA5: =SUM(G5:Z5) -> #ERROR!
A6: 5 | B6: 29 | C6: Male | D6: White | E6: 0 | F6: =RANDBETWEEN(0,1) -> 1 | G6: =ARRAY_CONSTRAIN(ARRAYFORMULA(INDEX([1]Data2!G6:G1005,RANDBETWEEN(1,ROWS([1]Data2!G6:G1005)))), 1, 1) -> #ERROR! | H6: =ARRAY_CONSTRAIN(ARRAYFORMULA(INDEX([1]Data2!H6:H1005,RANDBETWEEN(1,ROWS([1]Data2!H6:H1005)))), 1, 1) -> #ERROR! | I6: =ARRAY_CONSTRAIN(ARRAYFORMULA(INDEX([1]Data2!I6:I1005,RANDBETWEEN(1,ROWS([1]Data2!I6:I1005)))), 1, 1) -> #ERROR! | J6: =ARRAY_CONSTRAIN(ARRAYFORMULA(INDEX([1]Data2!J6:J1005,RANDBETWEEN(1,ROWS([1]Data2!J6:J1005)))), 1, 1) -> #ERROR! | K6: =ARRAY_CONSTRAIN(ARRAYFORMULA(INDEX([1]Data2!K6:K1005,RANDBETWEEN(1,ROWS([1]Data2!K6:K1005)))), 1, 1) -> #ERROR! | L6: =ARRAY_CONSTRAIN(ARRAYFORMULA(INDEX([1]Data2!L6:L1005,RANDBETWEEN(1,ROWS([1]Data2!L6:L1005)))), 1, 1) -> #ERROR! | M6: =ARRAY_CONSTRAIN(ARRAYFORMULA(INDEX([1]Data2!M6:M1005,RANDBETWEEN(1,ROWS([1]Data2!M6:M1005)))), 1, 1) -> #ERROR! | N6: =ARRAY_CONSTRAIN(ARRAYFORMULA(INDEX([1]Data2!N6:N1005,RANDBETWEEN(1,ROWS([1]Data2!N6:N1005)))), 1, 1) -> #ERROR! | ... Z6: =ARRAY_CONSTRAIN(ARRAYFORMULA(INDEX([1]Data2!Z6:Z1005,RANDBETWEEN(1,ROWS([1]Data2!Z6:Z1005)))), 1, 1) -> #ERROR! | AA6: =SUM(G6:Z6) -> #ERROR!
A7: 6 | B7: 50 | C7: Female | D7: Black | E7: 1 | F7: =RANDBETWEEN(0,1) -> 0 | G7: =ARRAY_CONSTRAIN(ARRAYFORMULA(INDEX([1]Data2!G7:G1006,RANDBETWEEN(1,ROWS([1]Data2!G7:G1006)))), 1, 1) -> #ERROR! | H7: =ARRAY_CONSTRAIN(ARRAYFORMULA(INDEX([1]Data2!H7:H1006,RANDBETWEEN(1,ROWS([1]Data2!H7:H1006)))), 1, 1) -> #ERROR! | I7: =ARRAY_CONSTRAIN(ARRAYFORMULA(INDEX([1]Data2!I7:I1006,RANDBETWEEN(1,ROWS([1]Data2!I7:I1006)))), 1, 1) -> #ERROR! | J7: =ARRAY_CONSTRAIN(ARRAYFORMULA(INDEX([1]Data2!J7:J1006,RANDBETWEEN(1,ROWS([1]Data2!J7:J1006)))), 1, 1) -> #ERROR! | K7: =ARRAY_CONSTRAIN(ARRAYFORMULA(INDEX([1]Data2!K7:K1006,RANDBETWEEN(1,ROWS([1]Data2!K7:K1006)))), 1, 1) -> #ERROR! | L7: =ARRAY_CONSTRAIN(ARRAYFORMULA(INDEX([1]Data2!L7:L1006,RANDBETWEEN(1,ROWS([1]Data2!L7:L1006)))), 1, 1) -> #ERROR! | M7: =ARRAY_CONSTRAIN(ARRAYFORMULA(INDEX([1]Data2!M7:M1006,RANDBETWEEN(1,ROWS([1]Data2!M7:M1006)))), 1, 1) -> #ERROR! | N7: =ARRAY_CONSTRAIN(ARRAYFORMULA(INDEX([1]Data2!N7:N1006,RANDBETWEEN(1,ROWS([1]Data2!N7:N1006)))), 1, 1) -> #ERROR! | ... Z7: =ARRAY_CONSTRAIN(ARRAYFORMULA(INDEX([1]Data2!Z7:Z1006,RANDBETWEEN(1,ROWS([1]Data2!Z7:Z1006)))), 1, 1) -> #ERROR! | AA7: =SUM(G7:Z7) -> #ERROR!
A8: 7 | B8: 31 | C8: Female | D8: White | E8: 0 | F8: =RANDBETWEEN(0,1) -> 0 | G8: =ARRAY_CONSTRAIN(ARRAYFORMULA(INDEX([1]Data2!G8:G1007,RANDBETWEEN(1,ROWS([1]Data2!G8:G1007)))), 1, 1) -> #ERROR! | H8: =ARRAY_CONSTRAIN(ARRAYFORMULA(INDEX([1]Data2!H8:H1007,RANDBETWEEN(1,ROWS([1]Data2!H8:H1007)))), 1, 1) -> #ERROR! | I8: =ARRAY_CONSTRAIN(ARRAYFORMULA(INDEX([1]Data2!I8:I1007,RANDBETWEEN(1,ROWS([1]Data2!I8:I1007)))), 1, 1) -> #ERROR! | J8: =ARRAY_CONSTRAIN(ARRAYFORMULA(INDEX([1]Data2!J8:J1007,RANDBETWEEN(1,ROWS([1]Data2!J8:J1007)))), 1, 1) -> #ERROR! | K8: =ARRAY_CONSTRAIN(ARRAYFORMULA(INDEX([1]Data2!K8:K1007,RANDBETWEEN(1,ROWS([1]Data2!K8:K1007)))), 1, 1) -> #ERROR! | L8: =ARRAY_CONSTRAIN(ARRAYFORMULA(INDEX([1]Data2!L8:L1007,RANDBETWEEN(1,ROWS([1]Data2!L8:L1007)))), 1, 1) -> #ERROR! | M8: =ARRAY_CONSTRAIN(ARRAYFORMULA(INDEX([1]Data2!M8:M1007,RANDBETWEEN(1,ROWS([1]Data2!M8:M1007)))), 1, 1) -> #ERROR! | N8: =ARRAY_CONSTRAIN(ARRAYFORMULA(INDEX([1]Data2!N8:N1007,RANDBETWEEN(1,ROWS([1]Data2!N8:N1007)))), 1, 1) -> #ERROR! | ... Z8: =ARRAY_CONSTRAIN(ARRAYFORMULA(INDEX([1]Data2!Z8:Z1007,RANDBETWEEN(1,ROWS([1]Data2!Z8:Z1007)))), 1, 1) -> #ERROR! | AA8: =SUM(G8:Z8) -> #ERROR!
A9: 8 | B9: 24 | C9: Female | D9: Black | E9: 1 | F9: =RANDBETWEEN(0,1) -> 0 | G9: =ARRAY_CONSTRAIN(ARRAYFORMULA(INDEX([1]Data2!G9:G1008,RANDBETWEEN(1,ROWS([1]Data2!G9:G1008)))), 1, 1) -> #ERROR! | H9: =ARRAY_CONSTRAIN(ARRAYFORMULA(INDEX([1]Data2!H9:H1008,RANDBETWEEN(1,ROWS([1]Data2!H9:H1008)))), 1, 1) -> #ERROR! | I9: =ARRAY_CONSTRAIN(ARRAYFORMULA(INDEX([1]Data2!I9:I1008,RANDBETWEEN(1,ROWS([1]Data2!I9:I1008)))), 1, 1) -> #ERROR! | J9: =ARRAY_CONSTRAIN(ARRAYFORMULA(INDEX([1]Data2!J9:J1008,RANDBETWEEN(1,ROWS([1]Data2!J9:J1008)))), 1, 1) -> #ERROR! | K9: =ARRAY_CONSTRAIN(ARRAYFORMULA(INDEX([1]Data2!K9:K1008,RANDBETWEEN(1,ROWS([1]Data2!K9:K1008)))), 1, 1) -> #ERROR! | L9: =ARRAY_CONSTRAIN(ARRAYFORMULA(INDEX([1]Data2!L9:L1008,RANDBETWEEN(1,ROWS([1]Data2!L9:L1008)))), 1, 1) -> #ERROR! | M9: =ARRAY_CONSTRAIN(ARRAYFORMULA(INDEX([1]Data2!M9:M1008,RANDBETWEEN(1,ROWS([1]Data2!M9:M1008)))), 1, 1) -> #ERROR! | N9: =ARRAY_CONSTRAIN(ARRAYFORMULA(INDEX([1]Data2!N9:N1008,RANDBETWEEN(1,ROWS([1]Data2!N9:N1008)))), 1, 1) -> #ERROR! | ... Z9: =ARRAY_CONSTRAIN(ARRAYFORMULA(INDEX([1]Data2!Z9:Z1008,RANDBETWEEN(1,ROWS([1]Data2!Z9:Z1008)))), 1, 1) -> #ERROR! | AA9: =SUM(G9:Z9) -> #ERROR!
A10: 9 | B10: 32 | C10: Female | D10: Black | E10: 1 | F10: =RANDBETWEEN(0,1) -> 1 | G10: =ARRAY_CONSTRAIN(ARRAYFORMULA(INDEX([1]Data2!G10:G1009,RANDBETWEEN(1,ROWS([1]Data2!G10:G1009)))), 1, 1) -> #ERROR! | H10: =ARRAY_CONSTRAIN(ARRAYFORMULA(INDEX([1]Data2!H10:H1009,RANDBETWEEN(1,ROWS([1]Data2!H10:H1009)))), 1, 1) -> #ERROR! | I10: =ARRAY_CONSTRAIN(ARRAYFORMULA(INDEX([1]Data2!I10:I1009,RANDBETWEEN(1,ROWS([1]Data2!I10:I1009)))), 1, 1) -> #ERROR! | J10: =ARRAY_CONSTRAIN(ARRAYFORMULA(INDEX([1]Data2!J10:J1009,RANDBETWEEN(1,ROWS([1]Data2!J10:J1009)))), 1, 1) -> #ERROR! | K10: =ARRAY_CONSTRAIN(ARRAYFORMULA(INDEX([1]Data2!K10:K1009,RANDBETWEEN(1,ROWS([1]Data2!K10:K1009)))), 1, 1) -> #ERROR! | L10: =ARRAY_CONSTRAIN(ARRAYFORMULA(INDEX([1]Data2!L10:L1009,RANDBETWEEN(1,ROWS([1]Data2!L10:L1009)))), 1, 1) -> #ERROR! | M10: =ARRAY_CONSTRAIN(ARRAYFORMULA(INDEX([1]Data2!M10:M1009,RANDBETWEEN(1,ROWS([1]Data2!M10:M1009)))), 1, 1) -> #ERROR! | N10: =ARRAY_CONSTRAIN(ARRAYFORMULA(INDEX([1]Data2!N10:N1009,RANDBETWEEN(1,ROWS([1]Data2!N10:N1009)))), 1, 1) -> #ERROR! | ... Z10: =ARRAY_CONSTRAIN(ARRAYFORMULA(INDEX([1]Data2!Z10:Z1009,RANDBETWEEN(1,ROWS([1]Data2!Z10:Z1009)))), 1, 1) -> #ERROR! | AA10: =SUM(G10:Z10) -> #ERROR!
A11: 10 | B11: 33 | C11: Female | D11: White | E11: 0 | F11: =RANDBETWEEN(0,1) -> 1 | G11: =ARRAY_CONSTRAIN(ARRAYFORMULA(INDEX([1]Data2!G11:G1010,RANDBETWEEN(1,ROWS([1]Data2!G11:G1010)))), 1, 1) -> #ERROR! | H11: =ARRAY_CONSTRAIN(ARRAYFORMULA(INDEX([1]Data2!H11:H1010,RANDBETWEEN(1,ROWS([1]Data2!H11:H1010)))), 1, 1) -> #ERROR! | I11: =ARRAY_CONSTRAIN(ARRAYFORMULA(INDEX([1]Data2!I11:I1010,RANDBETWEEN(1,ROWS([1]Data2!I11:I1010)))), 1, 1) -> #ERROR! | J11: =ARRAY_CONSTRAIN(ARRAYFORMULA(INDEX([1]Data2!J11:J1010,RANDBETWEEN(1,ROWS([1]Data2!J11:J1010)))), 1, 1) -> #ERROR! | K11: =ARRAY_CONSTRAIN(ARRAYFORMULA(INDEX([1]Data2!K11:K1010,RANDBETWEEN(1,ROWS([1]Data2!K11:K1010)))), 1, 1) -> #ERROR! | L11: =ARRAY_CONSTRAIN(ARRAYFORMULA(INDEX([1]Data2!L11:L1010,RANDBETWEEN(1,ROWS([1]Data2!L11:L1010)))), 1, 1) -> #ERROR! | M11: =ARRAY_CONSTRAIN(ARRAYFORMULA(INDEX([1]Data2!M11:M1010,RANDBETWEEN(1,ROWS([1]Data2!M11:M1010)))), 1, 1) -> #ERROR! | N11: =ARRAY_CONSTRAIN(ARRAYFORMULA(INDEX([1]Data2!N11:N1010,RANDBETWEEN(1,ROWS([1]Data2!N11:N1010)))), 1, 1) -> #ERROR! | ... Z11: =ARRAY_CONSTRAIN(ARRAYFORMULA(INDEX([1]Data2!Z11:Z1010,RANDBETWEEN(1,ROWS([1]Data2!Z11:Z1010)))), 1, 1) -> #ERROR! | AA11: =SUM(G11:Z11) -> #ERROR!
A12: 11 | B12: 46 | C12: Female | D12: White | E12: 0 | F12: =RANDBETWEEN(0,1) -> 0 | G12: =ARRAY_CONSTRAIN(ARRAYFORMULA(INDEX([1]Data2!G12:G1011,RANDBETWEEN(1,ROWS([1]Data2!G12:G1011)))), 1, 1) -> #ERROR! | H12: =ARRAY_CONSTRAIN(ARRAYFORMULA(INDEX([1]Data2!H12:H1011,RANDBETWEEN(1,ROWS([1]Data2!H12:H1011)))), 1, 1) -> #ERROR! | I12: =ARRAY_CONSTRAIN(ARRAYFORMULA(INDEX([1]Data2!I12:I1011,RANDBETWEEN(1,ROWS([1]Data2!I12:I1011)))), 1, 1) -> #ERROR! | J12: =ARRAY_CONSTRAIN(ARRAYFORMULA(INDEX([1]Data2!J12:J1011,RANDBETWEEN(1,ROWS([1]Data2!J12:J1011)))), 1, 1) -> #ERROR! | K12: =ARRAY_CONSTRAIN(ARRAYFORMULA(INDEX([1]Data2!K12:K1011,RANDBETWEEN(1,ROWS([1]Data2!K12:K1011)))), 1, 1) -> #ERROR! | L12: =ARRAY_CONSTRAIN(ARRAYFORMULA(INDEX([1]Data2!L12:L1011,RANDBETWEEN(1,ROWS([1]Data2!L12:L1011)))), 1, 1) -> #ERROR! | M12: =ARRAY_CONSTRAIN(ARRAYFORMULA(INDEX([1]Data2!M12:M1011,RANDBETWEEN(1,ROWS([1]Data2!M12:M1011)))), 1, 1) -> #ERROR! | N12: =ARRAY_CONSTRAIN(ARRAYFORMULA(INDEX([1]Data2!N12:N1011,RANDBETWEEN(1,ROWS([1]Data2!N12:N1011)))), 1, 1) -> #ERROR! | ... Z12: =ARRAY_CONSTRAIN(ARRAYFORMULA(INDEX([1]Data2!Z12:Z1011,RANDBETWEEN(1,ROWS([1]Data2!Z12:Z1011)))), 1, 1) -> #ERROR! | AA12: =SUM(G12:Z12) -> #ERROR!
A13: 12 | B13: 39 | C13: Female | D13: White | E13: 0 | F13: =RANDBETWEEN(0,1) -> 1 | G13: =ARRAY_CONSTRAIN(ARRAYFORMULA(INDEX([1]Data2!G13:G1012,RANDBETWEEN(1,ROWS([1]Data2!G13:G1012)))), 1, 1) -> #ERROR! | H13: =ARRAY_CONSTRAIN(ARRAYFORMULA(INDEX([1]Data2!H13:H1012,RANDBETWEEN(1,ROWS([1]Data2!H13:H1012)))), 1, 1) -> #ERROR! | I13: =ARRAY_CONSTRAIN(ARRAYFORMULA(INDEX([1]Data2!I13:I1012,RANDBETWEEN(1,ROWS([1]Data2!I13:I1012)))), 1, 1) -> #ERROR! | J13: =ARRAY_CONSTRAIN(ARRAYFORMULA(INDEX([1]Data2!J13:J1012,RANDBETWEEN(1,ROWS([1]Data2!J13:J1012)))), 1, 1) -> #ERROR! | K13: =ARRAY_CONSTRAIN(ARRAYFORMULA(INDEX([1]Data2!K13:K1012,RANDBETWEEN(1,ROWS([1]Data2!K13:K1012)))), 1, 1) -> #ERROR! | L13: =ARRAY_CONSTRAIN(ARRAYFORMULA(INDEX([1]Data2!L13:L1012,RANDBETWEEN(1,ROWS([1]Data2!L13:L1012)))), 1, 1) -> #ERROR! | M13: =ARRAY_CONSTRAIN(ARRAYFORMULA(INDEX([1]Data2!M13:M1012,RANDBETWEEN(1,ROWS([1]Data2!M13:M1012)))), 1, 1) -> #ERROR! | N13: =ARRAY_CONSTRAIN(ARRAYFORMULA(INDEX([1]Data2!N13:N1012,RANDBETWEEN(1,ROWS([1]Data2!N13:N1012)))), 1, 1) -> #ERROR! | ... Z13: =ARRAY_CONSTRAIN(ARRAYFORMULA(INDEX([1]Data2!Z13:Z1012,RANDBETWEEN(1,ROWS([1]Data2!Z13:Z1012)))), 1, 1) -> #ERROR! | AA13: =SUM(G13:Z13) -> #ERROR!
... A1001: 1000 | B1001: 30 | C1001: Female | D1001: Black | E1001: 1 | F1001: =RANDBETWEEN(0,1) -> 0 | G1001: =ARRAY_CONSTRAIN(ARRAYFORMULA(INDEX([1]Data2!G1001:G2000,RANDBETWEEN(1,ROWS([1]Data2!G1001:G2000)))), 1, 1) -> #ERROR! | H1001: =ARRAY_CONSTRAIN(ARRAYFORMULA(INDEX([1]Data2!H1001:H2000,RANDBETWEEN(1,ROWS([1]Data2!H1001:H2000)))), 1, 1) -> #ERROR! | I1001: =ARRAY_CONSTRAIN(ARRAYFORMULA(INDEX([1]Data2!I1001:I2000,RANDBETWEEN(1,ROWS([1]Data2!I1001:I2000)))), 1, 1) -> #ERROR! | J1001: =ARRAY_CONSTRAIN(ARRAYFORMULA(INDEX([1]Data2!J1001:J2000,RANDBETWEEN(1,ROWS([1]Data2!J1001:J2000)))), 1, 1) -> #ERROR! | K1001: =ARRAY_CONSTRAIN(ARRAYFORMULA(INDEX([1]Data2!K1001:K2000,RANDBETWEEN(1,ROWS([1]Data2!K1001:K2000)))), 1, 1) -> #ERROR! | L1001: =ARRAY_CONSTRAIN(ARRAYFORMULA(INDEX([1]Data2!L1001:L2000,RANDBETWEEN(1,ROWS([1]Data2!L1001:L2000)))), 1, 1) -> #ERROR! | M1001: =ARRAY_CONSTRAIN(ARRAYFORMULA(INDEX([1]Data2!M1001:M2000,RANDBETWEEN(1,ROWS([1]Data2!M1001:M2000)))), 1, 1) -> #ERROR! | N1001: =ARRAY_CONSTRAIN(ARRAYFORMULA(INDEX([1]Data2!N1001:N2000,RANDBETWEEN(1,ROWS([1]Data2!N1001:N2000)))), 1, 1) -> #ERROR! | ... Z1001: =ARRAY_CONSTRAIN(ARRAYFORMULA(INDEX([1]Data2!Z1001:Z2000,RANDBETWEEN(1,ROWS([1]Data2!Z1001:Z2000)))), 1, 1) -> #ERROR! | AA1001: =SUM(G1001:Z1001) -> #ERROR!

Sheet ArtificalDataCopy
A1: id | B1: age | C1: sex | D1: race | E1: BME | F1: Educ | G1: qu1 | H1: qu2 | I1: qu3 | J1: qu4 | K1: qu5 | L1: qu6 | M1: qu7 | N1: qu8 | O1: qu9 | P1: qu10 | Q1: qu11 | R1: qu12 | S1: qu13 | T1: qu14 | U1: qu15 | V1: qu16 | W1: qu17 | X1: qu18 | Y1: qu19 | Z1: qu20 | AA1: TotalScore
A2: 1 | B2: 49 | C2: Male | D2: White | E2: 0 | F2: 0 | G2: 3 | H2: 2 | I2: 2 | J2: 3 | K2: 4 | L2: 2 | M2: 3 | N2: 3 | O2: 4 | P2: 2 | Q2: 3 | R2: 2 | S2: 3 | T2: 3 | U2: 3 | V2: 2 | W2: 4 | X2: 4 | Y2: 3 | Z2: 2 | AA2: 57
A3: 2 | B3: 52 | C3: Female | D3: White | E3: 0 | F3: 1 | G3: 5 | H3: 2 | I3: 3 | J3: 3 | K3: 3 | L3: 2 | M3: 3 | N3: 1 | O3: 4 | P3: 4 | Q3: 4 | R3: 3 | S3: 4 | T3: 4 | U3: 3 | V3: 3 | W3: 4 | X3: 4 | Y3: 2 | Z3: 2 | AA3: 63
A4: 3 | B4: 31 | C4: Male | D4: Hispanic | E4: 1 | F4: 0 | G4: 2 | H4: 3 | I4: 3 | J4: 4 | K4: 4 | L4: 2 | M4: 1 | N4: 2 | O4: 3 | P4: 3 | Q4: 3 | R4: 3 | S4: 3 | T4: 2 | U4: 2 | V4: 2 | W4: 3 | X4: 3 | Y4: 3 | Z4: 2 | AA4: 53
A5: 4 | B5: 28 | C5: Male | D5: Black | E5: 1 | F5: 0 | G5: 5 | H5: 3 | I5: 3 | J5: 2 | K5: 4 | L5: 4 | M5: 2 | N5: 3 | O5: 2 | P5: 2 | Q5: 3 | R5: 4 | S5: 3 | T5: 3 | U5: 4 | V5: 3 | W5: 4 | X5: 3 | Y5: 3 | Z5: 1 | AA5: 61
A6: 5 | B6: 29 | C6: Male | D6: White | E6: 0 | F6: 0 | G6: 4 | H6: 2 | I6: 3 | J6: 3 | K6: 3 | L6: 3 | M6: 2 | N6: 3 | O6: 4 | P6: 2 | Q6: 3 | R6: 3 | S6: 4 | T6: 2 | U6: 4 | V6: 2 | W6: 3 | X6: 3 | Y6: 3 | Z6: 2 | AA6: 58
A7: 6 | B7: 50 | C7: Female | D7: Black | E7: 1 | F7: 0 | G7: 2 | H7: 2 | I7: 1 | J7: 2 | K7: 3 | L7: 5 | M7: 3 | N7: 3 | O7: 2 | P7: 3 | Q7: 3 | R7: 4 | S7: 4 | T7: 2 | U7: 3 | V7: 3 | W7: 3 | X7: 2 | Y7: 3 | Z7: 3 | AA7: 56
A8: 7 | B8: 31 | C8: Female | D8: White | E8: 0 | F8: 1 | G8: 1 | H8: 3 | I8: 3 | J8: 2 | K8: 3 | L8: 1 | M8: 3 | N8: 3 | O8: 4 | P8: 3 | Q8: 1 | R8: 3 | S8: 3 | T8: 2 | U8: 4 | V8: 3 | W8: 3 | X8: 1 | Y8: 5 | Z8: 3 | AA8: 54
A9: 8 | B9: 24 | C9: Female | D9: Black | E9: 1 | F9: 1 | G9: 3 | H9: 2 | I9: 3 | J9: 3 | K9: 3 | L9: 3 | M9: 3 | N9: 5 | O9: 3 | P9: 3 | Q9: 3 | R9: 3 | S9: 4 | T9: 3 | U9: 3 | V9: 4 | W9: 3 | X9: 3 | Y9: 2 | Z9: 1 | AA9: 60
A10: 9 | B10: 32 | C10: Female | D10: Black | E10: 1 | F10: 1 | G10: 3 | H10: 3 | I10: 3 | J10: 1 | K10: 2 | L10: 3 | M10: 2 | N10: 3 | O10: 4 | P10: 3 | Q10: 2 | R10: 4 | S10: 3 | T10: 3 | U10: 3 | V10: 3 | W10: 4 | X10: 3 | Y10: 2 | Z10: 3 | AA10: 57
A11: 10 | B11: 33 | C11: Female | D11: White | E11: 0 | F11: 0 | G11: 2 | H11: 2 | I11: 3 | J11: 0 | K11: 2 | L11: 3 | M11: 4 | N11: 3 | O11: 3 | P11: 4 | Q11: 4 | R11: 3 | S11: 3 | T11: 3 | U11: 3 | V11: 3 | W11: 5 | X11: 3 | Y11: 4 | Z11: 2 | AA11: 59
A12: 11 | B12: 46 | C12: Female | D12: White | E12: 0 | F12: 0 | G12: 2 | H12: 3 | I12: 2 | J12: 4 | K12: 3 | L12: 2 | M12: 4 | N12: 2 | O12: 3 | P12: 2 | Q12: 3 | R12: 4 | S12: 3 | T12: 2 | U12: 3 | V12: 4 | W12: 2 | X12: 3 | Y12: 1 | Z12: 3 | AA12: 55
A13: 12 | B13: 39 | C13: Female | D13: White | E13: 0 | F13: 1 | G13: 3 | H13: 3 | I13: 3 | J13: 0 | K13: 3 | L13: 3 | M13: 3 | N13: 3 | O13: 3 | P13: 5 | Q13: 3 | R13: 3 | S13: 2 | T13: 2 | U13: 4 | V13: 3 | W13: 4 | X13: 3 | Y13: 4 | Z13: 1 | AA13: 58
... A1001: 1000 | B1001: 30 | C1001: Female | D1001: Black | E1001: 1 | F1001: 0 | G1001: 0 | H1001: 0 | I1001: 0 | J1001: 0 | K1001: 0 | L1001: 0 | M1001: 0 | N1001: 0 | O1001: 0 | P1001: 0 | Q1001: 0 | R1001: 0 | S1001: 0 | T1001: 0 | U1001: 0 | V1001: 0 | W1001: 0 | X1001: 0 | Y1001: 0 | Z1001: 0 | AA1001: 0

Sheet TestData1
A1: id | B1: age | C1: sex | D1: race | E1: qu1 | F1: qu2 | G1: qu3 | H1: qu4 | I1: qu5 | J1: qu6 | K1: qu7 | L1: qu8 | M1: qu9 | N1: qu10 | O1: qu11 | P1: qu12 | Q1: qu13 | R1: qu14 | S1: qu15 | T1: qu16 | U1: qu17 | V1: qu18 | W1: qu19 | X1: qu20 | Y1: TotalScore
A2: 1 | B2: 49 | C2: Male | D2: White | E2: 3 | F2: 3 | G2: 3 | H2: 3 | I2: 3 | J2: 3 | K2: 3 | L2: 3 | M2: 3 | N2: 2 | O2: 3 | P2: 3 | Q2: 3 | R2: 2 | S2: 2 | T2: 3 | U2: 3 | V2: 2 | W2: 3 | X2: 1 | Y2: 54
A3: 2 | B3: 52 | C3: Female | D3: White | E3: 3 | F3: 2 | G3: 3 | H3: 3 | I3: 2 | J3: 2 | K3: 2 | L3: 3 | M3: 3 | N3: 3 | O3: 3 | P3: 3 | Q3: 3 | R3: 3 | S3: 3 | T3: 3 | U3: 3 | V3: 3 | W3: 3 | X3: 2 | Y3: 55
A4: 3 | B4: 31 | C4: Male | D4: Hispanic | E4: 3 | F4: 2 | G4: 2 | H4: 3 | I4: 2 | J4: 2 | K4: 3 | L4: 2 | M4: 3 | N4: 2 | O4: 4 | P4: 4 | Q4: 3 | R4: 4 | S4: 3 | T4: 3 | U4: 3 | V4: 4 | W4: 4 | X4: 2 | Y4: 58
A5: 4 | B5: 28 | C5: Male | D5: Black | E5: 4 | F5: 3 | G5: 3 | H5: 3 | I5: 3 | J5: 2 | K5: 3 | L5: 3 | M5: 3 | N5: 3 | O5: 3 | P5: 3 | Q5: 4 | R5: 3 | S5: 3 | T5: 3 | U5: 4 | V5: 3 | W5: 3 | X5: 3 | Y5: 62
A6: 5 | B6: 29 | C6: Male | D6: White | E6: 4 | F6: 2 | G6: 4 | H6: 4 | I6: 3 | J6: 4 | K6: 4 | L6: 4 | M6: 4 | N6: 4 | O6: 3 | P6: 3 | Q6: 3 | R6: 1 | S6: 2 | T6: 3 | U6: 3 | V6: 3 | W6: 3 | X6: 1 | Y6: 62
A7: 6 | B7: 50 | C7: Female | D7: Black | E7: 3 | F7: 2 | G7: 3 | H7: 2 | I7: 2 | J7: 2 | K7: 3 | L7: 3 | M7: 2 | N7: 3 | O7: 3 | P7: 3 | Q7: 3 | R7: 2 | S7: 3 | T7: 3 | U7: 3 | V7: 3 | W7: 3 | X7: 3 | Y7: 54
A8: 7 | B8: 31 | C8: Female | D8: White | E8: 2 | F8: 1 | G8: 2 | H8: 2 | I8: 2 | J8: 2 | K8: 2 | L8: 1 | M8: 2 | N8: 2 | O8: 3 | P8: 4 | Q8: 3 | R8: 2 | S8: 3 | T8: 4 | U8: 3 | V8: 3 | W8: 3 | X8: 3 | Y8: 49
A9: 8 | B9: 24 | C9: Female | D9: Black | E9: 3 | F9: 3 | G9: 3 | H9: 3 | I9: 3 | J9: 4 | K9: 3 | L9: 3 | M9: 3 | N9: 4 | O9: 4 | P9: 3 | Q9: 3 | R9: 3 | S9: 3 | T9: 3 | U9: 4 | V9: 3 | W9: 4 | X9: 2 | Y9: 64
